Workbook

Sheet General
Q1: #VALUE! | AU1: #VALUE!
A3: Folio Interno de Solicitud | B3: Fecha Ingreso de Solicitud | C3: Semaforo | D3: Origen de Recurso | E3: Dependencia | F3: Centro de Costo | G3: Capitulo | H3: Concepto del Gasto | I3: Giro o Partida | J3: Tipo Contracion | K3: Valor del Estudio de Mercado | L3: Estatus del Estudio de Mercado | M3: Estado | N3: Tipo de Solicitud: | O3: Monto SABYS | P3: Descripción del bien o servicio de acuerdo a la solicitud | Q3: Contratacion Plurianual | R3: Monto 2026 | S3: Monto 2027 | T3: Monto 2028 | U3: Monto 2029 | V3: Folio de Solicitud de Adquisición. (CA) | W3: Fecha de Liberación de Estudio de Mercado | X3: Nombre de Testigo Social (N/A,Nombre) | Y3: Tipo de gasto: | Z3: Fuente de financiamiento: | AA3: Importe de Suficiencia Presupuestal | AB3: Oficio de Suficiencia | AC3: Clave de Verificación | AD3: Descripción de la Clave de Verificación | AE3: Unidad de Medida | AF3: ¿Es contrato abierto? | AG3: ¿Es consolidado? | AH3: Modalidad del Procedimiento Adquisitivo | AI3: Dictamen de Procedencia(Pdf) | AJ3: Responsable del Procedimiento | AK3: No. de procedimiento | AL3: Convocatoria y/o Invitacion (URL) | AM3: Medio de Publicación: | AN3: Fecha de Junta de Aclaración: | AO3: Hora de Junta de Aclaración: | AP3: Fecha de Presentación y Apertura de Proposiciones: | AQ3: Hora de Presentación y Apertura de Proposiciones: | AR3: Fecha de Sesión del Comité de Adquisiciones y Servicios para Análisis Cualitativ | AS3: Hora de Sesión del Comité de Adquisiciones y Servicios para Análisis Cualitativo | AT3: Fecha de Contra Oferta: | AU3: Hora de Contra Oferta: | AV3: Fecha de Dictaminación de Adjudicación del Comité: | AW3: Hora de de Dictaminación de Adjudicación del Comité: | AX3: Fecha de Fallo: | AY3: Hora de Fallo: | AZ3: Nombre o Razón Social | BA3: RFC | BB3: Representación Legal | BC3: Cargar Documento (Pdf) | BD3: Monto Total Adjudicación con IVA | BE3: Numero de Contrato: | BF3: Inicio de Vigencia: | BG3: Termino de Vigencia: | BH3: Publicación del Testimonio del Testigo Social: | BI3: REMANENTE(Suf.Presupuestal | BJ3: Nombre del Responsable del Procedimiento | BK3: Comentarios | BL3: Estatus | BM3: Columna1
A4: F-0001-2026 | B4: 46063 | C4: Concluido | D4: Federal | E4: Secretaría de la Contraloría | F4: Coordinación Administrativa (21800005000000S) | G4: 3000 Servicios generales | H4: 3400 – Servicios Financieros, Bancarios y Comerciales | I4: 3451 Seguros y fianzas | J4: LPNP | K4: 1,234,097.32 | L4: Concluido | M4: Adjudicado | N4: Servicio- Contratacion de servicios generales | O4: 1234097.3 | P4: ASEGURAMIENTO VEHICULAR | Q4: NO | V4: F-SC-001-2026 | W4: 46076 | X4: N/A | Y4: GC-Gasto Corriente | Z4: 15000000 - Recursos federales | AA4: 1234097.32 | AB4: https://gobedomex-my.sharepoint.com/my?id=%2Fpersonal%2Fcoordtic%5Fom%5Fedomex%5Fgob%5Fmx%2FDocuments%2FDGRM%20Archivos%2F1%2FDICTAMEN%20DE%20PROCEDENCIA%20ADP%2D001%2D202618%2D02%2D2026%2D165332%2Epdf&parent=%2Fpersonal%2Fcoordtic%5Fom%5Fedomex%5Fgob%5Fmx%2FDocuments%2FDGRM%20Archivos%2F1&ga=1 | AC4: 34501-0010 | AD4: ASEGURAMIENTO VEHICULAR | AE4: SERVICIO | AF4: No | AG4: No | AH4: Adjudicación Directa electrónica | AK4: AA-74-058-915002994-N-1-2026 | AL4: https://comprasmx.buengobierno.gob.mx/contrataciones/#/procedimientos/detalle-ad-sc/4c614d2c-2a7b-68db-e063-a61200a9409b | AM4: Electrónico - COMPRAMEX | AP4: 46087 | AQ4: 0.45833333 | AX4: 46087 | AY4: 0.54166667 | AZ4: Quálitas Compañía de Seguros, S.A. de C.V. | BA4: QCS931209G49 | BD4: 1195384 | BE4: CASF/001/2026 | BF4: 46087 | BG4: 46387 | BH4: N/A | BI4: 38713.33 | BJ4: Dirección de Procedimientos Adquisitivos "B" | BL4: Adjudicado | BM4: 1
A5: F-0002-2026 | B5: 46106 | C5: Concluido | D5: Federal | E5: Secretaría de la Contraloría | F5: Coordinación Administrativa (21800005000000S) | G5: 2000 Materiales y Suministros | H5: 2600-COMBUSTIBLES, LUBRICANTES Y ADITIVOS. | I5: 2341 Combustibles, lubricantes, aditivos, carbón y derivados | J5: LPNP | K5: 3900000 | L5: Concluido | M5: Adjudicado | N5: Servicio- Contratacion de servicios generales | O5: 3900000 | P5: SUMINISTRO DE COMBUSTIBLE MEDIANTE MONEDEROS ELECTRÓNICOS EN LA MODALIDAD DE CONTRATO ABIERTO | Q5: NO | V5: F-SC-002-2026 | W5: 46105 | X5: N/A | Y5: GC-Gasto Corriente | Z5: ["15000000 - Recursos federales"] | AA5: 3900000 | AB5: https://gobedomex-my.sharepoint.com/personal/coordtic_om_edomex_gob_mx/Documents/Aplicaciones/Microsoft%20Forms/Sistema%20de%20Seguimiento%20(2)%201/N%C3%BAmero%20de%20Oficio%20de%20liberaci%C3%B3n%20de%20recursos/CERTIFICACI%C3%93N%20-%20MONEDEROS%20ELECTR%C3%93NICOS_ARTURO%20GOMEZ%20GALICIA.pdf | AC5: 33602-0008 | AD5: OTROS SERVICIOS COMERCIALES | AE5: SERVICIO | AF5: Si | AG5: No | AH5: Invitación Restringida electrónica | AK5: IA-74-058-915002994-N-2-2026 | AL5: https://comprasmx.buengobierno.gob.mx/sitiopublico/#/ | AM5: Electrónico - COMPRAMEX | AP5: 46128 | AQ5: 0.41666667 | AX5: 46129 | AY5: 0.70833333 | AZ5: EFECTIVALE, S. DE R.L. DE C.V. | BA5: EFE8908015L3 | BD5: 3900000 | BE5: CASF/002/2026 | BF5: 46129 | BG5: 46387 | BH5: N/A | BI5: 0 | BJ5: Dirección de Procedimientos Adquisitivos "B" | BL5: Adjudicado | BM5: 2
A6: F-0003-2026 | B6: 46149 | C6: Atrasado | D6: Federal | E6: Secretaría de la Contraloría | F6: Coordinación Administrativa (21800005000000S) | G6: 2000 Materiales y Suministros | H6: 2100 – Materiales de Administración, Emisión de Documentos y Artículos Oficiales | I6: 2111 Materiales y útiles de oficina | J6: CP | L6: En Proceso | M6: En Proceso | N6: Bien- Adquisición de materiales y suministros | O6: 100280 | P6: ADQUISICIÓN DE PAPEL BOND TAMAÑO CARTA | Q6: NO | BM6: 23
A7: F-0004-2026 | B7: 46149 | C7: Atrasado | D7: Federal | E7: Secretaría de la Contraloría | F7: Coordinación Administrativa (21800005000000S) | G7: 2000 Materiales y Suministros | H7: 2300 – Materias Primas y Materiales de Producción y Comercialización | I7: 2381 Mercancías para su comercialización en tiendas del sector público | J7: CP | L7: En Proceso | M7: En Proceso | N7: Bien- Adquisición de materiales y suministros | O7: 120770 | P7: ADQUISICIÓN DE MATERIALES, BIENES E INSUMOS REQUERIDOS POR EL LABORATORIO DE ANÁLISIS Y VERIFICACIÓN DE CLIDAD DE MATERIALES DE CONSTRUCCIÓN | Q7: NO | BM7: 32
A8: F-0005-2026 | B8: 46149 | C8: Atrasado | D8: Federal | E8: Secretaría de la Contraloría | F8: Coordinación Administrativa (21800005000000S) | G8: 3000 Servicios generales | H8: 3500 – Servicios de Instalación, Reparación, Mantenimiento y Conservación | I8: 3571 Reparación, instalación y mantenimiento de maquinaria, equipo industrial y diverso | J8: CP | L8: En Proceso | M8: En Proceso | N8: Servicio- Contratacion de servicios generales | O8: 80800 | P8: SERVICIO DE CALIBRACIÓN A LOS EQUIPOS ESPECIALIZADOS DEL LABORATORIO DE ANÁLISIS Y VERIFICACIÓN DE CALIDAD DE MATERIALES DE CONSTRUCCIÓN | Q8: NO | BM8: 4
A9: F-0006-2026 | B9: 46149 | C9: Atrasado | D9: Federal | E9: Secretaría de la Contraloría | F9: Coordinación Administrativa (21800005000000S) | G9: 3000 Servicios generales | H9: 3500 – Servicios de Instalación, Reparación, Mantenimiento y Conservación | I9: 3571 Reparación, instalación y mantenimiento de maquinaria, equipo industrial y diverso | J9: CP | L9: En Proceso | M9: En Proceso | N9: Servicio- Contratacion de servicios generales | O9: 178100 | P9: SERVICIO DE MANTENIMIENTO A LOS EQUIPOS ESPECIALIZADOS DEL LABORATORIO DE ANÁLISIS Y VERIFICACIÓN DE CALIDAD DE MATERIALES DE CONSTRUCCIÓN | Q9: NO | BM9: 10
A10: F-0007-2026 | B10: 46150 | C10: Rechazado | D10: Federal | E10: Consejería Jurídica | F10: Coordinación Administrativa (23300001000000S) | G10: 5000 Bienes muebles inmuebles e intangibles | H10: 5600 – Maquinaria, Otros Equipos y Herramientas | I10: 5631 Maquinaria y equipo de construcción | J10: LPNP | L10: Rechazado | M10: Rechazado | N10: Bien- Adquisición de materiales y suministros | O10: 4120000 | P10: ADQUISICIÓN DE MAQUINARIA Y EQUIPO DE CONSTRUCCIÓN (MINICARGADOR) | Q10: NO | BM10: 38
A11: S001 | B11: 46029 | C11: Concluido | D11: Estatal | E11: Consejería Jurídica | F11: Coordinación Administrativa (23300001000000S) | G11: 3000 Servicios generales | H11: 3800 – Servicios Oficiales | I11: 3821 Gastos de ceremonias oficiales y de orden social | J11: LPNP | K11: 2,257,873.33 | L11: Concluido | M11: Adjudicado | N11: Servicio- Contratacion de servicios generales | O11: 61641216 | P11: CARAVANAS ITINERANTES POR LA JUSTICIA SOCIAL | Q11: SI | R11: 78940488 | S11: 78940488 | T11: 78940488 | U11: 50234856 | V11: CA-0009-2026 | W11: 46058 | X11: LUIS MANUEL ENRÍQUEZ ESTÉVEZ | Y11: GC-Gasto Corriente | Z11: 11010101 - Ingresos propios del sector central | AA11: 264171179.61 | AC11: 3821103004 | AD11: "CARAVANAS ITINERANTES POR LA JUSTICIA SOCIAL." | AE11: SERVICIO | AF11: No | AG11: No | AH11: Licitación Publicación Presencial | AI11: N/A | AK11: LPNP-002-2026 | AL11: https://compramex.edomex.gob.mx/compramex/public/catalogosExternos/detalleConvocatoria.xhtml | AM11: Electrónico - COMPRAMEX | AN11: 46065 | AO11: 0.54166667 | AP11: 46071 | AQ11: 0.54166667 | AR11: 46073 | AS11: 0.58333333 | AT11: 46073 | AU11: 0.70833333 | AV11: 46073 | AX11: 46073 | AY11: 0.73958333 | AZ11: JAJMA, S. DE R.L. DE C.V. | BA11: JAJ050824G65 | BD11: 245583000 | BE11: CS/OPD/4/2026 | BF11: 46072 | BG11: 47361 | BH11: N/A | BI11: 18588180 | BJ11: DIRECCIÓN DE PROCEDIMIENTOS ADQUISITIVOS DEL SECTOR AUXILIAR Y APOYO INTERSECTORIAL | BL11: Adjudicado | BM11: 7
A12: S002 | B12: 46030 | C12: Concluido | D12: Estatal | E12: Consejería Jurídica | F12: Coordinación Administrativa (23300001000000S) | G12: 3000 Servicios generales | H12: 3700 – Servicios de Traslado y Viáticos | I12: 3791 Otros servicios de traslado y hospedaje | K12: 1,003.27 | L12: Concluido | M12: Concluido | N12: Servicio- Contratacion de servicios generales | O12: 0 | P12: SERVICIO DE ESTACIONAMIENTO PARA LA CONSEJERÍA JURÍDICA | Q12: NO | BM12: 44
A13: S003 | B13: 46031 | C13: Rechazado | D13: Estatal | E13: Secretaría del Agua | F13: Coordinación Administrativa (23200002000000S) | G13: 5000 Bienes muebles inmuebles e intangibles | H13: 5100 – Mobiliario y Equipo de Administración | I13: 5111 Muebles y Enceres | J13: IRP | K13: 0 | L13: Rechazado | M13: Rechazado | N13: Bien- Adquisición de materiales y suministros | O13: 1500000 | P13: ARCHIVERO ESCRITORIO EJECUTIVO ESCRITORIO OPERATIVO SILLA EJECUTIVA SILLA SECRETARIAL ARCHIVERO ANAQUELES LIBRERO MESA OPERATIVA MESA DE TRABAJO MESA DE JUNTAS DISPENSADOR DE AGUA PERCHERO | Q13: NO | BM13: 46
A14: S004 | B14: 46032 | C14: Rechazado | D14: Estatal | E14: Secretaría del Agua | F14: Coordinación Administrativa (23200002000000S) | G14: 4000 Transferencias asignaciones subsidios y otras ayudas | H14: 4200 – Transferencias al Resto del Sector Público | I14: 4242 Donativos a municipios | K14: 0 | L14: Rechazado | M14: Rechazado | N14: Bien- Adquisición de materiales y suministros | O14: 0 | P14: TUBERÍA DE 50.8 MILÍMETROS PARA EL PROGRAMA EMERGENTE PARA MEJORA DE INFRAESTRUCTURA EN REDES DE DISTRIBUCIÓN TUBERÍA DE 101.6 MILÍMETROS PARA EL PROGRAMA EMERGENTE PARA MEJORA DE INFRAESTRUCTURA EN REDES DE DISTRIBUCIÓN TUBERÍA DE 152.4 MILÍMETROS PARA EL PROGRAMA EMERGENTE PARA MEJORA DE INFRAESTRUCTURA EN REDES DE DISTRIBUCIÓN | Q14: NO | BM14: 12
A15: S005 | B15: 46033 | C15: Rechazado | D15: Estatal | E15: Secretaría del Agua | F15: Coordinación Administrativa (23200002000000S) | G15: 4000 Transferencias asignaciones subsidios y otras ayudas | H15: 4200 – Transferencias al Resto del Sector Público | I15: 4242 Donativos a municipios | K15: 0 | L15: Rechazado | M15: Rechazado | N15: Bien- Adquisición de materiales y suministros | O15: 0 | P15: PAQUETE 1 INSTALACIÓN Y PUESTA EN MARCHA DE SISTEMAS DE CAPTADORES DE AGUA EN ESPACIÓS PÚBLICOS PAQUETE 2 INSTALACIÓN Y PUESTA EN MARCHA DE SISTEMAS DE CAPTADORES DE AGUA EN ESPACIÓS PÚBLICOS PAQUETE 3 INSTALACIÓN Y PUESTA EN MARCHA DE SISTEMAS DE CAPTADORES DE AGUA EN ESPACIÓS PÚBLICOS | Q15: NO | BM15: 13
A16: S006 | B16: 46034 | C16: Rechazado | D16: Estatal | E16: Secretaría del Agua | F16: Coordinación Administrativa (23200002000000S) | G16: 2000 Materiales y Suministros | H16: 2400 – Materiales y Artículos de Construcción y de Reparación | I16: 2411 Productos minerales no metálicos | K16: 0 | L16: Rechazado | M16: Rechazado | N16: Bien- Adquisición de materiales y suministros | O16: 0 | P16: PROGRAMA DE BAÑOS ECOLÓGICOS | Q16: NO | BM16: 14
A17: S007 | B17: 46035 | C17: Concluido | D17: Estatal | E17: Organismos OPDS | F17: Sistema para el Desarrollo Integral de la Familia del Estado de México 200C01000000000 | G17: 4000 Transferencias asignaciones subsidios y otras ayudas | H17: 4400 – Ayudas Sociales | I17: 4412 Despensas | J17: LPNP | K17: 2,302,790,324.14 | L17: Concluido | M17: Adjudicado | N17: Bien- Adquisición de materiales y suministros | O17: 2.3276237e+09 | P17: PAQUETE DE DESAYUNOS ESCOLARES FRÍOS PAQUETE DE ALIMENTOS DE DESAYUNOS ESCOLARES CALIENTES CANASTA DE PRODUCTOS ALIMENTICIOS | Q17: NO | V17: CA-0005-2026 | W17: 46042 | X17: Juan Manuel Ruano González | Y17: GC-Gasto Corriente | Z17: 14010101 - Ingresos por el cobro de derechos y venta de bienes y servicios | AA17: 2327623741.59 | AC17: "4412010004, 4412010005, 4412010006" | AD17: "PAQUETE DE DESAYUNOS ESCOLARES FRÍOS PAQUETE DE DESAYUNOS ESCOLARES CALIENTES CANASTA DE PRODUCTOS ALIMENTICIOS " | AE17: BIEN | AF17: Si | AG17: No | AH17: Invitación Restringida Presencial | AI17: N/A | AK17: IRP-001-2026 | AL17: https://compramex.edomex.gob.mx/compramex/public/catalogosExternos/procedimientsoAdquisitivos.xhtml | AM17: Electrónico - COMPRAMEX | AN17: 46086 | AO17: 0.41666667 | AP17: 46089 | AQ17: 0.41666667 | AR17: 46090 | AS17: 0.625 | AT17: 46090 | AU17: 0.64583333 | AV17: 46090 | AX17: 46090 | AY17: 0.65625 | AZ17: Despensas y Provisiones de Alimentos, S.A. DE C.V. | BA17: DPA0108013Y4 | BD17: 2.3210109e+09 | BE17: CB/OPD/3/2026 | BF17: 46091 | BG17: 46387 | BH17: https://recursosmateriales.edomex.gob.mx/testimonios | BI17: 6612856.5 | BJ17: Dirección de Procedimientos Adquisitivos del Sector Auxiliar y Apoyo Intersectorial | BL17: Adjudicado | BM17: 15
A18: S007-D | B18: 46035 | C18: Concluido | D18: Estatal | E18: Organismos OPDS | F18: Sistema para el Desarrollo Integral de la Familia del Estado de México 200C01000000000 | G18: 4000 Transferencias asignaciones subsidios y otras ayudas | H18: 4400 – Ayudas Sociales | I18: 4412 Despensas | J18: LPNP | K18: 2,302,790,324.14 | L18: Concluido | M18: Desierta | N18: Bien- Adquisición de materiales y suministros | O18: 2.3276237e+09 | P18: PAQUETE DE DESAYUNOS ESCOLARES FRÍOS PAQUETE DE ALIMENTOS DE DESAYUNOS ESCOLARES CALIENTES CANASTA DE PRODUCTOS ALIMENTICIOS | Q18: NO | V18: CA-0005-2026 | W18: 46042 | X18: Juan Manuel Ruano González | Y18: GC-Gasto Corriente | Z18: 14010101 - Ingresos por el cobro de derechos y venta de bienes y servicios | AA18: 2327623741.59 | AC18: "4412010004, 4412010005, 4412010006" | AD18: "PAQUETE DE DESAYUNOS ESCOLARES FRÍOS PAQUETE DE DESAYUNOS ESCOLARES CALIENTES CANASTA DE PRODUCTOS ALIMENTICIOS " | AE18: BIEN | AF18: Si | AG18: No | AH18: Licitación Publicación Presencial | AI18: N/A | AK18: LPNP-001-2026 | AL18: https://compramex.edomex.gob.mx/compramex/public/catalogosExternos/detalleConvocatoria.xhtml | AM18: Electrónico - COMPRAMEX | AN18: 46065 | AO18: 0.41666667 | AP18: 46071 | AQ18: 0.41666667 | AR18: 46079 | AS18: 0.58333333 | AT18: 46079 | AU18: 0.66666667 | AV18: 46079 | AX18: 46079 | AY18: 0.6875 | AZ18: DESPENSAS Y PROVISIONES DE ALIMENTOS, S.A. DE C.V. | BA18: DPA0108013Y4 | BD18: 0 | BE18: Desierto | BH18: Desierto | BI18: 0 | BJ18: DIRECCIÓN DE PROCEDIMIENTOS ADQUISITIVOS DEL SECTOR AUXILIAR Y APOYO INTERSECTORIAL | BK18: NO CONTRAOFERTO | BL18: Desierta | BM18: 11
A19: S008 | B19: 46036 | C19: Concluido | D19: Estatal | E19: Secretaría de Seguridad | F19: Coordinación Administrativa | G19: 3000 Servicios generales | H19: 3100 – Servicios Básicos | I19: 3191 Servicios de telecomunicación especializados | J19: LPNP | K19: 331,113,054.70 | L19: Concluido | M19: Adjudicado | N19: Servicio- Contratacion de servicios generales | O19: 3.4135366e+08 | P19: SISTEMA INTEGRAL DE DISPOSITIVOS DE MONITOREO ELECTRONICO (BRAZALETES) | Q19: NO | V19: CA-0004-2026 | W19: 46045 | X19: NO APLICA | Y19: GC-Gasto Corriente | Z19: 11010101 - Ingresos propios del sector central | AA19: 331108374.96 | AC19: 3191012677 | AD19: SISTEMA INTEGRAL DE DISPOSITIVOS DE MONITOREO ELECTRÓNICO (BRAZALETES) | AE19: SERVICIO | AF19: Si | AG19: No | AH19: Adjudicación Directa Presencial | AI19: https://gobedomex-my.sharepoint.com/personal/coordtic_om_edomex_gob_mx/Documents/Aplicaciones/Microsoft%20Forms/Sistema%20de%20Seguimiento%20(2)%202/Pregunta/ADP-004-2026_ERANDI%20GUADALUPE%20AGA.pdf | AJ19: DIRECCIÓN DE PROCEDIMIENTOS ADQUISITIVOS DEL SECTOR AUXILIAR Y APOYO INTERSECTORIAL | AK19: ADP-004-2026 | AL19: https://compramex.edomex.gob.mx/compramex/public/catalogosExternos/procedimientsoAdquisitivos.xhtml | AM19: Invitación | AP19: 46052 | AQ19: 0.4375 | AR19: 46052 | AS19: 0.66666667 | AT19: 46052 | AU19: 0.72916667 | AV19: 46052 | AX19: 46052 | AY19: 0.73958333 | AZ19: PROMOTORA E INFRAESTRUCTURA GB, S.A. DE C.V. | BA19: PIG140711UQ7 | BB19: Poder Notarial, persona moral | BC19: https://gobedomex-my.sharepoint.com/personal/coordtic_om_edomex_gob_mx/Documents/Aplicaciones/Microsoft%20Forms/Sistema%20de%20Seguimiento%20(2)%202/Convocatoria%20de%20Bases%20yo%20Invitacion%20(PDF)/ADP-004-2026_ERANDI%20GUADALUPE%20AGA.pdf | BD19: 3.3110837e+08 | BE19: CS/OPD/3/2026 | BF19: 11355 | BG19: 46387 | BH19: N/A | BI19: 10245290 | BJ19: DIRECCIÓN DE PROCEDIMIENTOS ADQUISITIVOS DEL SECTOR AUXILIAR Y APOYO INTERSECTORIAL | BL19: Adjudicado | BM19: 19
A20: S009 | B20: 46037 | C20: Concluido | D20: Estatal | E20: Secretaría de Seguridad | F20: Coordinación Administrativa | G20: 3000 Servicios generales | H20: 3500 – Servicios de Instalación, Reparación, Mantenimiento y Conservación | I20: 3581 Servicios de lavandería, limpieza e higiene | J20: LPNP | K20: 613,312,275.00 | L20: Concluido | M20: Adjudicado | N20: Servicio- Contratacion de servicios generales | O20: 613312275 | P20: SERVICIO INTEGRAL DE LAVANDERIA, LIMPIEZA, DESINFECCION E HIGIENE | Q20: NO | V20: CA-0002-2026 | W20: 46045 | X20: NO APLICA | Y20: GC-Gasto Corriente | Z20: 11010101 - Ingresos propios del sector central | AA20: 613312172.55 | AC20: 3581132835 | AD20: SERVICIO INTEGRAL DE LAVANDERÍA LIMPIEZA, DESINFECCIÓN E HIGIENE | AE20: SERVICIO | AF20: Si | AG20: No | AH20: Adjudicación Directa Presencial | AI20: https://gobedomex-my.sharepoint.com/personal/coordtic_om_edomex_gob_mx/Documents/Aplicaciones/Microsoft%20Forms/Sistema%20de%20Seguimiento%20(2)%202/Pregunta/ADP-002-2026_ERANDI%20GUADALUPE%20AGA.pdf | AJ20: DIRECCIÓN DE PROCEDIMIENTOS ADQUISITIVOS DEL SECTOR AUXILIAR Y APOYO INTERSECTORIAL | AK20: ADP-003-2026 | AL20: https://gobedomex-my.sharepoint.com/personal/coordtic_om_edomex_gob_mx/Documents/Aplicaciones/Microsoft%20Forms/Sistema%20de%20Seguimiento%20(2)%202/Convocatoria%20de%20Bases%20yo%20Invitacion%20(PDF)/ADP-002-2026_ERANDI%20GUADALUPE%20AGA.pdf | AM20: Invitación | AP20: 46052 | AQ20: 0.41666667 | AR20: 46052 | AS20: 0.66666667 | AT20: 46052 | AU20: 0.70833333 | AV20: 46052 | AX20: 46052 | AY20: 0.71875 | AZ20: LA COSMOPOLITANA, S.A. DE C.V. | BA20: COS850425822 | BB20: Poder Notarial, persona moral | BC20: https://gobedomex-my.sharepoint.com/personal/coordtic_om_edomex_gob_mx/Documents/Aplicaciones/Microsoft%20Forms/Sistema%20de%20Seguimiento%20(2)%203/Pregunta/PODER_ERANDI%20GUADALUPE%20AGA%201.pdf | BD20: 6.1331217e+08 | BE20: CS/OPD/2/2026 | BF20: 46054 | BG20: 46387 | BH20: N/A | BI20: 102.45 | BJ20: DIRECCIÓN DE PROCEDIMIENTOS ADQUISITIVOS DEL SECTOR AUXILIAR Y APOYO INTERSECTORIAL | BL20: Adjudicado | BM20: 3
A21: S010 | B21: 46038 | C21: Concluido | D21: Estatal | E21: Secretaría de Seguridad | F21: Coordinación Administrativa | G21: 2000 Materiales y Suministros | H21: 2200 – Alimentos y Utensilios | I21: 2211 Productos alimenticios para personas | J21: LPNP | K21: 1,347,366,262.84 | L21: Concluido | M21: Adjudicado | N21: Bien- Adquisición de materiales y suministros | O21: 1.3473663e+09 | P21: SUMINISTRO DE VIVERES Y ALIMENTOS PARA CONSUMO HUMANO | Q21: NO | V21: CA-0003-2026 | W21: 46045 | X21: NO APLICA | Y21: GC-Gasto Corriente | Z21: 11010101 - Ingresos propios del sector central | AA21: 1347366262.84 | AC21: 2211011490 | AD21: SUMINISTRO DE VÍVERES Y ALIMENTOS PARA CONSUMO HUMANO | AE21: BIEN | AF21: Si | AG21: No | AH21: Adjudicación Directa Presencial | AI21: https://gobedomex-my.sharepoint.com/personal/coordtic_om_edomex_gob_mx/Documents/Aplicaciones/Microsoft%20Forms/Sistema%20de%20Seguimiento%20(2)%202/Pregunta/ADP-002-2026_ERANDI%20GUADALUPE%20AGA.pdf | AJ21: DIRECCIÓN DE PROCEDIMIENTOS ADQUISITIVOS DEL SECTOR AUXILIAR Y APOYO INTERSECTORIAL | AK21: ADP-002-2026 | AL21: https://gobedomex-my.sharepoint.com/personal/coordtic_om_edomex_gob_mx/Documents/Aplicaciones/Microsoft%20Forms/Sistema%20de%20Seguimiento%20(2)%202/Convocatoria%20de%20Bases%20yo%20Invitacion%20(PDF)/ADP-002-2026_ERANDI%20GUADALUPE%20AGA.pdf | AM21: Invitación | AP21: 46052 | AQ21: 0.39583333 | AR21: 46052 | AS21: 0.66666667 | AT21: 46052 | AU21: 0.6875 | AV21: 46052 | AX21: 46052 | AY21: 0.69791667 | AZ21: LA COSMOPOLITANA, S.A. DE C.V. | BA21: COS850425822 | BB21: Poder Notarial, persona moral | BC21: https://gobedomex-my.sharepoint.com/personal/coordtic_om_edomex_gob_mx/Documents/Aplicaciones/Microsoft%20Forms/Sistema%20de%20Seguimiento%20(2)%203/Pregunta/PODER_ERANDI%20GUADALUPE%20AGA.pdf | BD21: 1.3473663e+09 | BE21: CB/OPD/1/2026 | BF21: 46054 | BG21: 46387 | BH21: N/A | BI21: 0 | BJ21: DIRECCIÓN DE PROCEDIMIENTOS ADQUISITIVOS DEL SECTOR AUXILIAR Y APOYO INTERSECTORIAL | BL21: Adjudicado | BM21: 29
A22: S011 | B22: 46039 | C22: Concluido | D22: Estatal | E22: Secretaría de Cultura y Turismo | F22: Coordinación Administrativa | G22: 3000 Servicios generales | H22: 3800 – Servicios Oficiales | I22: 3841 Exposiciones y ferias | J22: IRP | K22: 1,220,900.00 | L22: Concluido | M22: Adjudicado | N22: Servicio- Contratacion de servicios generales | O22: 1288900 | P22: SERVICIO INTEGRAL PARA LA PARTICIPACION DEL ESTADO DE MÉXICO EN LA FERIA INTERNACIONAL DEL TURISMO FITUR 2026 | Q22: NO | V22: CA-0001-2026 | W22: 46035 | X22: NO APLICA | Y22: GC-Gasto Corriente | Z22: 11010101 - Ingresos propios del sector central | AA22: 1288900 | AB22: https://gobedomex-my.sharepoint.com/personal/coordtic_om_edomex_gob_mx/Documents/Aplicaciones/Microsoft%20Forms/Sistema%20de%20Seguimiento%20(2)%201/N%C3%BAmero%20de%20Oficio%20de%20liberaci%C3%B3n%20de%20recursos/Scanned-image14-01-2026-120958%20(1)_JAQUELINE%20CASTA%C3%91EDA.pdf | AC22: 3841010123 | AD22: SERVICIO INTEGRAL PARA LA PARTICIPACIÓN DEL ESTADO DE MÉXICO EN LA FERIA INTERNACIONAL DE TURISMO “FITUR” 2026 | AE22: SERVICIO | AF22: No | AG22: No | AH22: Adjudicación Directa Presencial | AI22: DICTAMEN DE PROCEDENCIA ADP-001-202618-02-2026-165332.pdf | AJ22: DIRECCIÓN DE PROCEDIMIENTOS ADQUISITIVOS DEL SECTOR AUXILIAR Y APOYO INTERSECTORIAL | AK22: ADP-001-2026 | AL22: https://compramex.edomex.gob.mx/compramex/public/catalogosExternos/detalleConvocatoria.xhtml | AM22: Invitación | AP22: 46038 | AQ22: 0.70833333 | AR22: 46041 | AS22: 0.39583333 | AT22: 46041 | AU22: 0.41666667 | AV22: 46041 | AX22: 46041 | AY22: 0.42708333 | AZ22: CREATIVIDAD Y ESPECTACULOS S.A DE C.V | BA22: CES0107171KA | BD22: 1220900 | BE22: CS/OPD/1/2026 | BF22: 46041 | BG22: 46048 | BH22: N/A | BI22: 68000 | BJ22: DIRECCIÓN DE PROCEDIMIENTOS ADQUISITIVOS DEL SECTOR AUXILIAR Y APOYO INTERSECTORIAL | BL22: Adjudicado | BM22: 31
A23: S012 | B23: 46040 | C23: Concluido | D23: Estatal | E23: Secretaría de Finanzas | F23: Coordinación Administrativa(20700002000000S) | G23: 3000 Servicios generales | H23: 3800 – Servicios Oficiales | I23: 3821 Gastos de ceremonias oficiales y de orden social | J23: IRP | K23: 157,690.40 | L23: Concluido | M23: Concluido | N23: Servicio- Contratacion de servicios generales | O23: 157690.4 | P23: SERVICIO DE ALIMENTOS | Q23: NO | BM23: 47
A24: S013 | B24: 46036 | C24: Rechazado | D24: Estatal | E24: Secretaría de las Mujeres | F24: Coordinación Administrativa | G24: 3000 Servicios generales | H24: 3990-Otros Servicios Generales | I24: 3992 Gastos y servicios menores | K24: 0 | L24: Rechazado | M24: Rechazado | N24: Servicio- Contratacion de servicios generales | O24: 0 | P24: SERVICIO DE SUMINISTRO DE GARRAFÓN DE AGUA | Q24: NO | BM24: 48
A25: S014 | B25: 46041 | C25: Rechazado | D25: Estatal | E25: Secretaría de las Mujeres | F25: Coordinación Administrativa | G25: 3000 Servicios generales | H25: 3300 – Servicios Profesionales, Científicos, Técnicos y Otros Servicios | I25: 3311 Asesorías asociadas a convenios o acuerdos | K25: 0 | L25: Rechazado | M25: Rechazado | N25: Servicio- Contratacion de servicios generales | O25: 0 | P25: ASESORÍA Y REVISIÓN DE LOS PROCESOS DE NÓMINA RELATIVOS AL PERSONAL POR CONTRATO INDIVIDUAL DE TRABAJO POR TIEMPO DETERMINADO | Q25: NO | BM25: 49
A26: S015 | B26: 46042 | C26: Rechazado | D26: Estatal | E26: Secretaría de las Mujeres | F26: Coordinación Administrativa | G26: 3000 Servicios generales | H26: 3700 – Servicios de Traslado y Viáticos | I26: 3791 Otros servicios de traslado y hospedaje | K26: 0 | L26: Rechazado | M26: Rechazado | N26: Servicio- Contratacion de servicios generales | O26: 0 | P26: SERVICIO DE ESTACIONAMIENTO | Q26: NO | BM26: 50
A27: S016 | B27: 46043 | C27: Rechazado | D27: Estatal | E27: Secretaría de las Mujeres | F27: Coordinación Administrativa | G27: 5000 Bienes muebles inmuebles e intangibles | H27: 5300 – Equipo e Instrumental Médico y de Laboratorio | I27: 5311 Equipo médico y de laboratorio | K27: 0 | L27: Rechazado | M27: Rechazado | N27: Bien- Adquisición de materiales y suministros | O27: 0 | P27: MESA DE EXPLORACIÓN ESTÁNDAR SILLA DE RUEDAS ANDADERA INDUSTRIAL PLEGABLE MULETAS AUXILIARES DE ALUMINIO BÁSCULA ELECTRÓNICA PARA BEBÉ | Q27: NO | BM27: 51
A28: S017 | B28: 46036 | C28: Rechazado | D28: Estatal | E28: Secretaría de las Mujeres | F28: Coordinación Administrativa | G28: 3000 Servicios generales | H28: 3500 – Servicios de Instalación, Reparación, Mantenimiento y Conservación | I28: 3571 Reparación, instalación y mantenimiento de maquinaria, equipo industrial y diverso | K28: 0 | L28: Rechazado | M28: Rechazado | N28: Servicio- Contratacion de servicios generales | O28: 0 | P28: MANTENIMIENTO PREVENTIVO Y CORRECTIVO PARA ELEVADOR DE LA SECRETARÍA DE LAS MUJERES | Q28: No | BM28: 52
A29: S018 | B29: 46044 | C29: Rechazado | D29: Estatal | E29: Secretaría de las Mujeres | F29: Coordinación Administrativa | G29: 3000 Servicios generales | H29: 3100 – Servicios Básicos | I29: 3121 Gas | K29: 0 | L29: Rechazado | M29: Rechazado | N29: Servicio- Contratacion de servicios generales | O29: 0 | P29: SUMINISTRO DE GAS L.P. PARA LOS CENTROS LIBRE DE LA SECRETARIA DE LAS MUJERES | Q29: NO | BM29: 53
A30: S019 | B30: 46045 | C30: Rechazado | D30: Estatal | E30: Secretaría de las Mujeres | F30: Coordinación Administrativa | G30: 2000 Materiales y Suministros | H30: 2500 – Productos Químicos, Farmacéuticos y de Laboratorio | I30: 2541 Materiales, accesorios y suministros médicos | K30: 0 | L30: Rechazado | M30: Rechazado | N30: Bien- Adquisición de materiales y suministros | O30: 0 | P30: NEBULIZADOR ULTRASÓNICO HOSPITALARIO KIT DE NEBULIZADOR PEDIÁTRICA KIT DE NEBULIZADOR ADULTO MONITOR DE SIGNOS VITALES PORTÁTIL | Q30: NO | BM30: 54
A31: S020 | B31: 46046 | C31: Rechazado | D31: Estatal | E31: Secretaría de las Mujeres | F31: Coordinación Administrativa | G31: 2000 Materiales y Suministros | H31: 2500 – Productos Químicos, Farmacéuticos y de Laboratorio | I31: 2531 Medicinas y productos farmacéuticos | K31: 0 | L31: Rechazado | M31: Rechazado | N31: Bien- Adquisición de materiales y suministros | O31: 0 | P31: VITAMINAS Y MINERALES GOMITAS LORATADINA 5 MILIGRAMOS JARABE LORATADINA 10 MILIGRAMOS TRAMADOL 37.5 MILIGRAMOS AMANTADINA, CLORFENAMINA Y PARACETAMOL SUSPENSIÓN INFANTIL DE 60 MILILITROS BUTILHIOSINA, PARACETAMOL, SOLUCIÓN EN GOTAS DE 20 MILILITROS LORATADINA, PARACETAMOL Y FENILEFRINA TABLETAS NAPROXENO CON PARACETAMOL SUPOSITORIOS NAPROXENO SÓDICO CON PARACETAMOL 100 MILILITROS PARACETAMOL SOLUCIÓN EN GOTAS 30 MILILITROS PARACETAMOL SOLUCIÓN INFANTIL 3.2 GRAMOS FRASCO 120 MILILITROS NAPROXENO CON PARACETAMOL TABLETAS SALBUTAMOL PARA NEBULIZAR SULFATO DE PLATA CREMA 1 G/100 G TARRO CON 30 G. DICLOFENACO GEL, TUBO DE 60 GRAMOS DICLOFENACO TABLETAS 100 MILIGRAMOS COMPLEJO B CON DICLOFENACO TABLETAS COMPLEJO B CON DICLOFENACO INYECTABLE 100,100,20,5,75 MG/3 ML. CAJA CON 3 ÁMPULAS DEXAMETASONA TABLETAS 4 MILIGRAMOS MICONAZOL EN CREMA AMBROXOL, SALBUTAMOL JARABE 120 MILILITROS NITROFURAZONA 0.2 G POMADA 85 G TUBO 85 G SALBUMATOL PARA INHALACIÓN ÁCIDO ACETILSALICÍLICO DE 500 MILIGRAMOS ANTIGRIPAL PARACETAMOL, CAFEINA, CLORHIDRATO DE FENILEFRINA MALEATO DE CLORFENAMINA 500/25/5/4 MG. CAJA CON 10 TAB. CLORFENAMINA COMPUESTA 500 MG PARACETAMOL TAB. CAJA CON 10 TAB. AMANTADINA/CLORFENAMINA/PARACETAMOL GOTAS PEDIÁTRICAS FRASCO CON 60 ML. HIOSCINA, PARACETAMOL 10/500 MG. CAJA CON 24 TAB TRAMADOL/PARACETAMOL CAJA CON 20 TABLETAS PARACETAMOL SOLUCIÓN PEDIÁTRICA FRASCO/GOTERO 15 ML 100 MG/1 ML. SOBRES DE SUERO ORAL POLVO SABOR MANZANA CAJA CON 100 SOBRES 28.3 G. CALCIO EFERVESCENTE SALBUTAMOL AEROSOL AMBROXOL /SALBUTAMOL JARABE (0,040/0,150 GRAMOS/ 100 MILILITROS) PARACETAMOL DE 500 MILIGRAMOS IODOPOVIDONA ANTISÉPTICO PARA PIEL Y MUCOSA 120 MILILITROS CLOTRIMAZOL, TUBO CON 20 GRAMOS OXIDO DE ZINC CREMA AMOXICILINA, ACIDO CLAVULÁNICO, SUSPENSIÓN DE 60 MILILITROS AMOXICILINA 500 MILIGRAMOS AMOXICILINA 7.5 GRAMOS (500 MILIGRAMOS/5 MILILITROS) COMPLEJO B TABLETAS DEXAMETASONA INYECTABLE DE 8 MILILITROS | Q31: NO | BM31: 55
A32: S021 | B32: 46047 | C32: Rechazado | D32: Estatal | E32: Secretaría de las Mujeres | F32: Coordinación Administrativa | G32: 2000 Materiales y Suministros | H32: 2700 – Vestuario, Blancos, Prendas de Protección y Artículos Deportivos | I32: 2721 Prendas de seguridad y protección personal | K32: 0 | L32: Rechazado | M32: Rechazado | N32: Bien- Adquisición de materiales y suministros | O32: 0 | P32: SILBATO PARA BRIGADISTA OVERIK DESECHABLE CUBREZAPATO LAMPARA MANOS LIBRES PARA COMBATIR INCENDIOS MOCHILA PARA HERRAMIENTAS CINTURON DE HERRAMIENTAS, CON BOLSA PARA HERRAMIENTAS TRAJE DE BOMBERO PORTAEXTINTOR PARA EXTINTOR DE 9 KILOS CINTA DELIMIRADORA AMARILLA CON NEGRO CINTA DELIMITADORA PROHIBIDO EL PASO CINTA DELIMITADORA PRECAUCIÓN DETECTOR DE HUMO CON ALARMA DETECTOR DE GAS NATURAL Y GAS L.P. BATA DE TRABAJO | Q32: NO | BM32: 56
A33: S022 | B33: 46048 | C33: Rechazado | D33: Estatal | E33: Secretaría de las Mujeres | F33: Coordinación Administrativa | G33: 2000 Materiales y Suministros | H33: 2500 – Productos Químicos, Farmacéuticos y de Laboratorio | I33: 2541 Materiales, accesorios y suministros médicos | K33: 0 | L33: Rechazado | M33: Rechazado | N33: Bien- Adquisición de materiales y suministros | O33: 0 | P33: CUBREBOCAS TIPO MASCARILLA 5 CAPAS KN95 CUBREBOCAS TRICAPA, CAJA BAUMANÓMETRO DIGITAL GLUCÓMETRO OXÍMETRO TORUNDA DE ALGODÓN VENDA ELÁSTICA DE 5 CENTÍMETROS AGUA OXIGENADA DE 480 MILILITROS ESTETOSCOPIO DOBLE SUMINISTROS PARA BOTIQUÍN ALCOHOL ETÍLICO DE 250 MILILITROS GUANTES DE LÁTEX SABANAS DESECHABLES AZUL PARA CAMILLA TERMÓMETRO DIGITAL TIPO PISTOLA VENDA ELÁSTICA DE 7.5 CENTÍMETROS BOTIQUÍN PORTÁTIL GASA ESTÉRIL DE 10 POR 10 CENTÍMETROS CINTA MICROPOROSA COLOR PIEL CINTA 5CM X 9.1 MT. VENDITAS TRANSPIEL SURTIDAS VENDA ELÁSTICA DE 10 CENTÍMETROS ABATELENGUAS COLLARÍN DE INMOVILIZACIÓN AJUSTABLE TIRAS REACTIVAS Y LANCETAS | Q33: NO | BM33: 16
A34: S023 | B34: 46049 | C34: Rechazado | D34: Estatal | E34: Secretaría de las Mujeres | F34: Coordinación Administrativa | G34: 2000 Materiales y Suministros | H34: 2700 – Vestuario, Blancos, Prendas de Protección y Artículos Deportivos | I34: 2721 Prendas de seguridad y protección personal | K34: 0 | L34: Rechazado | M34: Rechazado | N34: Bien- Adquisición de materiales y suministros | O34: 0 | P34: CHALECO DE SEGURIDAD CASCO PROTECTOR LENTES DE PROTECCIÓN GUANTE DE CARNAZA ZAPATO INDUSTRIAL CON CASQUILLO DIELÉCTRICO GUANTES PARA COMBATIENTE DE INCENDIO CINTURON FAJA ARNÉS DE SEGURIDAD ANTICAIDAS CON CINCO ANILLOS LÍNEA DE VIDA GUANTES DIELÉCTRICOS PROTECCIÓN HASTA 1000 V. | Q34: NO | BM34: 26
A35: S024 | B35: 46050 | C35: Concluido | D35: Estatal | E35: Oficialía Mayor | F35: Coordinación Administrativa (23400000030000S) | G35: 3000 Servicios generales | H35: 3200 – Servicios de Arrendamiento | I35: 3251 Arrendamiento de vehículos | J35: LPNP | K35: 59,918,597.64 | L35: Concluido | M35: Adjudicado | N35: Servicio- Contratacion de servicios generales | O35: 67808036 | P35: RENTA DE AUTOBUSES | Q35: NO | V35: CA-0007-2026 | W35: 46057 | X35: NO APLICA | Y35: GC-Gasto Corriente | Z35: 11010101 - Ingresos propios del sector central | AA35: 59918597.64 | AC35: 3251010060 | AD35: SERVICIO DE RENTA DE AUTOBUSES PARA EL TRASLADO DE PERSONAL. | AE35: SERVICIO | AF35: Si | AG35: No | AH35: Licitación Publicación Presencial | AI35: N/A | AK35: LPNP-004-2026 | AL35: https://compramex.edomex.gob.mx/compramex/public/catalogosExternos/detalleConvocatoria.xhtml | AM35: Electrónico - COMPRAMEX | AN35: 46066 | AO35: 0.5 | AP35: 46072 | AQ35: 0.41666667 | AR35: 46076 | AS35: 0.58333333 | AT35: 46076 | AU35: 0.69791667 | AV35: 46076 | AX35: 46076 | AY35: 0.71875 | AZ35: ENLACES TERRESTRES TURMAR, S. DE R.L. DE C.V. | BA35: ETT160825FP7 | BD35: 59918598 | BE35: CS/OPD/6/2026 | BF35: 46073 | BG35: 46387 | BH35: N/A | BI35: 0 | BJ35: DIRECCIÓN DE PROCEDIMIENTOS ADQUISITIVOS DEL SECTOR AUXILIAR Y APOYO INTERSECTORIAL | BL35: Adjudicado | BM35: 33
A36: S025 | B36: 46051 | C36: Concluido | D36: Estatal | E36: Secretaría de Bienestar | F36: Coordinación Administrativa | G36: 4000 Transferencias asignaciones subsidios y otras ayudas | H36: 4400 – Ayudas Sociales | I36: 4413 Gastos relacionados con actividades culturales, deportivas y de ayuda extraordinaria | J36: LPNP | K36: 388,157,000.00 | L36: Concluido | M36: Adjudicado | N36: Servicio- Contratacion de servicios generales | O36: 352850190 | P36: SERVICIO DE EMISIÓN DE TARJETAS PERSONALIZADAS QUE SIRVA COMO MEDIO DE ACCESO AL APOYO MONETARIO Y DE SERVICIOS QUE OTORGA EL PROGRAMA DE DESARROLLO SOCIAL "MUJERES CON BIENESTAR" | Q36: NO | V36: CA-0010-2026 | W36: 46059 | X36: LUIS MANUEL ENRÍQUEZ ESTÉVEZ | Y36: GC-Gasto Corriente | Z36: 15010114 - Ramo 28 | AA36: 388157000 | AC36: 4413011138 | AD36: SERVICIO DE EMISIÓN DE TARJETAS PERSONALIZADAS QUE SIRVA COMO MEDIO DE ACCESO AL APOYO MONETARIO Y DE SERVICIOS QUE OTORGA EL PROGRAMA DE DESARROLLO SOCIAL "MUJERES CON BIENESTAR". | AE36: SERVICIO | AF36: Si | AG36: No | AH36: Licitación Publicación Presencial | AI36: N/A | AK36: LPNP-005-2026 | AL36: https://compramex.edomex.gob.mx/compramex/public/catalogosExternos/detalleConvocatoria.xhtml | AM36: Electrónico - COMPRAMEX | AN36: 46066 | AO36: 0.41666667 | AP36: 46071 | AQ36: 0.66666667 | AR36: 46073 | AS36: 0.58333333 | AT36: 46073 | AU36: 0.66666667 | AV36: 46073 | AX36: 46073 | AY36: 0.6875 | AZ36: SERVICIOS BROXEL, S.A.P.I. DE C.V. | BA36: SBR130327HU9 | BD36: 352814000 | BE36: CS/OPD/5/2026 | BF36: 46072 | BG36: 46387 | BI36: 35343000 | BJ36: DIRECCIÓN DE PROCEDIMIENTOS ADQUISITIVOS DEL SECTOR AUXILIAR Y APOYO INTERSECTORIAL | BL36: Adjudicado | BM36: 34
A37: S026 | B37: 46052 | C37: Concluido | D37: Estatal | E37: Secretaría de Educación, Ciencia, Tecnología e Innovación | F37: Coordinación Administrativa | G37: 3000 Servicios generales | H37: 3800 – Servicios Oficiales | I37: 3821 Gastos de ceremonias oficiales y de orden social | J37: LPNP | K37: 3,993,939.17 | L37: Concluido | M37: Adjudicado | N37: Servicio- Contratacion de servicios generales | O37: 4000000 | P37: SERVICIO INTEGRAL PARA LA ORGANIZACIÓN Y EJECUCIÓN DE LA "PRESEA ESTADO DE MÉXICO" 2025 | Q37: NO | V37: CA-0006-2026 | W37: 46056 | X37: NO APLICA | Y37: GC-Gasto Corriente | Z37: 11010101 - Ingresos propios del sector central | AA37: 4000000 | AC37: 3821103007 | AD37: SERVICIO INTEGRAL PARA LA ORGANIZACIÓN Y EJECUCIÓN DE LA "PRESA ESTADO DE MÉXICO" 2025. | AE37: SERVICIO | AF37: No | AG37: No | AH37: Licitación Publica Nacional Presencial | AI37: N/A | AK37: LPNP-003-2026 | AL37: https://compramex.edomex.gob.mx/compramex/public/catalogosExternos/detalleConvocatoria.xhtml | AM37: Electrónico - COMPRAMEX | AN37: 46066 | AO37: 0.41666667 | AP37: 46071 | AQ37: 0.41666667 | AR37: 46073 | AS37: 0.58333333 | AT37: 46073 | AU37: 0.70833333 | AV37: 46073 | AX37: 46073 | AY37: 0.72916667 | AZ37: GREGORIA CUEVAS ALVIRDE | BA37: CUAG780429480 | BD37: 3823000 | BE37: CS/B/1/2026 | BF37: 46073 | BG37: 46083 | BH37: N/A | BI37: 170939.17 | BJ37: Orlando Gutiérrez Vilchis | BL37: Adjudicado | BM37: 5
A38: S027 | B38: 46053 | C38: Concluido | D38: Estatal | E38: Secretaría de Cultura y Turismo | F38: Coordinación Administrativa | G38: 3000 Servicios generales | H38: 3800 – Servicios Oficiales | I38: 3841 Exposiciones y ferias | J38: CP | K38: 576,666.76 | L38: Concluido | M38: Concluido | N38: Servicio- Contratacion de servicios generales | O38: 580000 | P38: SERVICIO INTEGRAL PARA LA "EXPO FERIA TEQUIXQUIAC 206" | Q38: NO | BM38: 17
A39: S028 | B39: 46054 | C39: Concluido | D39: Estatal | E39: Oficialía Mayor | F39: Coordinación Administrativa (23400000030000S) | G39: 3000 Servicios generales | H39: 3300 – Servicios Profesionales, Científicos, Técnicos y Otros Servicios | I39: 3341 Capacitación | J39: CP | K39: 392,354.01 | L39: Concluido | M39: Concluido | N39: Servicio- Contratacion de servicios generales | O39: 500000 | P39: ENTRENAMIENTO DE EXTINCIÓN CONTRA INCENDIOS (HELICOPTER AERIAL FIREFIGHTING TRAINING) | Q39: NO | BM39: 18
A40: S029 | B40: 46055 | C40: Concluido | D40: Estatal | E40: Secretaría de Salud | F40: Coordinación Administrativa ( 20800001000000S ) | G40: 3000 Servicios generales | H40: 3700 – Servicios de Traslado y Viáticos | I40: 3791 Otros servicios de traslado y hospedaje | J40: CP | K40: 965.51 | L40: Concluido | M40: Concluido | N40: Servicio- Contratacion de servicios generales | O40: 117000 | P40: SERVICIO DE ESTACIONAMIENTO | Q40: NO | BM40: 20
A41: S030 | B41: 46056 | C41: Concluido | D41: Estatal | E41: Oficialía Mayor | F41: Coordinación Administrativa (23400000030000S) | G41: 3000 Servicios generales | H41: 3200 – Servicios de Arrendamiento | I41: 3251 Arrendamiento de vehículos | J41: CP | K41: 580,000.00 | L41: Concluido | M41: Concluido | N41: Servicio- Contratacion de servicios generales | O41: 580000 | P41: SERVICIO DE RENTA DE AUTOBUSES PARA EL TRASLADO DEL PERSONAL. | Q41: NO | BM41: 21
A42: S031 | B42: 46057 | C42: Rechazado | D42: Estatal | E42: Consejería Jurídica | F42: Coordinación Administrativa (23300001000000S) | G42: 3000 Servicios generales | H42: 3800 – Servicios Oficiales | I42: 3821 Gastos de ceremonias oficiales y de orden social | K42: 0 | L42: Rechazado | M42: Rechazado | N42: Servicio- Contratacion de servicios generales | O42: 0 | P42: ALCANCE A OFICIO DE CARAVANAS ITINERANTES | Q42: NO | BM42: 57
A43: S032 | B43: 46050 | C43: Concluido | D43: Estatal | E43: Secretaría de Finanzas | F43: Coordinación Administrativa(20700002000000S) | G43: 3000 Servicios generales | H43: 3300 – Servicios Profesionales, Científicos, Técnicos y Otros Servicios | I43: 3361 Servicios de apoyo administrativo y fotocopiado | J43: CP | K43: 561,541.50 | L43: Concluido | M43: Concluido | N43: Servicio- Contratacion de servicios generales | O43: 580000 | P43: ENCUADERNACIÓN DE LA CUENTA PÚBLICA DEL GOBIERNO DEL ESTADO DE MÉXICO 2025 IMPRESIÓN Y ENCUADERNACIÓN DEL MANUAL ÚNICO DE CONTABILIDAD GUBERNAMENTAL 2026 (VIGÉSIMA QUINTA EDICIÓN) | Q43: NO | BM43: 22
A44: S033 | B44: 46050 | C44: Concluido | D44: Estatal | E44: Secretaría de Finanzas | F44: DIRECCIÓN DE ADMINISTRACIÓN Y SERVICIOS GENERALES | G44: 2000 Materiales y Suministros | H44: 2100 – Materiales de Administración, Emisión de Documentos y Artículos Oficiales | I44: 2171 Material didáctico | J44: CP | K44: 495.00 | L44: Concluido | M44: Concluido | N44: Bien- Adquisición de materiales y suministros | O44: 263658 | P44: FISCO AGENDA 2026 | Q44: NO | BM44: 58
A45: S034 | B45: 46050 | C45: Concluido | D45: Estatal | E45: Secretaría de Finanzas | F45: DIRECCIÓN DE ADMINISTRACIÓN Y SERVICIOS GENERALES | G45: 3000 Servicios generales | H45: 3900 – Otros Servicios Generales | I45: 3992 Gastos y servicios menores | J45: CP | K45: 71.50 | L45: Concluido | M45: Concluido | N45: Servicio- Contratacion de servicios generales | O45: 324788 | P45: SERVICIO DE GARRAFONES DE AGUA PARA LA DIRECCIÓN GENERAL DE RECAUDACIÓN | Q45: NO | BM45: 24
A46: S035 | B46: 46050 | C46: Concluido | D46: Estatal | E46: Secretaría de Finanzas | F46: DIRECCIÓN DE ADMINISTRACIÓN Y SERVICIOS GENERALES | G46: 3000 Servicios generales | H46: 3500 – Servicios de Instalación, Reparación, Mantenimiento y Conservación | I46: 3591 Servicios de fumigación | J46: CP | K46: 31,764.23 | L46: Concluido | M46: Concluido | N46: Servicio- Contratacion de servicios generales | O46: 398860 | P46: SERVICIO DE FUMIGACIÓN Y CONTROL DE PLAGAS PARA DIRECCIÓN GENERAL DE RECAUDACIÓN | Q46: NO | BM46: 59
A47: S036 | B47: 46050 | C47: Concluido | D47: Estatal | E47: Secretaría de Finanzas | F47: DIRECCIÓN DE ADMINISTRACIÓN Y SERVICIOS GENERALES | G47: 2000 Materiales y Suministros | H47: 2100 – Materiales de Administración, Emisión de Documentos y Artículos Oficiales | I47: 2171 Material didáctico | J47: CP | K47: 2,550.00 | L47: Concluido | M47: Concluido | N47: Bien- Adquisición de materiales y suministros | O47: 263658 | P47: MULTI AGENDA FISCAL Y COMPLEMENTO 2026 | Q47: NO | BM47: 60
A48: S037 | B48: 46051 | C48: Concluido | D48: Estatal | E48: Oficialía Mayor | F48: COORDINACIÓN ADMINISTRATIVA | G48: 3000 Servicios generales | H48: 3300 – Servicios Profesionales, Científicos, Técnicos y Otros Servicios | I48: 3361 Servicios de apoyo administrativo y fotocopiado | K48: 65,244,589.32 | L48: Concluido | M48: Adjudicado | N48: Servicio- Contratacion de servicios generales | O48: 0 | P48: CONTRATACIÓN DE SERVICIOS DE FOTOCOPIADO, IMPRESIÓN Y DIGITALIZACIÓN PARA LAS DEPENDENCIAS, ORGANISMOS AUXILIARES, ORGANISMOS AUTÓNOMOS Y TRIBUNALES ADMINISTRATIVOS DEL PODER EJECUTIVO DEL ESTADO DE MÉXICO. | Q48: NO | V48: CA-0020-2026 | W48: 46073 | X48: NO APLICA | Y48: GC-Gasto Corriente | Z48: 11010101 - Ingresos propios del sector central | AA48: 65244589.32 | AC48: 3361050003 | AD48: "CONTRATACION DE SERVICIOS DE FOTOCOPIADO, IMPRESIÓN Y DIGITALIZACIÓN PARA LAS DEPENDENCIAS, ORGANISMOS AUXILIARES, ORGANISMOS AUTONÓMOS Y TRIBUNALES ADMINISTRATIVOS DEL PODER EJECUTIVO DEL ESTADO DE MEXICO." | AE48: SERVICIO | AF48: No | AG48: Si | AH48: Adjudicación Directa Presencial | AK48: ADP-010-2026 | AL48: https://compramex.edomex.gob.mx/compramex/public/catalogosExternos/detalleConvocatoria.xhtml | AM48: Electrónico - COMPRAMEX | AP48: 46080 | AQ48: 0.39583333 | AR48: 46080 | AS48: 0.58333333 | AT48: 46080 | AU48: 0.64583333 | AV48: 46080 | AX48: 46080 | AY48: 0.65625 | AZ48: BLACK ECCO TI, S.A. DE C.V. | BA48: BET190705434 | BD48: 65244589 | BE48: CS/OPD/7/2026 | BF48: 46082 | BG48: 46203 | BH48: N/A | BI48: 0 | BJ48: DIRECCIÓN DE PROCEDIMIENTOS ADQUISITIVOS DEL SECTOR AUXILIAR Y APOYO INTERSECTORIAL | BL48: Adjudicado | BM48: 6
A49: S038 | B49: 46051 | C49: Concluido | D49: Estatal | E49: Oficialía Mayor | F49: COORDINACIÓN ADMINISTRATIVA | G49: 3000 Servicios generales | H49: 3800 – Servicios Oficiales | I49: 3821 Gastos de ceremonias oficiales y de orden social | K49: 315,136.95 | L49: Concluido | M49: Adjudicado | N49: Servicio- Contratacion de servicios generales | O49: 0 | P49: RENTA DE SANITARIO PORTÁTIL TIPO A. RENTA DE SANITARIO PORTÁTIL TIPO B. RENTA DE SANITARIO PORTÁTIL PARA PERSONAS CON DISCAPACIDAD. RENTA DE SANITARIO TIPO C. RENTA DE SANITARIO PORTÁTIL TIPO CAMPER MIXTO. RENTA DE SANITARIO PORTÁTIL TIPO CAMPER HOMBRES. RENTA DE SANITARIO PORTÁTIL TIPO CAMPER MUJERES. RENTA DE MÓDULO DE SANITARIO ARMABLE MUJERES. RENTA DE MÓDULO DE SANITARIO ARMABLE HOMBRES. RENTA DE LAVAMANOS DOBLE. RENTA DE REGADERA PORTÁTIL. RENTA DE MODULO DE MINGITORIO. RENTA DE SANITARIO PORTÁTIL TIPO CAMPER DE OFICINA. RENTA DE MÓDULO DISPENSADOR DE GEL ANTIBACTERIAL. RENTA DE MÓDULO DE SANITARIO DOBLE. | Q49: NO | V49: CA-0017-2026 | W49: 46066 | X49: NO APLICA | Y49: GC-Gasto Corriente | Z49: 11010101 - Ingresos propios del sector central | AA49: 26421561 | AC49: "3821060001 3821060002 3821060003 3821060004 3821060005 3821060006 3821060007 3821060008 3821060009 3821102937 3821140001 3821060010 3821060011 3821102938 3821060012" | AD49: LETRINAS | AE49: SERVICIO | AF49: Si | AG49: No | AH49: Invitación Restringida Presencial | AK49: IRP-002-2026 | AL49: https://compramex.edomex.gob.mx/compramex/public/catalogosExternos/detalleConvocatoria.xhtml | AM49: Electrónico - COMPRAMEX | AN49: 46101 | AO49: 0.41666667 | AP49: 46104 | AQ49: 0.41666667 | AR49: 46106 | AS49: 0.58333333 | AT49: 46106 | AU49: 0.66666667 | AV49: 46106 | AX49: 46106 | AY49: 0.6875 | AZ49: RENTA DE REGADERAS Y SERVICIOS, S.A. DE C.V. | BA49: RRS1302111IA | BD49: 26421561 | BE49: CS/OPD/10/2026 | BF49: 46106 | BG49: 46387 | BH49: N/A | BI49: 0 | BJ49: Dirección de Procedimientos Adquisitivos del Sector Auxiliar y Apoyo Intersectorial | BL49: Adjudicado | BM49: 41
A50: S038-D | B50: 46051 | C50: Concluido | D50: Estatal | E50: Oficialía Mayor | F50: COORDINACIÓN ADMINISTRATIVA | G50: 3000 Servicios generales | H50: 3800 – Servicios Oficiales | I50: 3821 Gastos de ceremonias oficiales y de orden social | K50: 315,136.95 | L50: Concluido | M50: Desierta | N50: Servicio- Contratacion de servicios generales | O50: 0 | P50: RENTA DE SANITARIO PORTÁTIL TIPO A. RENTA DE SANITARIO PORTÁTIL TIPO B. RENTA DE SANITARIO PORTÁTIL PARA PERSONAS CON DISCAPACIDAD. RENTA DE SANITARIO TIPO C. RENTA DE SANITARIO PORTÁTIL TIPO CAMPER MIXTO. RENTA DE SANITARIO PORTÁTIL TIPO CAMPER HOMBRES. RENTA DE SANITARIO PORTÁTIL TIPO CAMPER MUJERES. RENTA DE MÓDULO DE SANITARIO ARMABLE MUJERES. RENTA DE MÓDULO DE SANITARIO ARMABLE HOMBRES. RENTA DE LAVAMANOS DOBLE. RENTA DE REGADERA PORTÁTIL. RENTA DE MODULO DE MINGITORIO. RENTA DE SANITARIO PORTÁTIL TIPO CAMPER DE OFICINA. RENTA DE MÓDULO DISPENSADOR DE GEL ANTIBACTERIAL. RENTA DE MÓDULO DE SANITARIO DOBLE. | Q50: NO | V50: CA-0017-2026 | W50: 46066 | X50: NO APLICA | Y50: GC-Gasto Corriente | Z50: 11010101 - Ingresos propios del sector central | AA50: 26421561 | AC50: "3821060001 3821060002 3821060003 3821060004 3821060005 3821060006 3821060007 3821060008 3821060009 3821102937 3821140001 3821060010 3821060011 3821102938 3821060012" | AD50: LETRINAS | AE50: SERVICIO | AF50: Si | AG50: No | AH50: Licitación Publicación Presencial | AI50: N/A | AK50: LPNP-008-2026 | AL50: https://compramex.edomex.gob.mx/compramex/public/catalogosExternos/detalleConvocatoria.xhtml | AM50: Electrónico - COMPRAMEX | AN50: 46073 | AO50: 0.66666667 | AP50: 46073 | AQ50: 0.66666667 | AR50: 46078 | AS50: 0.58333333 | AT50: 46078 | AU50: 0.70833333 | AV50: 46078 | AX50: 46078 | AY50: 0.72916667 | AZ50: Desierto | BA50: Desierto | BD50: 0 | BE50: Desierto | BH50: Desierto | BI50: 0 | BJ50: Dirección de Procedimientos Adquisitivos del Sector Auxiliar y Apoyo Intersectorial | BK50: Desierto, ningún oferente cumplió cualitativamente para CA-0017-2026 | BL50: Desierta | BM50: 8
A51: S039 | B51: 46051 | C51: Concluido | D51: Estatal | E51: Oficialía Mayor | F51: COORDINACIÓN ADMINISTRATIVA | G51: 3000 Servicios generales | H51: 3800 – Servicios Oficiales | I51: 3821 Gastos de ceremonias oficiales y de orden social | K51: 1,376.48 | L51: Concluido | M51: Adjudicado | N51: Servicio- Contratacion de servicios generales | O51: 0 | P51: RENTA DE FUNDA PARA VALLA METÁLICA RENTA DE CARPA DE 3, 3.5 Y 4 METROS DE ALTURA. RENTA DE CARPA DE 20, 30, 40 O 50 METROS DE ANCHO RENTA DE CARPA DE 6 METROS DE ALTURA RENTA DE MESA REDONDA RENTA DE MESA TABLÓN RENTA DE ENLONADO RENTA DE VALLA DE METÁLICA RENTA DE MANTEL PARA MESA RENTA DE CARPA PANORÁMICA DE 20 METROS DE LARGO RENTA DE GRADAS RENTA DE SILLA PLEGADIZA RENTA DE SILLA TIPO TIFFANY RENTA DE SILLA DE TELA PLIANA RENTA DE CARPA DE 5 METROS DE ALTURA | Q51: NO | V51: CA-0016-2026 | W51: 46066 | X51: NO APLICA | Y51: GC-Gasto Corriente | Z51: 11010101 - Ingresos propios del sector central | AA51: 116016974.17 | AC51: "3821020001 3821102927 3821102928 3821050057 3821102929 3821102930 3821030001 3821030002 3821102931 3821102932 3821102933 3821030003 3821102934 3821102935 3821102936" | AD51: CARPAS | AE51: SERVICIO | AF51: Si | AG51: No | AH51: Licitación Publicación Presencial | AI51: N/A | AK51: LPNP-008-2026 | AL51: https://compramex.edomex.gob.mx/compramex/public/catalogosExternos/detalleConvocatoria.xhtml | AM51: Electrónico - COMPRAMEX | AN51: 46073 | AO51: 0.66666667 | AP51: 46076 | AQ51: 0.66666667 | AR51: 46078 | AS51: 0.58333333 | AT51: 46078 | AU51: 0.70833333 | AV51: 46078 | AX51: 46078 | AY51: 0.72916667 | AZ51: SERVICIOS Y EVENTOS BK, S.A. DE C.V. | BA51: SEB1502102P4 | BD51: 1.1601697e+08 | BE51: CS/OPD/9/2026 | BF51: 46082 | BG51: 46387 | BH51: N/A | BI51: 0 | BJ51: DIRECCIÓN DE PROCEDIMIENTOS ADQUISITIVOS DEL SECTOR AUXILIAR Y APOYO INTERSECTORIAL | BL51: Adjudicado | BM51: 9
A52: S040 | B52: 46051 | C52: Concluido | D52: Estatal | E52: Oficialía Mayor | F52: COORDINACIÓN ADMINISTRATIVA | G52: 2000 Materiales y Suministros | H52: 2600-COMBUSTIBLES, LUBRICANTES Y ADITIVOS. | I52: 2611-COMBUSTIBLES, LUBRICANTES Y ADITIVOS. | K52: 622,209,010.66 | L52: Concluido | M52: Adjudicado | N52: Bien- Adquisición de materiales y suministros | O52: 0 | P52: SUMINISTRO DE MONEDEROS ELECTRÓNICOS DE COMBUSTIBLES, LUBRICANTES Y ADITIVOS | Q52: NO | V52: CA-0014-2026 | W52: 46066 | X52: LUIS MANUEL ENRÍQUEZ ESTÉVEZ | Y52: GC-Gasto Corriente | Z52: 11010101 - Ingresos propios del sector central | AA52: 622209010.66 | AC52: 2611012243 | AD52: SUMINISTRO DE MONEDEROS ELECTRÓNICOS DE COMBUSTIBLES, LUBRICANTES Y ADITIVOS | AE52: PAQUETE | AF52: Si | AG52: No | AH52: Licitación Publicación Presencial | AI52: N/A | AK52: LPNP-006-2026 | AL52: https://compramex.edomex.gob.mx/compramex/public/catalogosExternos/detalleConvocatoria.xhtml | AM52: Electrónico - COMPRAMEX | AN52: 46073 | AO52: 0.41666667 | AP52: 46076 | AQ52: 0.41666667 | AR52: 46078 | AS52: 0.58333333 | AT52: 46078 | AU52: 0.66666667 | AV52: 46078 | AX52: 46078 | AY52: 0.67708333 | AZ52: SERVICIOS BROXEL, S.AP.I. DE C.V. | BA52: SBR130327HU9 | BD52: 6.2220901e+08 | BE52: CB/OPD/2/2026 | BF52: 46082 | BG52: 46387 | BI52: 0 | BJ52: DIRECCIÓN DE PROCEDIMIENTOS ADQUISITIVOS DEL SECTOR AUXILIAR Y APOYO INTERSECTORIAL | BL52: Adjudicado | BM52: 35
A53: S041 | B53: 46051 | C53: Concluido | D53: Estatal | E53: Oficialía Mayor | F53: COORDINACIÓN ADMINISTRATIVA | G53: 3000 Servicios generales | H53: 3500 – Servicios de Instalación, Reparación, Mantenimiento y Conservación | I53: 3581 Servicios de lavandería, limpieza e higiene | K53: 377,730,332.44 | L53: Concluido | M53: Adjudicado | N53: Servicio- Contratacion de servicios generales | O53: 0 | P53: SERVICIO DE ASEO Y LIMPIEZA DE INMUEBLES. | Q53: NO | V53: CA-0015-2026 | W53: 46066 | X53: PAVEL RAMSES HUERTAS CABRERA | Y53: GC-Gasto Corriente | Z53: 11010101 - Ingresos propios del sector central | AA53: 377730332.44 | AC53: 3581122834 | AD53: SERVICIO DE ASEO Y LIMPIEZA DE INMUEBLES | AE53: SERVICIO | AF53: Si | AG53: No | AH53: Licitación Publicación Presencial | AI53: N/A | AK53: LPNP-007-2026 | AL53: https://compramex.edomex.gob.mx/compramex/public/catalogosExternos/detalleConvocatoria.xhtml | AM53: Electrónico - COMPRAMEX | AN53: 46073 | AO53: 0.5 | AP53: 46076 | AQ53: 0.5 | AR53: 46078 | AS53: 0.58333333 | AT53: 46078 | AU53: 0.6875 | AV53: 46078 | AX53: 46078 | AY53: 0.69791667 | AZ53: SLYCOM, S.A. DE C.V. | BA53: SLY2312195E7 | BD53: 3.7773033e+08 | BE53: CS/OPD/8/2026 | BF53: 46082 | BG53: 46387 | BI53: 0 | BJ53: DIRECCIÓN DE PROCEDIMIENTOS ADQUISITIVOS DEL SECTOR AUXILIAR Y APOYO INTERSECTORIAL | BL53: Adjudicado | BM53: 36
A54: S042 | B54: 46052 | C54: Concluido | D54: Estatal | E54: Secretaría de Cultura y Turismo | F54: COORDINACIÓN ADMINISTRATIVA | G54: 3000 Servicios generales | H54: 3800 – Servicios Oficiales | I54: 3841 Exposiciones y ferias | J54: CP | K54: 344,725.00 | L54: Concluido | M54: Concluido | N54: Servicio- Contratacion de servicios generales | O54: 350000 | P54: SERVICIO INTEGRAL PARA EL STAND CON EL QUE PARTICIPARÁ LA SECRETARÍA DE CULTURA Y TURISMO A TRAVÉS DEL CONSEJO EDITORIAL DE LA ADMINISTRACIÓN PÚBLICA ESTATAL EN LA “47 EDICIÓN DE LA FERIA INTERNACIONAL DEL LIBRO DEL PALACIO DE MINERÍA”. | Q54: NO | BM54: 61
A55: S043 | B55: 46052 | C55: Concluido | D55: Estatal | E55: Secretaría de Seguridad | F55: DIRECCIÓN DE SERVICIOS GENERALES Y APOYO LOGÍSTICO | G55: 3000 Servicios generales | H55: 3100 – Servicios Básicos | I55: 3121 Gas | J55: LPNP | K55: 33,900,068.87 | L55: Concluido | M55: Adjudicado | N55: Servicio- Contratacion de servicios generales | O55: 33900069 | P55: SUMINISTRO DE GAS L.P. EN CENTROS PENITENCIARIOS Y DE REINSERCIÓN SOCIAL | Q55: NO | V55: CA-0011-2026 | W55: 46057 | X55: N/A | Y55: GC-Gasto Corriente | Z55: 11010101 - Ingresos propios del sector central | AA55: 33900068.87 | AC55: 3121012680 | AD55: SUMINISTRO DE GAS L.P. EN CENTROS PENITENCIARIOS Y DE REINSERCIÓN SOCIAL | AE55: SERVICIO | AF55: No | AG55: No | AH55: Adjudicación Directa Presencial | AK55: ADP-006-2026 | AL55: https://compramex.edomex.gob.mx/compramex/public/catalogosExternos/detalleConvocatoria.xhtml | AM55: Electrónico - COMPRAMEX | AP55: 46073 | AQ55: 0.41666667 | AR55: 46076 | AS55: 0.58333333 | AT55: 46076 | AU55: 0.70833333 | AV55: 46076 | AX55: 46076 | AY55: 0.71875 | AZ55: GRUPO CENTURIÓN COMBUSTIBLES, S.A.P.I DE C.V. | BA55: GCE140919BVA | BD55: 33900069 | BE55: CS/B/3/2026 | BF55: 46082 | BG55: 46356 | BH55: N/A | BI55: 0 | BJ55: Orlando Gutiérrez Vilchis | BL55: Adjudicado | BM55: 37
A56: S044 | B56: 46056 | C56: Rechazado | D56: Estatal | E56: Secretaría de Finanzas | F56: DIRECCIÓN DE ADMINISTRACIÓN Y SERVICIOS GENERALES | G56: 3000 Servicios generales | H56: 3400 – Servicios Financieros, Bancarios y Comerciales | I56: 3421 Servicios de cobranza, investigación crediticia y similar | J56: LPNP | K56: 0 | L56: Rechazado | M56: Rechazado | N56: Servicio- Contratacion de servicios generales | O56: 1.2844992e+08 | P56: ENTREGA A DOMICILIO DE MEDIOS DE IDENTIFICACIÓN VEHICULAR | Q56: NO | BM56: 62
A57: S045 | B57: 46050 | C57: Concluido | D57: Estatal | E57: Oficialía Mayor | F57: COORDINACIÓN ADMINISTRATIVA | G57: 3000 Servicios generales | H57: 3300 – Servicios Profesionales, Científicos, Técnicos y Otros Servicios | I57: 3381 Servicios de vigilancia | J57: LPNP | K57: 633,856,081.24 | L57: Concluido | M57: Adjudicado | N57: Servicio- Contratacion de servicios generales | O57: 6.3385608e+08 | P57: SERVICIO DE SEGURIDAD Y VIGILANCIA | Q57: NO | V57: CA-0008-2026 | W57: 46057 | X57: SI | Y57: GC-Gasto Corriente | Z57: 11010101 - Ingresos propios del sector central | AA57: 633856081.24 | AC57: 3381012756 | AD57: SERVICIO DE SEGURIDAD Y VIGILANCIA. | AE57: SERVICIO | AF57: Si | AG57: Si | AH57: Adjudicación Directa Presencial | AK57: ADP-005-2026 | AL57: https://compramex.edomex.gob.mx/compramex/public/catalogosExternos/detalleConvocatoria.xhtml | AM57: Electrónico - COMPRAMEX | AP57: 46070 | AQ57: 0.41666667 | AR57: 46072 | AS57: 0.64583333 | AT57: 46072 | AU57: 0.66666667 | AV57: 46072 | AX57: 46072 | AY57: 0.6875 | AZ57: CUERPO DE GUARDIAS DE SEGURIDAD INDUSTRIAL BANCARIA Y COMERCIAL DEL VALLE DE TOLUCA | BA57: CGS8512298A8 | BD57: 6.3385608e+08 | BE57: CS/B/2/2026 | BF57: 46082 | BG57: 46387 | BI57: 0 | BJ57: Orlando Gutiérrez Vilchis | BL57: Adjudicado | BM57: 39
A58: S046 | B58: 46057 | C58: Concluido | D58: Estatal | E58: Secretaría de Finanzas | F58: SUBCOORDINACIÓN DE ADQUISICIONES Y CONTROL PATRIMONIAL | G58: 3000 Servicios generales | H58: 3500 – Servicios de Instalación, Reparación, Mantenimiento y Conservación | I58: 3571 Reparación, instalación y mantenimiento de maquinaria, equipo industrial y diverso | J58: CP | K58: 4466 | L58: Concluido | M58: Concluido | N58: Servicio- Contratacion de servicios generales | O58: 35700 | P58: REPARACIÓN Y MANTENIMIENTO PARA ELEVADOR INSTALADO EN LA OFICINA DE LA GUBERNATURA | Q58: NO | BM58: 25
A59: S047 | B59: 46057 | C59: Concluido | D59: Estatal | E59: Secretaría de Finanzas | F59: SUBCOORDINACIÓN DE ADQUISICIONES Y CONTROL PATRIMONIAL | G59: 3000 Servicios generales | H59: 3500 – Servicios de Instalación, Reparación, Mantenimiento y Conservación | I59: 3591 Servicios de fumigación | J59: CP | K59: 34,761.69 | L59: Concluido | M59: Concluido | N59: Servicio- Contratacion de servicios generales | O59: 41895 | P59: SERVICIO DE FUMIGACIÓN Y CONRTOL DE PLAGAS PARA LAS OFICINAS DE LA GUBERNATURA | Q59: NO | BM59: 27
A60: S048 | B60: 46057 | C60: Concluido | D60: Estatal | E60: Secretaría de Finanzas | F60: SUBCOORDINACIÓN DE ADQUISICIONES Y CONTROL PATRIMONIAL | G60: 3000 Servicios generales | H60: 3500 – Servicios de Instalación, Reparación, Mantenimiento y Conservación | I60: 3591 Servicios de fumigación | J60: CP | K60: 26,649.42 | L60: Concluido | M60: Concluido | N60: Servicio- Contratacion de servicios generales | O60: 14301 | P60: SERVICIO DE FUMIGACIÓN Y CONTROL DE PLAGAS PARA LA OFICINA DE LA VOCERÍA DE LA GUBERNATURA | Q60: NO | BM60: 28
A61: S049 | B61: 46057 | C61: Concluido | D61: Estatal | E61: Secretaría de Finanzas | F61: SUBCOORDINACIÓN DE ADQUISICIONES Y CONTROL PATRIMONIAL | G61: 3000 Servicios generales | H61: 3500 – Servicios de Instalación, Reparación, Mantenimiento y Conservación | I61: 3591 Servicios de fumigación | J61: CP | K61: 125,092.38 | L61: Concluido | M61: Concluido | N61: Servicio- Contratacion de servicios generales | O61: 43835 | P61: SERVICIO DE FUMIGACIÓN Y CONTROL DE PLAGAS PARA LA OFICINAS DE LA UNIDAD DE APOYO A LA ADMINISTRACIÓN GENERAL | Q61: NO | BM61: 63
A62: S050 | B62: 46057 | C62: Concluido | D62: Estatal | E62: Secretaría de Seguridad | F62: DIRECCIÓN DE SERVICIOS GENERALES Y APOYO LOGÍSTICO | G62: 2000 Materiales y Suministros | H62: 2200 – Alimentos y Utensilios | I62: 2222 Productos alimenticios para animales | J62: LPNP | K62: 3,367.50 | L62: Concluido | M62: Adjudicado | N62: Bien- Adquisición de materiales y suministros | O62: 11908085 | P62: ALFALFA ACHICALADA. ALIMENTO PARA CANINOS ADULTOS. ALIMENTO EXTRUIDO AL 100% PARA EQUINOS. | Q62: NO | V62: CA-0019-2026 | W62: 46069 | X62: NO APLICA | Y62: GC-Gasto Corriente | Z62: 11010101 - Ingresos propios del sector central | AA62: 11877796.5 | AC62: "2222010005, 2222011539, 2222011540" | AD62: "ALFALFA ACHICALDA ALIMENTO PARA CANINOS ADULTOS ALIMENTO EXTRUIDO AL 100% PARA EQUINOS" | AE62: "Paca, Bulto, Bulto" | AF62: No | AG62: No | AH62: Licitación Publicación Presencial | AI62: N/A | AK62: LPNP-009-2026 | AL62: https://compramex.edomex.gob.mx/compramex/public/catalogosExternos/detalleConvocatoria.xhtml | AM62: Electrónico - COMPRAMEX | AN62: 46076 | AO62: 0.41666667 | AP62: 46079 | AQ62: 0.41666667 | AR62: 46080 | AS62: 0.58333333 | AT62: 46080 | AU62: 0.70833333 | AV62: 46080 | AX62: 46080 | AY62: 0.72916667 | AZ62: PAMELA GUTIÉRREZ OSORNIO | BA62: GUOP9402275H4 | BD62: 11332200 | BE62: CB/B/3/2026 | BF62: 46085 | BG62: 46178 | BH62: N/A | BI62: 545596.5 | BJ62: Orlando Gutiérrez Vilchis | BL62: Adjudicado | BM62: 40
A63: S051 | B63: 46057 | C63: Concluido | D63: Estatal | E63: Secretaría de Seguridad | F63: DIRECCIÓN DE SERVICIOS GENERALES Y APOYO LOGÍSTICO | G63: 2000 Materiales y Suministros | H63: 2200 – Alimentos y Utensilios | I63: 2211 Productos alimenticios para personas | J63: LPNP | K63: 1,601,349.58 | L63: Concluido | M63: Adjudicado | N63: Bien- Adquisición de materiales y suministros | O63: 94508237 | P63: HARINA DE TRIGO PARA LA ELABORACIÓN DE PAN HARINA DE MAÍZ PARA LA ELABORACIÓN DE TORTILLA MATERIAS PRIMAS PARA LA ELABORACIÓN DE PAN Y TORTILLA | Q63: NO | V63: CA-0013-2026 | W63: 46059 | X63: NO APLICA | Y63: GC-Gasto Corriente | Z63: 11010101 - Ingresos propios del sector central | AA63: 94508237 | AC63: "2211010004, 2211010005, 2211010020" | AD63: "HARINA DE TRIGO PARA LA ELABORACIÓN DE PAN. HARINA DE MAÍZ PARA LA ELABORACIÓN DE TORTILLA. MATERIAS PRIMAS PARA LA ELABORACIÓN DE PAN Y TORTILLA." | AE63: "Bulto, Bulto, Paquete" | AF63: Si | AG63: No | AH63: Adjudicación Directa Presencial | AK63: ADP-007-2026 | AL63: https://compramex.edomex.gob.mx/compramex/public/catalogosExternos/detalleConvocatoria.xhtml | AM63: Electrónico - COMPRAMEX | AP63: 46073 | AQ63: 0.45833333 | AR63: 46076 | AS63: 0.58333333 | AT63: 46076 | AU63: 0.72916667 | AV63: 46076 | AX63: 46076 | AY63: 0.73958333 | AZ63: LA COSMOPOLITANA, S.A. DE C.V. | BA63: COS850425822 | BD63: 91234866 | BE63: CB/B/1/2026 | BF63: 46082 | BG63: 46387 | BH63: N/A | BI63: 0 | BJ63: Orlando Gutiérrez Vilchis | BL63: Adjudicado | BM63: 42
A64: S052 | B64: 46057 | C64: Concluido | D64: Estatal | E64: Secretaría de Seguridad | F64: DIRECCIÓN DE SERVICIOS GENERALES Y APOYO LOGÍSTICO | G64: 2000 Materiales y Suministros | H64: 2200 – Alimentos y Utensilios | I64: 2211 Productos alimenticios para personas | J64: LPNP | K64: 292,798,548.00 | L64: Concluido | M64: Adjudicado | N64: Bien- Adquisición de materiales y suministros | O64: 293382230 | P64: SUMINISTRO DE VIVERES Y ALIMENTOS PARA CONSUMO HUMANO | Q64: NO | V64: CA-0012-2026 | W64: 46059 | X64: NO APLICA | Y64: GC-Gasto Corriente | Z64: 11010101 - Ingresos propios del sector central | AA64: 293382230 | AC64: 2211011496 | AD64: SUMINISTRO DE VIVERES | AE64: PAQUETE | AF64: Si | AG64: No | AH64: Adjudicación Directa Presencial | AK64: ADP-008-2026 | AL64: file:///C:/Users/UsuarioGEM/Downloads/1.%20INVITACIO%C3%ACN%20ADP-008-2026%202211%20PRODUCTOS%20ALIMENTICIOS%20PARA%20PERSONAS%20(V%C3%8DVERES)T.pdf | AM64: Electrónico - COMPRAMEX | AP64: 46076 | AQ64: 0.45833333 | AR64: 46077 | AS64: 0.58333333 | AT64: 46077 | AU64: 0.70833333 | AV64: 46076 | AX64: 46076 | AY64: 0.71875 | AZ64: LA COSMOPOLITANA, S.A. DE C.V. | BA64: COS850425822 | BD64: 292798548 | BE64: CB/B/2/2026 | BF64: 46082 | BG64: 46368 | BH64: N/A | BI64: 0 | BJ64: Orlando Gutiérrez Vilchis | BL64: Adjudicado | BM64: 43
A65: S053 | B65: 46058 | C65: Concluido | D65: Estatal | E65: Secretaría de Finanzas | F65: COORDINACIÓN ADMINISTRATIVA | G65: 3000 Servicios generales | H65: 3900 – Otros Servicios Generales | I65: 3992 GASTOS DE SERVICIOS MENORES | J65: LPNP | K65: 71.50 | L65: Concluido | M65: Concluido | N65: Servicio- Contratacion de servicios generales | O65: 247052.25 | P65: GARRAFÓN DE AGUA | Q65: NO | BM65: 64
A66: S054 | B66: 46058 | C66: Concluido | D66: Estatal | E66: Secretaría de Cultura y Turismo | F66: COORDINACIÓN ADMINISTRATIVA | G66: 3000 Servicios generales | H66: 3800 – Servicios Oficiales | I66: 3831 Congresos y convenciones | J66: CP | K66: 578,250.00 | L66: Concluido | M66: Concluido | N66: Servicio- Contratacion de servicios generales | O66: 580000 | P66: CONTRATACIÓN DEL SERVICIO DE CAPACITACIÓN A TRAVES DEL “DIPLOMADO PARA LA FORMACIÓN DE GUÍAS DE TURISTAS ESPECIALIZADOS EN EXCURSIONISMO DE LOS PUEBLOS CON ENCANTO” | Q66: NO | BM66: 65
A67: S055 | B67: 46059 | C67: Concluido | D67: Estatal | E67: Consejería Jurídica | F67: COORDINACIÓN ADMINISTRATIVA | G67: 3000 Servicios generales | H67: 3800 – Servicios Oficiales | I67: 3821 Gastos de ceremonias oficiales y de orden social | K67: 130,469.10 | L67: Concluido | M67: Concluido | N67: Servicio- Contratacion de servicios generales | O67: 0 | P67: CONTRATACIÓN DE TESTIGO SOCIAL PARA LA CONTRATACIÓN DEL SERVICIO INTEGRAL “CARAVANAS ITINERANTES POR LA JUSTICIA SOCIAL” | Q67: NO | BM67: 66
A68: S056 | B68: 46062 | C68: Concluido | D68: Estatal | E68: Oficialía Mayor | F68: Coordinación Administrativa (23400000030000S) | G68: 3000 Servicios generales | H68: 3300 – Servicios Profesionales, Científicos, Técnicos y Otros Servicios | I68: 3381 Servicios de vigilancia | K68: 130469,1 | L68: Concluido | M68: Concluido | N68: Servicio- Contratacion de servicios generales | O68: 0 | P68: TESTIGO SOCIAL PARA LA CONTRATACIÓN DEL SERVICIO DE SEGURIDAD Y VIGILANCIA | Q68: NO | BM68: 67
A69: S057 | B69: 46062 | C69: Concluido | D69: Estatal | E69: Oficialía Mayor | F69: Coordinación Administrativa (23400000030000S) | G69: 2000 Materiales y Suministros | H69: 2400 – Materiales y Artículos de Construcción y de Reparación | I69: 2461 Material eléctrico y electrónico | J69: IRP | K69: 62,762.45 | L69: Concluido | M69: Concluido | N69: Bien- Adquisición de materiales y suministros | O69: 1050278 | P69: CALBE TIPO POT CAL. 10 ROLLO CON 100 MT. (BLANCO O GRIS) ROLLO DE 100 MT. CADA UNA DE CABLE PORTA ELECTRODO DE 1/0 ANTIFLAMA ROLLO DE 100 MT. CADA UNA DE CABLE PORTA ELECTRODO DE 2/0 ANTIFLAMA ROLLO DE 100 MT. CADA UNA DE CABLE PORTA ELECTRODO DE 3/0 ANTIFLAMA ROLLO DE 100 MT. CADA UNA DE CABLE PORTA ELECTRODO ANTIFLAMA CALIBRE 2 CONTACTO USO RUDO MONOFÁSICO TAPAS PARA CONTACTO DE USO RUDO DE ALUMINIO CHALUPAS DE ALUMINIO PARA CONTACTO USO RUDO LÁMPARAS SORDAS TORRE DE MINIBRUTO CON 4 UNIDADES C/U DE 120 VOLTS FOCOS DE MINIBRUTOS 120 VOLTS 650 WATTS INTERRUPTORES DOBLE TIRO DE ZAPATAS DE COBRE PARA CONECTORES CAM LOOK CONECTORES DE CHASIS CONECTORES DE CHASIS YELOW JACKET CABLE CABLE DUPLEX PROBADOR DE CORRIENTE TIPO LAPIZ SOQUET LÁMPARA DE EMERGENCIA LÁMPARA EXTENSIÓN ELECTRICA DE 20 METROS USO RUDO EXTENSIÓN ELÉCTRICA USO RUDO DE 6 METROS CABLE THW CALIBRE 14 TERMO-PASTILLA 10 AMPERES TERMO-PASTILLA 15 AMPERES TERMO-PASTILLA 40 AMPERES REFLECTOR LED DE 100 WATTS LÁMPARA DE MANO TÁCTICA DE 3000 LUMENES FOCO LED 45 WATTS PANEL LED DE 60 POR 60 CENTIMETROS, LUZ CALIDA LÁMPARA DE EMERGENCIA DE 60 LEDS CABLE POT FOCO AHORRADOR LUZ CALIDA DE 45 WATTS MCA, MAG FOCO AHORRADOR LUZ CALIDA DE 65 WATTS MCA, MAG FOCO LED TIPO MR-16 MARCA TECNOLITE DE 5.5 W. COLOR DE LUZ CALIDA 3000 °K FOCO PILOTO DE 10 WATTS 110-140 VOLTS LAMPARA FLUORESCENTE TIPO SLIM DE 30 WATTS LUZ DE DIA LÁMPARA FLUORESCENTE TIPO SLIM DE 60 WATTS LUZ DE DIA LAMPARA LED LAMPARA LED LAMPARA LED LÁMPARA TUBULAR LÁMPARA TUBULAR PASTILLA BREAKER FEDERAL PASTILLA BREAKER FEDERAL CENTRO DE CARGA EXTENSIÓN ELÉCTRICA REFLECTOR LED BASE PARA LAMPARA T8 CABLE USO RUDO CINTA COMPROBADOR DE VOLTAJE CONDUCTOR DE COBRE DE NUDO CONECTOR CILÍNDRICO CONECTOR DERIVADOR CONECTOR DERIVADOR ELEMENTO QUÍMICO, PARA PUESTA A TIERRA FOCO DE 33W FOTOCELDA MULTIRANGO DE 110-240 V KIT DE CRIMPADORA HIDRÁULICA LÁMPARA DE 10 WATTS DE LED TERMINAL PARA PUESTA A TIERRA ZAPATA CILÍNDRICA BIMETÁLICA SOQUET TIPO MOGUL LAMPARA TIPO SUBURBANA DE LED CABLE ELÉCTRICO DUPLEX CALIBRE 10 LINTERNA RECARGABLE FOCO DE 100 WATTS EXTENSIÓN ELÉCTRICA USO RUDO DE 20 METROS APAGADOR SENCILLO CON TAPA EXTENSIÓN ELÉCTRICA USO RUDO DE 15 METROS PROBADOR DE CORRIENTE TIPO LAPIZ SOQUET CINCHO DE 10 CENTÍMETROS CANALETA DE 2 VÍAS DE PVC CINTA PARA DUCTOS LÁMPARA DE EMERGENCIA DE 90 LEDS FOCO AHORRADOR DE 23 WATTS FOCO AHORRADOR DE 65 WATTS CANALETA DE 1/2 PULGADA FOCO AHORRADOR DE 10 WATTS CONTACTO DUPLEX CON PLACA CINTA DE AISLAR DE 19 MILÍMETROS EXTENSIÓN ELÉCTRICA DE 4 METROS EXTENSIÓN ELÉCTRICA USO RUDO DE 10 METROS LÁMPARA LINTERNA DE MANO RECARGABLE CLAVIJA METÁLICA USO RUDO FOCO AHORRADOR DE 15 WATTS CANALETA PLÁSTICA DE 12 POR 32 MILÍMETROS POR 2 METROS DE LARGO GRAPA PARA CABLE FUSIBLE DE 30 AMPERES FUSIBLE DE 60 AMPERES TIPO CARTUCHO CONTACTO SENCILLO CON TAPA CLAVIJA MULTICONTACTO DE 6 ENTRADAS EXTENSIÓN ELÉCTRICA USO RUDO DE 5 METROS CABLE DUPLEX CALIBRE 12 EXTENSIÓN ELÉCTRICA DE 5 METROS SOQUET DE BAQUELITA FOCO AHORRADOR DE 24 WATTS CANALETA BLANCA DE 17 MILÍMETROS POR 35 MILÍMETROS POR 2 METROS EXTENSIÓN ELÉCTRICA DE 3 METROS CENTRO DE CARGA 6 ESPACIOS PROBADOR DE POLARIDAD PARA CONTACTOS CANALETA AUTOADHERIBLE 20 POR 20 MILÍMETROS POR 2 METROS DE LARGO CINCHOS DE 15 CENTÍMETROS CINCHOS DE 30 CENTÍMETROS GUÍA PARA CABLE 30 METROS CAJA CHALUPA DE 2 POR 4 PULGADAS APAGADOR CON PLACA CENTRO DE CARGA QOD2S CENTRO DE CARGA QOD4S FOCO ESPIRAL DE 26 WATTS T2 TAPA DE 2 PERFORACIONES PARA JACK RJ45 REFLECTOR LED DE 200 WATTS LINTERNA TIPO MINERO LISTÓN FUSIBLE DE 30 AMPERES EXTENSIÓN PARA LÍNEA TELEFÓNICA DE 10 METROS EXTENSIÓN PARA LÍNEA TELEFÓNICA DE 15 METROS CABLE THW AWG CALIBRE 12 LÁMPARA TUBO DE LED 18 WATTS LÁMPARA FLUORESCENTE DE 14 WATTS T8 PILA ALCALINA AA PILA ALCALINA AAA POLIDUCTO DE 1/2 PULGADA CARGADOR CON (4) BATERIAS RECARGABLES CINCHOS DE 20 CENTÍMETROS GABINETE BLANCO CON REJA Y FOCOS LED 36 W EXTENSIÓN ELECTRICA DE 20 METROS USO RUDO EXTENSIÓN ELÉCTRICA USO RUDO DE 6 METROS EXTENSIÓN ELÉCTRICA USO RUDO DE 30 METROS CANALETA PLÁSTICA 2 X 1.2 X 200 CENTÍMETROS AUTOADHERIBLE CANALETA PLÁSTICA 2.5 X 2.5 X 200 CENTÍMETROS AUTOADHERIBLE CANALETA PLÁSTICA 2.4 POR 4.0 POR 200 CENTÍMETROS AUTOADHERIBLE CABLE THW CALIBRE 8 CABLE THW CALIBRE 14 CABLE THW CALIBRE 16 CABLE THW DEL NÚMERO 10 CABLE UTP CATEGORIA 6 CINTA ADHESIVA DOBLE CARA TRANSPARENTE 1 PULGADA DE ANCHO POR 1.50 METROS DE LARGO APAGADOR ESCALERA CON PLACA INTERRUPTOR TERMOMAGNÉTICO DE 3 POLOS DE 100 AMPERES CABLE DUPLEX CALIBRE 14 APAGADOR SENCILLO VISIBLE CUADRADO CAJA UNIVERSAL PARA CANALETA CANALETA DE ALUMNIO MEDIA CAÑA DE 2 ½ PULGADA PLACA PARA CONTACTO DUPLEX CONTACTO DUPLEX POLARIZADO SIN TAPA LÁMPARA DE MANO TÁCTICA DE 3000 LUMENES CABLE THW DEL NÚMERO 12 SOCKET PARA TUBO T8 CON BASE G13 CONECTOR PARA TUBO LED T8 CONTACTO CON PLACA BALASTRO 3 POR 14 WATTS APAGADOR DOBLE CON TAPA LAMPARA FLUORESCENTE ESPIRAL DE 23 WATTS. FOCO DULUX 2 PINES DE S13W CINTA CANELA GRIS INDUSTRIAL PAQUETE DE BATERÍAS AAA EXTENSIÓN DE 10 METROS PILA O BATERÍA RECARGABLE NÍQUEL-METAL, TAMAÑO C 4 PILAS O BATERÍAS RECARGABLES TIPO “AAA” CAJA DE CONTACTOS PARA CANALETA 4 PILAS O BATERÍAS RECARGABLES "AA" LÁMPARA DE EMERGENCIA TIPO LED PROBADOR UNIVERSAL DE PILAS CARGADOR DE PILAS BATERÍA RECARGABLE AA CABLE TELEFÓNICO CONECTOR RJ CATEGORÍA 5 CABLE ESPIRAL TELEFÓNICO CABLE DE USO RUDO CALIBRE 12 (3 POR 12) CINTA DE AISLAR DE VINIL BATERÍA ALCALINA AA DESECHABLE CAJA EXTERIOR SENCILLA CABLE DE USO RUDO CALIBRE 14 LÁMPARA COLGANTE TECNOLOGIA LED CLAVIJA CONVERTIDORA TERMO-PASTILLA 15 AMPERES TERMO-PASTILLA 20 AMPERES TERMO-PASTILLA 30 AMPERES TUBO CONDUIT PARED DELGADA ½ PULGADA CODO CONDUIT PARED DELGADA ½ PULGADA EXTENSIÓN ELÉCTRICA DE USO RUDO 2 METROS ROSETA CON JACK PLUG RJ11 BATERÍA RECARGABLE AA | Q69: NO | BM69: 68
A70: S058 | B70: 46062 | C70: Rechazado | D70: Estatal | E70: Oficialía Mayor | F70: Coordinación Administrativa (23400000030000S) | G70: 3000 Servicios generales | H70: 3500 – Servicios de Instalación, Reparación, Mantenimiento y Conservación | I70: 3511 Reparación y mantenimiento de inmuebles | J70: LPNP | K70: 0 | L70: Rechazado | M70: Rechazado | N70: Servicio- Contratacion de servicios generales | O70: 12000000 | P70: SERVICIO DE IMPERMEABILIZACIÓN DE AZOTEA EN EL INMUEBLE DENOMINADO PALACIO DE GOBIERNO. IMPERMEABILIZACIÓN DE EDIFICIOS ARCHIVO GENERAL DEL ESTADO DE MÉXICO. SERVICIO DE PINTURA DE DOS EDIFICIOS ARCHIVO GENERAL DEL ESTADO DE MÉXICO. | Q70: NO | BM70: 30
A71: S059 | B71: 46062 | C71: Concluido | D71: Estatal | E71: Secretaría de Seguridad | F71: Oficialía Mayor (20603000000000L) | G71: 3000 Servicios generales | H71: 3100 – Servicios Básicos | I71: 3131 Servicio de agua | J71: LPNP | K71: 133,632,803.97 | L71: Concluido | M71: Adjudicado | N71: Servicio- Contratacion de servicios generales | O71: 1.3205711e+08 | P71: SERVICIO DE SUMINISTRO, ABASTECIMIENTO Y DISTRIBUCIÓN DIARIO DE AGUA POTABLE EN PIPA | Q71: NO | V71: CA-0018-2026 | W71: 46065 | X71: NO APLICA | Y71: GC-Gasto Corriente | Z71: 11010101 - Ingresos propios del sector central | AA71: 133362860.59 | AB71: https://gobedomex-my.sharepoint.com/personal/coordtic_om_edomex_gob_mx/Documents/Aplicaciones/Microsoft%20Forms/Sistema%20de%20Seguimiento%20(2)%201/N%C3%BAmero%20de%20Oficio%20de%20liberaci%C3%B3n%20de%20recursos/Suficiencia%20CA-0018_JAQUELINE%20CASTA%C3%91EDA.pdf | AC71: 3131012681 | AD71: SERVICIO DE SUMINISTRO, ABASTECIMIENTO Y DISTRIBUCIÓN DIARIO DE AGUA POTABLE EN PIPA | AE71: SERVICIO | AF71: Si | AG71: No | AH71: Adjudicación Directa Presencial | AK71: ADP-009-2026 | AL71: file:///C:/Users/UsuarioGEM/Downloads/1.%20INVITACI%C3%93N%20ADP-009-2026%203131%20SERVICIO%20DE%20AGUAt.pdf | AM71: Electrónico - COMPRAMEX | AP71: 46076 | AQ71: 0.5 | AR71: 46077 | AS71: 0.58333333 | AT71: 46077 | AU71: 0.72916667 | AV71: 46077 | AX71: 46077 | AY71: 0.73958333 | AZ71: M19-INGENIERÍA CIVIL, S.A. DE C.V. | BA71: MCI150429I96 | BD71: 1.333628e+08 | BE71: CS/B/4/2026 | BF71: 46082 | BG71: 46387 | BH71: N/A | BI71: 0 | BJ71: Orlando Gutiérrez Vilchis | BL71: Adjudicado | BM71: 45
A72: S060 | B72: 46063 | C72: Rechazado | D72: Estatal | E72: Oficialía Mayor | F72: Coordinación Administrativa (23400000030000S) | G72: 3000 Servicios generales | H72: 3500 – Servicios de Instalación, Reparación, Mantenimiento y Conservación | I72: 3531 Reparación, instalación y mantenimiento de bienes informáticos, microfilmación y tecnologías de la información | J72: LPNP | K72: 0 | L72: Rechazado | M72: Rechazado | N72: Servicio- Contratacion de servicios generales | O72: 4495753 | P72: MANTENIMIENTO PREVENTIVO Y CORRECTIVO DEL SISTEMA DE DETECCIÓN DE HUMO (MARCA BOSCH) INSTALACIÓN Y CAMBIO DE BATERÍAS AL SISTEMA DE ENERGÍA ININTERRUMPIDA (UPS) MARCA EATON MODELO FE7KVA SERVICIO DE MANTENIMIENTO A LA INFRAESTRUCTURA DE TELEFONÍA DEL CENTRO DE ATENCIÓN TELEFÓNICA DEL GOBIERNO DEL ESTADO DE MÉXICO | Q72: NO | BM72: 69
A73: S061 | B73: 46063 | C73: Concluido | D73: Estatal | E73: Oficialía Mayor | F73: Coordinación Administrativa (23400000030000S) | G73: 2000 Materiales y Suministros | H73: 2700 – Vestuario, Blancos, Prendas de Protección y Artículos Deportivos | I73: 2721 Prendas de seguridad y protección personal | J73: LPNP | K73: 45404,24 | L73: Concluido | M73: Concluido | N73: Bien- Adquisición de materiales y suministros | O73: 1280682.8 | P73: BOTAS DE HULE DE SEGURIDAD, INDUSTRIAL DIELÉCTRICA. GUANTES DE PIEL PARA TRABAJO. IMPERMEABLE TIPO GABARDINA. IMPERMEABLE DE DOS PIEZAS DIELÉCTRICO. MOCHILA TÁCTICA MILITAR SENDERISMO. CHALECO PARA TOPOGRÁFIA. CHALECO DE ALTA VISIVILIDAD CON TIRAS REFLEJANTES. CARETA PROTECTORA FACIAL CON LENTES. ARNÉS PARA DESCENSO EN BARRANCOS. GUANTES DIELÉCTRICOS PROTECCIÓN HASTA 1000 V. GUANTES DE TRABAJO PARA DEMOLICIÓN. RESPIRADOR REUTILIZABLE CON ANTEOJOS DE SEGURIDAD Y FILTROS. GUANTES DE CARNAZA PARA SOLDAR PUÑO LARGO. CINTURON PORTA HERRAMIENTA. | Q73: NO | BM73: 70
A74: S062 | B74: 46063 | C74: Concluido | D74: Estatal | E74: Consejería Jurídica | F74: Coordinación Administrativa (23300001000000S) | G74: 3000 Servicios generales | H74: 3300 – Servicios Profesionales, Científicos, Técnicos y Otros Servicios | I74: 3362 Impresiones de documentos oficiales | J74: CP | K74: 126.00 | L74: concluido | M74: concluido | N74: Servicio- Contratacion de servicios generales | O74: 148862 | P74: IMPRESIÓN DE GAFETE INVEA DEL ESTADO DE MÉXICO 2026 | Q74: NO | BM74: 71
A75: S063 | B75: 46063 | C75: Rechazado | D75: Estatal | E75: Secretaría de Seguridad | F75: Oficialía Mayor (20603000000000L) | G75: 3000 Servicios generales | H75: 3200 – Servicios de Arrendamiento | I75: 3271 Arrendamiento de activos intangibles | J75: IRP | K75: 0 | L75: Rechazado | M75: Rechazado | N75: Servicio- Contratacion de servicios generales | O75: 1300000 | P75: RENOVACIÓN DEL SOFTWARE DE LA MARCA VMWARE DE LA SECRETARÍA DE SEGURIDAD | Q75: NO | BM75: 72
A76: S064 | B76: 46064 | C76: Concluido | D76: Estatal | E76: Oficialía Mayor | F76: Coordinación Administrativa (23400000030000S) | G76: 2000 Materiales y Suministros | H76: 2600-COMBUSTIBLES, LUBRICANTES Y ADITIVOS. | I76: 2611 COMBUSTIBLES, LUBRICANTES Y ADITIVOS. | K76: 130,469.10 | L76: Concluido | M76: Concluido | N76: Servicio- Contratacion de servicios generales | O76: 0 | P76: TESTIGO SOCIAL PARA LA CONTRATACIÓN DEL SERVICIO DE COMBUSTIBLES, LUBRICANTES Y ADITIVOS | Q76: NO | BM76: 73
A77: S065 | B77: 46064 | C77: Concluido | D77: Estatal | E77: Oficialía Mayor | F77: Coordinación Administrativa (23400000030000S) | G77: 3000 Servicios generales | H77: 3500 – Servicios de Instalación, Reparación, Mantenimiento y Conservación | I77: 3581 Servicios de lavandería, limpieza e higiene | K77: 130,469.10 | L77: Concluido | M77: Concluido | N77: Servicio- Contratacion de servicios generales | O77: 0 | P77: TESTIGO SOCIAL PARA LA CONTRATACIÓN DEL SERVICIO DE LAVANDERÍA, LIMPIEZA E HIGIENE | Q77: NO | BM77: 74
A78: S066 | B78: 46065 | C78: Concluido | D78: Estatal | E78: Secretaría del Campo | F78: Coordinación Administrativa | G78: 4000 Transferencias asignaciones subsidios y otras ayudas | H78: 4400 – Ayudas Sociales | I78: 4415 Apoyo a la infraestructura agropecuaria y forestal | J78: IRP | K78: 100.00 | L78: Concluido | M78: Concluido | N78: Bien- Adquisición de materiales y suministros | O78: 883000 | P78: KAIROMONA (ATRAYENTE) PARA EL MONITOREO DE LA MOSCA DEL GUSANO BARRENADOR DEL GANADO. TRAMPA ADHESIVA AZUL DE 10 POR 24 PUNTO 5 CENTIMETROS PARA EL MONITOREO DE LA MOSCA DEL GUSANO BARRENADOR DEL GANADO. | Q78: NO | BM78: 75
A79: S067 | B79: 46065 | C79: Concluido | D79: Estatal | E79: Secretaría del Campo | F79: Coordinación Administrativa | G79: 3000 Servicios generales | H79: 3300 – Servicios Profesionales, Científicos, Técnicos y Otros Servicios | I79: 3311 Servicios Profesionales, Científicos, Técnicos y Otros Servicios | J79: CP | K79: 72200 | L79: Concluido | M79: Concluido | N79: Servicio- Contratacion de servicios generales | O79: 75000 | P79: SERVICIO PROFESIONAL DE AUDITORÍA EXTERNA PARA REALIZAR TRABAJOS DE REVISIÓN, ANÁLISIS Y DICTAMINACIÓN DE ESTADOS FINANCIEROS DEL FIDEICOMISO FONDO ALIANZA PARA EL CAMPO DEL ESTADO DE MÉXICO (FACEM) | Q79: NO | BM79: 76
A80: S068 | B80: 46069 | C80: Concluido | D80: Estatal | E80: Secretaría de Cultura y Turismo | F80: Coordinación Administrativa | G80: 2000 Materiales y Suministros | H80: 2400 – Materiales y Artículos de Construcción y de Reparación | I80: 2441 Madera y productos de madera | J80: IRP | K80: 13,374.28 | L80: Concluido | M80: Concluido | N80: Bien- Adquisición de materiales y suministros | O80: 586650 | P80: VIGA DE MADERA DE PINO (10 POR 20 CENTÍMETROS) TABLA DE MADERA DE PINO (30 CENTÍMETROS POR 2.5 METROS) DECK DE MADERA DE TECA (9 CENTÍMETROS POR 1.20 METROS) DECK DE MADERA CUMARÚ (9 CENTÍMETROS POR 1.20 METROS) DUELA DE MADERA DE ENCINO AMERICANO (6 POR 90 CENTÍMETROS) DUELA DE MADERA DE ENCINO AMERICANO (7 POR 90 CENTÍMETROS) DUELA DE MADERA DE ENCINO NACIONAL (7 POR 90 CENTÍMETROS) | Q80: NO | BM80: 77
A81: S069 | B81: 46069 | C81: Concluido | D81: Estatal | E81: Secretaría de Cultura y Turismo | F81: Coordinación Administrativa | G81: 3000 Servicios generales | H81: 3800 – Servicios Oficiales | I81: 3821 Gastos de ceremonias oficiales y de orden social | J81: CP | K81: 174,333.33 | L81: Concluido | M81: Concluido | N81: Servicio- Contratacion de servicios generales | O81: 175000 | P81: CONTRATACIÓN DE EQUIPO DE SONIDO PARA EL “FESTIVAL CULTURAL QUINTO SOL, EN SU EDICIÓN XXXIX”. | Q81: NO | BM81: 78
A82: S070 | B82: 46069 | C82: Concluido | D82: Estatal | E82: Secretaría de Cultura y Turismo | F82: Coordinación Administrativa | G82: 3000 Servicios generales | H82: 3300 – Servicios Profesionales, Científicos, Técnicos y Otros Servicios | I82: 3363 Servicios de impresión de documentos oficiales | J82: CP | K82: 5,339.30 | L82: Concluido | M82: Concluido | N82: Servicio- Contratacion de servicios generales | O82: 76500 | P82: IMPRESIÓN DE CARTEL PARA EL FESTIVAL CULTURAL QUINTO SOL, EN SU EDICIÓN XXXIX. IMPRESIÓN DE LONA PARA EL FESTIVAL CULTURAL QUINTO SOL, EN SU EDICIÓN XXXIX. IMPRESIÓN DE BANNER PARA EL FESTIVAL CULTURAL QUINTO SOL, EN SU EDICIÓN XXXIX. IMPRESIÓN DE GAFETE “STAFF” PARA EL FESTIVAL CULTURAL QUINTO SOL, EN SU EDICIÓN XXXIX. IMPRESIÓN DE GAFETE “PARTICIPANTE” PARA EL FESTIVAL CULTURAL QUINTO SOL, EN SU EDICIÓN XXXIX. | Q82: NO | BM82: 79
A83: S071 | B83: 46069 | C83: Concluido | D83: Estatal | E83: Secretaría de Cultura y Turismo | F83: Coordinación Administrativa | G83: 3000 Servicios generales | H83: 3800 – Servicios Oficiales | I83: 3821 Gastos de ceremonias oficiales y de orden social | J83: CP | K83: 206.40 | L83: Concluido | M83: Concluido | N83: Servicio- Contratacion de servicios generales | O83: 367802 | P83: SERVICIO DE BOX LUNCH DE LA TEMPORADA DE CONCIERTOS 154 DE LA ORQUESTA SINFÓNICA DEL ESTADO DE MÉXICO Y LA TEMPORADA 17 DE LA ORQUESTA FILARMÓNICA DEL ESTADO DE MÉXICO. | Q83: NO | BM83: 80
A84: S072 | B84: 46069 | C84: Concluido | D84: Estatal | E84: Consejería Jurídica | F84: Coordinación Administrativa (23300001000000S) | G84: 5000 Bienes muebles inmuebles e intangibles | H84: 5400 – Vehículos y Equipo de Transporte | I84: 5411 Vehículos y equipo de transporte terrestre | J84: LPNP | K84: 1,095,074.50 | L84: Concluido | M84: Concluido | N84: Bien- Adquisición de materiales y suministros | O84: 7157349 | P84: VEHÍCULO TIPO SEDÁN 2026 CAMIONETA TIPO VAN 2026 | Q84: NO | BM84: 81
A85: S073 | B85: 46069 | C85: Rechazado | D85: Estatal | E85: Secretaría de las Mujeres | F85: Coordinación Administrativa | G85: 2000 Materiales y Suministros | H85: 2200 – Alimentos y Utensilios | I85: 2211 Productos alimenticios para personas | J85: LPNP | K85: 0 | L85: Rechazado | M85: Rechazado | N85: Bien- Adquisición de materiales y suministros | O85: 4518775 | P85: SUMINISTRO DE ABARROTES Y ALIMENTOS PARA LOS REFUGIOS DE LAS MUJERES EN SITUACIÓN DE VIOLENCIA. | Q85: NO | BM85: 82
A86: S074 | B86: 46069 | C86: Concluido | D86: Estatal | E86: Secretaría de las Mujeres | F86: Coordinación Administrativa | G86: 3000 Servicios generales | H86: 3100 – Servicios Básicos | I86: 3121 Gas | J86: LPNP | K86: 10,34 | L86: Concluido | M86: Concluido | N86: Servicio- Contratacion de servicios generales | O86: 322366.39 | P86: SUMINISTRO DE GAS L.P. PARA LOS CENTROS LIBRE DE LA SECRETARIA DE LAS MUJERES | Q86: NO | BM86: 83
A87: S075 | B87: 46069 | C87: Rechazado | D87: Estatal | E87: Secretaría de las Mujeres | F87: Coordinación Administrativa | G87: 3000 Servicios generales | H87: 3500 – Servicios de Instalación, Reparación, Mantenimiento y Conservación | I87: 3571 Reparación, instalación y mantenimiento de maquinaria, equipo industrial y diverso | J87: LPNP | K87: 0 | L87: Rechazado | M87: Rechazado | N87: Servicio- Contratacion de servicios generales | O87: 381784.88 | P87: MANTENIMIENTO PREVENTIVO Y CORRECTIVO PARA ELEVADOR DE LA SECRETARÍA DE LAS MUJERES | Q87: NO | BM87: 84
A88: S076 | B88: 46069 | C88: Rechazado | D88: Estatal | E88: Secretaría de las Mujeres | F88: Coordinación Administrativa | G88: 3000 Servicios generales | H88: 3300 – Servicios Profesionales, Científicos, Técnicos y Otros Servicios | I88: 3311 Asesorías asociadas a convenios o acuerdos | J88: CP | K88: 0 | L88: Rechazado | M88: Rechazado | N88: Servicio- Contratacion de servicios generales | O88: 163000 | P88: ASESORÍA Y REVISIÓN DE LOS PROCESOS DE NÓMINA RELATIVOS AL PERSONAL POR CONTRATO INDIVIDUAL DE TRABAJO POR TIEMPO DETERMINADO | Q88: NO | BM88: 85
A89: S077 | B89: 46069 | C89: Rechazado | D89: Estatal | E89: Secretaría de las Mujeres | F89: Coordinación Administrativa | G89: 3000 Servicios generales | H89: 3700 – Servicios de Traslado y Viáticos | I89: 3791 Otros servicios de traslado y hospedaje | J89: IRP | K89: 0 | L89: Rechazado | M89: Rechazado | N89: Servicio- Contratacion de servicios generales | O89: 751140 | P89: SERVICIO DE ESTACIONAMIENTO | Q89: NO | BM89: 86
... A98: S086 | B98: 46072 | C98: Concluido | D98: Estatal | E98: Secretaría de Finanzas | F98: Coordinación Administrativa(20700002000000S) | G98: 5000 Bienes muebles inmuebles e intangibles | H98: 5100 – Mobiliario y Equipo de Administración | I98: 5151 Bienes informáticos | J98: CP | K98: 316,218.29 | L98: concluido | M98: concluido | N98: Bien- Adquisición de materiales y suministros | O98: 232023 | P98: SUMINISTRO DE UN SISTEMA DE ENERGÍA INTERRUMPIDA (UPS) DE DOBLE CONVERSIÓN CON POTENCIA NOMINAL DE 4500 WATTS Y 5000 VA, UNA TOMA DE ENTRADA DE CORRIENTE NEMA L6-30P, DOS TOMAS DE SALIDA TIPO NEMA L6-20R, DOS TOMAS DE SALIDA TIPO NEMA L6-30R, AUTONOMÍA A PLENA CARGA DE 3.1 MINUTOS Y FACTOR DE FORMA PARA MONTAJE EN RACK. EQUIPO DE DIGITALIZACIÓN (ESCÁNER) CON ALIMENTADOR AUTOMÁTICO DE DOCUMENTOS, VELOCIDAD DE ESCANEO DE 100 PPM E INTERFAZ USB 2.0 O SUPERIOR. PROYECTOR CON TECNOLOGÍA DLP O 3LCD, BRILLO DE 3800 ANSI LÚMENES, RESOLUCIÓN NATIVA DE WXGA (1280 X 800), RELACIÓN DE ASPECTO DE 16:10, VIDA DE LA LÁMPARA DE 4000 HORAS, UN PUERTO DE ENTRADA VA Y DOS PUERTOS HDMI. SUMINISTRO DE UN EQUIPO DE CONMUTACIÓN DE DATOS (SWITCH) DE 24 PUERTOS GBE POE+ Y 4 PUERTOS SFP-10 GBE, POE POWER BUDGET DE 370 WATTS Y CAPACIDAD DE CONMUTACIÓN DE 128 GBPS. | Q98: NO | BM98: 95
A99: S087 | B99: 46071 | C99: Rechazado | D99: Estatal | E99: Oficialía Mayor | F99: Coordinación Administrativa (23400000030000S) | G99: 3000 Servicios generales | H99: 3400 – Servicios Financieros, Bancarios y Comerciales | I99: 3451 Seguros y fianzas | K99: 0 | L99: Rechazado | M99: Rechazado | N99: Servicio- Contratacion de servicios generales | O99: 0 | P99: SEGURO DE LANCHAS. SEGURO DE AERONAVES. SEGURO EMPRESARIAL. SEGURO DE MAQUINARIA PESADA. | Q99: NO | BM99: 96
A100: S088 | B100: 46071 | C100: Rechazado | D100: Estatal | E100: Oficialía Mayor | F100: Dirección General de Recursos Materiales (23400005000000L) | G100: 3000 Servicios generales | H100: 3400 – Servicios Financieros, Bancarios y Comerciales | I100: 3451 Seguros y fianzas | K100: 0 | L100: Rechazado | M100: Rechazado | N100: Servicio- Contratacion de servicios generales | O100: 0 | P100: SEGURO DE GASTOS MÉDICOS MAYORES | Q100: NO | BM100: 97
A101: S089 | B101: 46071 | C101: Rechazado | D101: Estatal | E101: Oficialía Mayor | F101: Dirección General de Recursos Materiales (23400005000000L) | G101: 3000 Servicios generales | H101: 3400 – Servicios Financieros, Bancarios y Comerciales | I101: 3451 Seguros y fianzas | K101: 0 | L101: Rechazado | M101: Rechazado | N101: Servicio- Contratacion de servicios generales | O101: 0 | P101: SEGURO DE AUTOMÓVILES. SEGURO DE VEHÍCULOS DE CARGA Y PASAJE. SEGURO DE MOTOCICLETAS. | Q101: NO | BM101: 98
A102: S090 | B102: 46071 | C102: Rechazado | D102: Estatal | E102: Oficialía Mayor | F102: Dirección General de Recursos Materiales (23400005000000L) | G102: 3000 Servicios generales | H102: 3400 – Servicios Financieros, Bancarios y Comerciales | I102: 3451 Seguros y fianzas | K102: 0 | L102: Rechazado | M102: Rechazado | N102: Servicio- Contratacion de servicios generales | O102: 0 | P102: SEGURO DE VIDA COLECTIVO SEGURO DE VIDA INSTITUCIONAL Y DE AHORRO VOLUNTARIO (SEGURO DE SEPARACIÓN, SEGURO DE RETIRO O CUALQUIER OTRA DENOMINACIÓN). | Q102: NO | BM102: 99
A103: S091 | B103: 46072 | C103: Concluido | D103: Estatal | E103: Secretaría de las Mujeres | F103: Coordinación Administrativa | G103: 3000 Servicios generales | H103: 3300 – Servicios Profesionales, Científicos, Técnicos y Otros Servicios | I103: 3992 Gastos y servicios menores | J103: CP | K103: 71.50 | L103: Concluido | M103: Concluido | N103: Servicio- Contratacion de servicios generales | O103: 200000 | P103: SUMINISTRO DE GARRAFÓN DE AGUA | Q103: NO | BM103: 100
A104: S092 | B104: 46072 | C104: Concluido | D104: Estatal | E104: Secretaría de las Mujeres | F104: Coordinación Administrativa | G104: 3000 Servicios generales | H104: 3300 – Servicios Profesionales, Científicos, Técnicos y Otros Servicios | I104: 3311 Asesorías asociadas a convenios o acuerdos | J104: CP | K104: 178,620.00 | L104: Concluido | M104: Concluido | N104: Servicio- Contratacion de servicios generales | O104: 163000 | P104: ASESORÍA Y REVISIÓN DE LOS PROCESOS DE NÓMINA RELATIVOS AL PERSONAL POR CONTRATO INDIVIDUAL DE TRABAJO POR TIEMPO DETERMINADO | Q104: NO | BM104: 101
A105: S093 | B105: 46072 | C105: Concluido | D105: Estatal | E105: Secretaría de las Mujeres | F105: Coordinación Administrativa | G105: 3000 Servicios generales | H105: 3500 – Servicios de Instalación, Reparación, Mantenimiento y Conservación | I105: 3571 Reparación, instalación y mantenimiento de maquinaria, equipo industrial y diverso | J105: LPNP | K105: 3319 | L105: Concluido | M105: Concluido | N105: Servicio- Contratacion de servicios generales | O105: 381784.88 | P105: MANTENIMIENTO PREVENTIVO Y CORRECTIVO PARA ELEVADOR DE LA SECRETARÍA DE LAS MUJERES | Q105: NO | BM105: 102
A106: S094 | B106: 46072 | C106: Concluido | D106: Estatal | E106: Secretaría de las Mujeres | F106: Coordinación Administrativa | G106: 3000 Servicios generales | H106: 3700 – Servicios de Traslado y Viáticos | I106: 3791 Otros servicios de traslado y hospedaje | J106: IRP | K106: 1,300.00 | L106: concluido | M106: concluido | N106: Servicio- Contratacion de servicios generales | O106: 751140 | P106: SERVICIO DE ESTACIONAMIENTO | Q106: NO | BM106: 103
A107: S095 | B107: 46072 | C107: Concluido | D107: Estatal | E107: Secretaría de las Mujeres | F107: Coordinación Administrativa | G107: 3000 Servicios generales | H107: 3500 – Servicios de Instalación, Reparación, Mantenimiento y Conservación | I107: 3581 Servicios de lavandería, limpieza e higiene | J107: CP | K107: 1726,8 | L107: Concluido | M107: Concluido | N107: Servicio- Contratacion de servicios generales | O107: 17662.5 | P107: SERVICIO DE SANITIZACIÓN PARA LA COORDINACIÓN DE GESTIÓN GUBERNAMENTAL | Q107: NO | BM107: 104
A108: S096 | B108: 46076 | C108: Concluido | D108: Estatal | E108: Secretaría de Bienestar | F108: Oficina del C. Srio. de Bienestar (229A00000000000) | G108: 4000 Transferencias asignaciones subsidios y otras ayudas | H108: 4400 – Ayudas Sociales | I108: 4412 Despensas | J108: LPNP | K108: 727.86 | L108: Concluido | M108: Adjudicado | N108: Bien- Adquisición de materiales y suministros | O108: 2175949676 | P108: CANASTA DE PRODUCTOS ALIMENTICIOS | Q108: NO | V108: CA-0022-2026 | W108: 46094 | X108: PAVEL RAMSES HUERTAS CABRERA | Y108: GC-Gasto Corriente | Z108: 11010101 - Ingresos propios del sector central | AA108: 2175949676 | AB108: https://gobedomex-my.sharepoint.com/personal/coordtic_om_edomex_gob_mx/Documents/Aplicaciones/Microsoft%20Forms/Sistema%20de%20Seguimiento%20(2)%201/N%C3%BAmero%20de%20Oficio%20de%20liberaci%C3%B3n%20de%20recursos/CA-0022-2026_AMIRA%20YOSELYN%20MEJIA.pdf | AC108: 4412010002 | AD108: CANASTA DE PRODUCTOS ALIMENTICIOS | AE108: PAQUETE | AF108: Si | AG108: No | AH108: Licitación Publicación Presencial | AK108: LPNP-010-2026 | AL108: https://compramex.edomex.gob.mx/compramex/public/catalogosExternos/detalleConvocatoria.xhtml | AM108: Periódico - Local y Nacional | AN108: 46105 | AO108: 0.41666667 | AP108: 46108 | AQ108: 0.41666667 | AR108: 46112 | AS108: 0.5 | AT108: 46112 | AU108: 0.54166667 | AV108: 46112 | AX108: 46112 | AY108: 0.5625 | AZ108: PRODUCTOS SEREL, S.A. DE C.V. EN PROPUESTA CONJUNTA CON COMERCIALIZADORA AGRÍCOLA Y DE BIENES LANDSMARK, S.A. DE C.V. | BA108: PSE891129GS1 , CAB830907AY5 | BD108: 2.1052172e+09 | BE108: CB/OPD/4/2026 | BF108: 46112 | BG108: 46387 | BI108: 70732509 | BJ108: DIRECCIÓN DE PROCEDIMIENTOS ADQUISITIVOS DEL SECTOR AUXILIAR Y APOYO INTERSECTORIAL | BL108: Adjudicado | BM108: 105
A109: S097 | B109: 46076 | C109: Concluido | D109: Estatal | E109: Agencia Digital del Estado de México | F109: Oficina de la o del C. Titular de la Agencia Digital del Estado de México (23800001A000000) | G109: 3000 Servicios generales | H109: 3200 – Servicios de Arrendamiento | I109: 3271 Arrendamiento de activos intangibles | J109: IRP | K109: 1,297,471.39 | L109: Concluido | M109: Concluido | N109: Servicio- Contratacion de servicios generales | O109: 1260000 | P109: SUSCRIPCIÓN A LA PLATAFORMA FONT AWESOME PLAN PRO SUSCRUPCIÓN AL SOFTWARE FIGMA PLAN ORGANIZATION PUESTO FULL SUSCRIPCIÓN A GOOGLE AI, PLAN ULTRA, PARA UN USUARIO SUSCRIPCIÓN PARA HACER USO DE LA PLATAFORMA MOTION ARRAY PLAN EVERYTHING PARA UN USUARIO SUSCRIPCIÓN A LA PLATAFORMA FREEPIK PREMIUM PARA UN USUARIO SUSCRIPCIÓN AL SOFTWARE GENIALLY INDIVIDUAL, PLAN MASTER SUSCRIPCIÓN A LA SUITE ADOBE CREATIVE CLOUD PRO PARA UN USUARIO SUSCRIPCIÓN AL SOFTWARE CANVA PLAN NEGOCIOS PARA UNA PERSONA | Q109: NO | V109: CA-0060-2026 | W109: 46091 | X109: N/A | Y109: GC-Gasto Corriente | Z109: ["11010101 - Ingresos propios del sector central"] | AA109: 1260000 | AB109: https://gobedomex-my.sharepoint.com/personal/coordtic_om_edomex_gob_mx/Documents/Aplicaciones/Microsoft%20Forms/Sistema%20de%20Seguimiento%20(2)%201/N%C3%BAmero%20de%20Oficio%20de%20liberaci%C3%B3n%20de%20recursos/Suficiencia%20CA-0060-2026_AMIRA%20YOSELYN%20MEJIA.pdf | AC109: "3271013607 3271013608 3271013609 3271013610 3271013611 3271013612 3271013613 3271013614 " | AD109: "SUSCRIPCIÓN A LA PLATAFORMA FONT AWESOME PLAN PRO. SUSCRIPCIÓN AL SOFTWARE FIGMA PLAN ORGANIZATION PUESTO FULL. SUSCRIPCIÓN A GOOGLE AI, PLAN ULTRA, PARA UN USUARIO. SUSCRIPCIÓN PARA HACER USO DE LA PLATAFORMA MOTION ARRAY PLAN EVERYTHING PARA UN USUARIO SUSCRIPCIÓN A LA PLATAFORMA FREEPIK PREMIUM PARA UN USUARIO. SUSCRIPCIÓN AL SOFWARE GENIALLY INDIVIDUAL, PLAN MASTER. SUSCRIPCIÓN A LA SUITE ADOBE CREATIVE CLOUD PRO PARA UN USUARIO SUSCRIPCIÓN AL SOFTWARE CANVA PLAN NEGOCIOS PARA UNA PERSONA. " | AE109: Servicio | AF109: No | AG109: No | BM109: 106
...

Sheet Estudio de Mercado
A2: Folio Interno de Solicitud | B2: Fecha Ingreso de Solicitud | C2: Semaforo | D2: Origen de Recurso | E2: Dependencia | F2: Centro de Costo | G2: Capitulo | H2: Concepto del Gasto | I2: Giro o Partida | J2: Tipo Contracion | K2: Valor del Estudio de Mercado | L2: Estatus del Estudio de Mercado | M2: Estado | N2: Tipo de Solicitud: | O2: Monto SABYS | P2: Descripción del bien o servicio de acuerdo a la solicitud | Q2: Contratacion Plurianual | R2: Monto 2026 | S2: Monto 2027 | T2: Monto 2028 | U2: Monto 2029
A3: F-0001-2026 | B3: 46063 | C3: =IF(L3="Rechazado", "Rechazado", IF(L3="Concluido", "Concluido", IF(AND(L3="En Proceso", TODAY()<=WORKDAY(B3,15)), "En Tiempo", IF(L3="En Proceso", "Atrasado", "")))) -> Concluido | D3: Federal | E3: Secretaría de la Contraloría | F3: Coordinación Administrativa (21800005000000S) | G3: 3000 Servicios generales | H3: 3400 – Servicios Financieros, Bancarios y Comerciales | I3: 3451 Seguros y fianzas | J3: =IF(O3="","", IFERROR( IF(VALUE(SUBSTITUTE(SUBSTITUTE(TRIM(O3),"$",""),",",""))<=0,"", IF(VALUE(SUBSTITUTE(SUBSTITUTE(TRIM(O3),"$",""),",",""))<=580000,"CP", IF(VALUE(SUBSTITUTE(SUBSTITUTE(TRIM(O3),"$",""),",",""))<=1740000,"IRP","LPNP"))), "")) -> IRP | K3: 1,234,097.32 | L3: Concluido | M3: =IFERROR(IF(OR(VLOOKUP(A3,Adjudicacion!A:N,14,0)=0, VLOOKUP(A3,Adjudicacion!A:N,14,0)=""), L3, VLOOKUP(A3,Adjudicacion!A:N,14,0)), L3) -> Adjudicado | N3: Servicio- Contratacion de servicios generales | O3: 1234097.3 | P3: ASEGURAMIENTO VEHICULAR | Q3: NO
A4: F-0002-2026 | B4: 46106 | C4: =IF(L4="Rechazado", "Rechazado", IF(L4="Concluido", "Concluido", IF(AND(L4="En Proceso", TODAY()<=WORKDAY(B4,15)), "En Tiempo", IF(L4="En Proceso", "Atrasado", "")))) -> Concluido | D4: Federal | E4: Secretaría de la Contraloría | F4: Coordinación Administrativa (21800005000000S) | G4: 2000 Materiales y Suministros | H4: 2600-COMBUSTIBLES, LUBRICANTES Y ADITIVOS. | I4: 2341 Combustibles, lubricantes, aditivos, carbón y derivados | J4: =IF(O4="","", IFERROR( IF(VALUE(SUBSTITUTE(SUBSTITUTE(TRIM(O4),"$",""),",",""))<=0,"", IF(VALUE(SUBSTITUTE(SUBSTITUTE(TRIM(O4),"$",""),",",""))<=580000,"CP", IF(VALUE(SUBSTITUTE(SUBSTITUTE(TRIM(O4),"$",""),",",""))<=1740000,"IRP","LPNP"))), "")) -> LPNP | K4: 3900000 | L4: Concluido | M4: =IFERROR(IF(OR(VLOOKUP(A4,Adjudicacion!A:N,14,0)=0, VLOOKUP(A4,Adjudicacion!A:N,14,0)=""), L4, VLOOKUP(A4,Adjudicacion!A:N,14,0)), L4) -> Adjudicado | N4: Servicio- Contratacion de servicios generales | O4: 3900000 | P4: SUMINISTRO DE COMBUSTIBLE MEDIANTE MONEDEROS ELECTRÓNICOS EN LA MODALIDAD DE CONTRATO ABIERTO | Q4: NO
A5: F-0003-2026 | B5: 46149 | C5: =IF(L5="Rechazado", "Rechazado", IF(L5="Concluido", "Concluido", IF(AND(L5="En Proceso", TODAY()<=WORKDAY(B5,15)), "En Tiempo", IF(L5="En Proceso", "Atrasado", "")))) -> Atrasado | D5: Federal | E5: Secretaría de la Contraloría | F5: Coordinación Administrativa (21800005000000S) | G5: 2000 Materiales y Suministros | H5: 2100 – Materiales de Administración, Emisión de Documentos y Artículos Oficiales | I5: 2111 Materiales y útiles de oficina | J5: =IF(O5="","", IFERROR( IF(VALUE(SUBSTITUTE(SUBSTITUTE(TRIM(O5),"$",""),",",""))<=0,"", IF(VALUE(SUBSTITUTE(SUBSTITUTE(TRIM(O5),"$",""),",",""))<=580000,"CP", IF(VALUE(SUBSTITUTE(SUBSTITUTE(TRIM(O5),"$",""),",",""))<=1740000,"IRP","LPNP"))), "")) -> CP | L5: En Proceso | M5: =IFERROR(IF(OR(VLOOKUP(A5,Adjudicacion!A:N,14,0)=0, VLOOKUP(A5,Adjudicacion!A:N,14,0)=""), L5, VLOOKUP(A5,Adjudicacion!A:N,14,0)), L5) -> En Proceso | N5: Bien- Adquisición de materiales y suministros | O5: 100280 | P5: ADQUISICIÓN DE PAPEL BOND TAMAÑO CARTA | Q5: NO
A6: F-0004-2026 | B6: 46149 | C6: =IF(L6="Rechazado", "Rechazado", IF(L6="Concluido", "Concluido", IF(AND(L6="En Proceso", TODAY()<=WORKDAY(B6,15)), "En Tiempo", IF(L6="En Proceso", "Atrasado", "")))) -> Atrasado | D6: Federal | E6: Secretaría de la Contraloría | F6: Coordinación Administrativa (21800005000000S) | G6: 2000 Materiales y Suministros | H6: 2300 – Materias Primas y Materiales de Producción y Comercialización | I6: 2381 Mercancías para su comercialización en tiendas del sector público | J6: =IF(O6="","", IFERROR( IF(VALUE(SUBSTITUTE(SUBSTITUTE(TRIM(O6),"$",""),",",""))<=0,"", IF(VALUE(SUBSTITUTE(SUBSTITUTE(TRIM(O6),"$",""),",",""))<=580000,"CP", IF(VALUE(SUBSTITUTE(SUBSTITUTE(TRIM(O6),"$",""),",",""))<=1740000,"IRP","LPNP"))), "")) -> CP | L6: En Proceso | M6: =IFERROR(IF(OR(VLOOKUP(A6,Adjudicacion!A:N,14,0)=0, VLOOKUP(A6,Adjudicacion!A:N,14,0)=""), L6, VLOOKUP(A6,Adjudicacion!A:N,14,0)), L6) -> En Proceso | N6: Bien- Adquisición de materiales y suministros | O6: 120770 | P6: ADQUISICIÓN DE MATERIALES, BIENES E INSUMOS REQUERIDOS POR EL LABORATORIO DE ANÁLISIS Y VERIFICACIÓN DE CLIDAD DE MATERIALES DE CONSTRUCCIÓN | Q6: NO
A7: F-0005-2026 | B7: 46149 | C7: =IF(L7="Rechazado", "Rechazado", IF(L7="Concluido", "Concluido", IF(AND(L7="En Proceso", TODAY()<=WORKDAY(B7,15)), "En Tiempo", IF(L7="En Proceso", "Atrasado", "")))) -> Atrasado | D7: Federal | E7: Secretaría de la Contraloría | F7: Coordinación Administrativa (21800005000000S) | G7: 3000 Servicios generales | H7: 3500 – Servicios de Instalación, Reparación, Mantenimiento y Conservación | I7: 3571 Reparación, instalación y mantenimiento de maquinaria, equipo industrial y diverso | J7: =IF(O7="","", IFERROR( IF(VALUE(SUBSTITUTE(SUBSTITUTE(TRIM(O7),"$",""),",",""))<=0,"", IF(VALUE(SUBSTITUTE(SUBSTITUTE(TRIM(O7),"$",""),",",""))<=580000,"CP", IF(VALUE(SUBSTITUTE(SUBSTITUTE(TRIM(O7),"$",""),",",""))<=1740000,"IRP","LPNP"))), "")) -> CP | L7: En Proceso | M7: =IFERROR(IF(OR(VLOOKUP(A7,Adjudicacion!A:N,14,0)=0, VLOOKUP(A7,Adjudicacion!A:N,14,0)=""), L7, VLOOKUP(A7,Adjudicacion!A:N,14,0)), L7) -> En Proceso | N7: Servicio- Contratacion de servicios generales | O7: 80800 | P7: SERVICIO DE CALIBRACIÓN A LOS EQUIPOS ESPECIALIZADOS DEL LABORATORIO DE ANÁLISIS Y VERIFICACIÓN DE CALIDAD DE MATERIALES DE CONSTRUCCIÓN | Q7: NO
A8: F-0006-2026 | B8: 46149 | C8: =IF(L8="Rechazado", "Rechazado", IF(L8="Concluido", "Concluido", IF(AND(L8="En Proceso", TODAY()<=WORKDAY(B8,15)), "En Tiempo", IF(L8="En Proceso", "Atrasado", "")))) -> Atrasado | D8: Federal | E8: Secretaría de la Contraloría | F8: Coordinación Administrativa (21800005000000S) | G8: 3000 Servicios generales | H8: 3500 – Servicios de Instalación, Reparación, Mantenimiento y Conservación | I8: 3571 Reparación, instalación y mantenimiento de maquinaria, equipo industrial y diverso | J8: =IF(O8="","", IFERROR( IF(VALUE(SUBSTITUTE(SUBSTITUTE(TRIM(O8),"$",""),",",""))<=0,"", IF(VALUE(SUBSTITUTE(SUBSTITUTE(TRIM(O8),"$",""),",",""))<=580000,"CP", IF(VALUE(SUBSTITUTE(SUBSTITUTE(TRIM(O8),"$",""),",",""))<=1740000,"IRP","LPNP"))), "")) -> CP | L8: En Proceso | M8: =IFERROR(IF(OR(VLOOKUP(A8,Adjudicacion!A:N,14,0)=0, VLOOKUP(A8,Adjudicacion!A:N,14,0)=""), L8, VLOOKUP(A8,Adjudicacion!A:N,14,0)), L8) -> En Proceso | N8: Servicio- Contratacion de servicios generales | O8: 178100 | P8: SERVICIO DE MANTENIMIENTO A LOS EQUIPOS ESPECIALIZADOS DEL LABORATORIO DE ANÁLISIS Y VERIFICACIÓN DE CALIDAD DE MATERIALES DE CONSTRUCCIÓN | Q8: NO
A9: F-0007-2026 | B9: 46150 | C9: =IF(L9="Rechazado", "Rechazado", IF(L9="Concluido", "Concluido", IF(AND(L9="En Proceso", TODAY()<=WORKDAY(B9,15)), "En Tiempo", IF(L9="En Proceso", "Atrasado", "")))) -> Rechazado | D9: Federal | E9: Consejería Jurídica | F9: Coordinación Administrativa (23300001000000S) | G9: 5000 Bienes muebles inmuebles e intangibles | H9: 5600 – Maquinaria, Otros Equipos y Herramientas | I9: 5631 Maquinaria y equipo de construcción | J9: =IF(O9="","", IFERROR( IF(VALUE(SUBSTITUTE(SUBSTITUTE(TRIM(O9),"$",""),",",""))<=0,"", IF(VALUE(SUBSTITUTE(SUBSTITUTE(TRIM(O9),"$",""),",",""))<=580000,"CP", IF(VALUE(SUBSTITUTE(SUBSTITUTE(TRIM(O9),"$",""),",",""))<=1740000,"IRP","LPNP"))), "")) -> LPNP | L9: Rechazado | M9: =IFERROR(IF(OR(VLOOKUP(A9,Adjudicacion!A:N,14,0)=0, VLOOKUP(A9,Adjudicacion!A:N,14,0)=""), L9, VLOOKUP(A9,Adjudicacion!A:N,14,0)), L9) -> Rechazado | N9: Bien- Adquisición de materiales y suministros | O9: 4120000 | P9: ADQUISICIÓN DE MAQUINARIA Y EQUIPO DE CONSTRUCCIÓN (MINICARGADOR) | Q9: NO
A10: S001 | B10: 46029 | C10: =IF(L10="Rechazado", "Rechazado", IF(L10="Concluido", "Concluido", IF(AND(L10="En Proceso", TODAY()<=WORKDAY(B10,15)), "En Tiempo", IF(L10="En Proceso", "Atrasado", "")))) -> Concluido | D10: Estatal | E10: Consejería Jurídica | F10: Coordinación Administrativa (23300001000000S) | G10: 3000 Servicios generales | H10: 3800 – Servicios Oficiales | I10: 3821 Gastos de ceremonias oficiales y de orden social | J10: =IF(O10="","", IFERROR( IF(VALUE(SUBSTITUTE(SUBSTITUTE(TRIM(O10),"$",""),",",""))<=0,"", IF(VALUE(SUBSTITUTE(SUBSTITUTE(TRIM(O10),"$",""),",",""))<=580000,"CP", IF(VALUE(SUBSTITUTE(SUBSTITUTE(TRIM(O10),"$",""),",",""))<=1740000,"IRP","LPNP"))), "")) -> LPNP | K10: 2,257,873.33 | L10: Concluido | M10: =IFERROR(IF(OR(VLOOKUP(A10,Adjudicacion!A:N,14,0)=0, VLOOKUP(A10,Adjudicacion!A:N,14,0)=""), L10, VLOOKUP(A10,Adjudicacion!A:N,14,0)), L10) -> Adjudicado | N10: Servicio- Contratacion de servicios generales | O10: 61641216 | P10: CARAVANAS ITINERANTES POR LA JUSTICIA SOCIAL | Q10: SI | R10: 78940488 | S10: 78940488 | T10: 78940488 | U10: 50234856
A11: S002 | B11: 46030 | C11: =IF(L11="Rechazado", "Rechazado", IF(L11="Concluido", "Concluido", IF(AND(L11="En Proceso", TODAY()<=WORKDAY(B11,15)), "En Tiempo", IF(L11="En Proceso", "Atrasado", "")))) -> Concluido | D11: Estatal | E11: Consejería Jurídica | F11: Coordinación Administrativa (23300001000000S) | G11: 3000 Servicios generales | H11: 3700 – Servicios de Traslado y Viáticos | I11: 3791 Otros servicios de traslado y hospedaje | J11: =IF(O11="","", IFERROR( IF(VALUE(SUBSTITUTE(SUBSTITUTE(TRIM(O11),"$",""),",",""))<=0,"", IF(VALUE(SUBSTITUTE(SUBSTITUTE(TRIM(O11),"$",""),",",""))<=580000,"CP", IF(VALUE(SUBSTITUTE(SUBSTITUTE(TRIM(O11),"$",""),",",""))<=1740000,"IRP","LPNP"))), "")) | K11: 1,003.27 | L11: Concluido | M11: =IFERROR(IF(OR(VLOOKUP(A11,Adjudicacion!A:N,14,0)=0, VLOOKUP(A11,Adjudicacion!A:N,14,0)=""), L11, VLOOKUP(A11,Adjudicacion!A:N,14,0)), L11) -> Concluido | N11: Servicio- Contratacion de servicios generales | O11: 0 | P11: SERVICIO DE ESTACIONAMIENTO PARA LA CONSEJERÍA JURÍDICA | Q11: NO
A12: S003 | B12: 46031 | C12: =IF(L12="Rechazado", "Rechazado", IF(L12="Concluido", "Concluido", IF(AND(L12="En Proceso", TODAY()<=WORKDAY(B12,15)), "En Tiempo", IF(L12="En Proceso", "Atrasado", "")))) -> Rechazado | D12: Estatal | E12: Secretaría del Agua | F12: Coordinación Administrativa (23200002000000S) | G12: 5000 Bienes muebles inmuebles e intangibles | H12: 5100 – Mobiliario y Equipo de Administración | I12: 5111 Muebles y Enceres | J12: =IF(O12="","", IFERROR( IF(VALUE(SUBSTITUTE(SUBSTITUTE(TRIM(O12),"$",""),",",""))<=0,"", IF(VALUE(SUBSTITUTE(SUBSTITUTE(TRIM(O12),"$",""),",",""))<=580000,"CP", IF(VALUE(SUBSTITUTE(SUBSTITUTE(TRIM(O12),"$",""),",",""))<=1740000,"IRP","LPNP"))), "")) -> IRP | K12: 0 | L12: Rechazado | M12: =IFERROR(IF(OR(VLOOKUP(A12,Adjudicacion!A:N,14,0)=0, VLOOKUP(A12,Adjudicacion!A:N,14,0)=""), L12, VLOOKUP(A12,Adjudicacion!A:N,14,0)), L12) -> Rechazado | N12: Bien- Adquisición de materiales y suministros | O12: 1500000 | P12: ARCHIVERO ESCRITORIO EJECUTIVO ESCRITORIO OPERATIVO SILLA EJECUTIVA SILLA SECRETARIAL ARCHIVERO ANAQUELES LIBRERO MESA OPERATIVA MESA DE TRABAJO MESA DE JUNTAS DISPENSADOR DE AGUA PERCHERO | Q12: NO
A13: S004 | B13: 46032 | C13: =IF(L13="Rechazado", "Rechazado", IF(L13="Concluido", "Concluido", IF(AND(L13="En Proceso", TODAY()<=WORKDAY(B13,15)), "En Tiempo", IF(L13="En Proceso", "Atrasado", "")))) -> Rechazado | D13: Estatal | E13: Secretaría del Agua | F13: Coordinación Administrativa (23200002000000S) | G13: 4000 Transferencias asignaciones subsidios y otras ayudas | H13: 4200 – Transferencias al Resto del Sector Público | I13: 4242 Donativos a municipios | J13: =IF(O13="","", IFERROR( IF(VALUE(SUBSTITUTE(SUBSTITUTE(TRIM(O13),"$",""),",",""))<=0,"", IF(VALUE(SUBSTITUTE(SUBSTITUTE(TRIM(O13),"$",""),",",""))<=580000,"CP", IF(VALUE(SUBSTITUTE(SUBSTITUTE(TRIM(O13),"$",""),",",""))<=1740000,"IRP","LPNP"))), "")) | K13: 0 | L13: Rechazado | M13: =IFERROR(IF(OR(VLOOKUP(A13,Adjudicacion!A:N,14,0)=0, VLOOKUP(A13,Adjudicacion!A:N,14,0)=""), L13, VLOOKUP(A13,Adjudicacion!A:N,14,0)), L13) -> Rechazado | N13: Bien- Adquisición de materiales y suministros | O13: 0 | P13: TUBERÍA DE 50.8 MILÍMETROS PARA EL PROGRAMA EMERGENTE PARA MEJORA DE INFRAESTRUCTURA EN REDES DE DISTRIBUCIÓN TUBERÍA DE 101.6 MILÍMETROS PARA EL PROGRAMA EMERGENTE PARA MEJORA DE INFRAESTRUCTURA EN REDES DE DISTRIBUCIÓN TUBERÍA DE 152.4 MILÍMETROS PARA EL PROGRAMA EMERGENTE PARA MEJORA DE INFRAESTRUCTURA EN REDES DE DISTRIBUCIÓN | Q13: NO
A14: S005 | B14: 46033 | C14: =IF(L14="Rechazado", "Rechazado", IF(L14="Concluido", "Concluido", IF(AND(L14="En Proceso", TODAY()<=WORKDAY(B14,15)), "En Tiempo", IF(L14="En Proceso", "Atrasado", "")))) -> Rechazado | D14: Estatal | E14: Secretaría del Agua | F14: Coordinación Administrativa (23200002000000S) | G14: 4000 Transferencias asignaciones subsidios y otras ayudas | H14: 4200 – Transferencias al Resto del Sector Público | I14: 4242 Donativos a municipios | J14: =IF(O14="","", IFERROR( IF(VALUE(SUBSTITUTE(SUBSTITUTE(TRIM(O14),"$",""),",",""))<=0,"", IF(VALUE(SUBSTITUTE(SUBSTITUTE(TRIM(O14),"$",""),",",""))<=580000,"CP", IF(VALUE(SUBSTITUTE(SUBSTITUTE(TRIM(O14),"$",""),",",""))<=1740000,"IRP","LPNP"))), "")) | K14: 0 | L14: Rechazado | M14: =IFERROR(IF(OR(VLOOKUP(A14,Adjudicacion!A:N,14,0)=0, VLOOKUP(A14,Adjudicacion!A:N,14,0)=""), L14, VLOOKUP(A14,Adjudicacion!A:N,14,0)), L14) -> Rechazado | N14: Bien- Adquisición de materiales y suministros | O14: 0 | P14: PAQUETE 1 INSTALACIÓN Y PUESTA EN MARCHA DE SISTEMAS DE CAPTADORES DE AGUA EN ESPACIÓS PÚBLICOS PAQUETE 2 INSTALACIÓN Y PUESTA EN MARCHA DE SISTEMAS DE CAPTADORES DE AGUA EN ESPACIÓS PÚBLICOS PAQUETE 3 INSTALACIÓN Y PUESTA EN MARCHA DE SISTEMAS DE CAPTADORES DE AGUA EN ESPACIÓS PÚBLICOS | Q14: NO
A15: S006 | B15: 46034 | C15: =IF(L15="Rechazado", "Rechazado", IF(L15="Concluido", "Concluido", IF(AND(L15="En Proceso", TODAY()<=WORKDAY(B15,15)), "En Tiempo", IF(L15="En Proceso", "Atrasado", "")))) -> Rechazado | D15: Estatal | E15: Secretaría del Agua | F15: Coordinación Administrativa (23200002000000S) | G15: 2000 Materiales y Suministros | H15: 2400 – Materiales y Artículos de Construcción y de Reparación | I15: 2411 Productos minerales no metálicos | J15: =IF(O15="","", IFERROR( IF(VALUE(SUBSTITUTE(SUBSTITUTE(TRIM(O15),"$",""),",",""))<=0,"", IF(VALUE(SUBSTITUTE(SUBSTITUTE(TRIM(O15),"$",""),",",""))<=580000,"CP", IF(VALUE(SUBSTITUTE(SUBSTITUTE(TRIM(O15),"$",""),",",""))<=1740000,"IRP","LPNP"))), "")) | K15: 0 | L15: Rechazado | M15: =IFERROR(IF(OR(VLOOKUP(A15,Adjudicacion!A:N,14,0)=0, VLOOKUP(A15,Adjudicacion!A:N,14,0)=""), L15, VLOOKUP(A15,Adjudicacion!A:N,14,0)), L15) -> Rechazado | N15: Bien- Adquisición de materiales y suministros | O15: 0 | P15: PROGRAMA DE BAÑOS ECOLÓGICOS | Q15: NO
A16: S007 | B16: 46035 | C16: =IF(L16="Rechazado", "Rechazado", IF(L16="Concluido", "Concluido", IF(AND(L16="En Proceso", TODAY()<=WORKDAY(B16,15)), "En Tiempo", IF(L16="En Proceso", "Atrasado", "")))) -> Concluido | D16: Estatal | E16: Organismos OPDS | F16: Sistema para el Desarrollo Integral de la Familia del Estado de México 200C01000000000 | G16: 4000 Transferencias asignaciones subsidios y otras ayudas | H16: 4400 – Ayudas Sociales | I16: 4412 Despensas | J16: =IF(O16="","", IFERROR( IF(VALUE(SUBSTITUTE(SUBSTITUTE(TRIM(O16),"$",""),",",""))<=0,"", IF(VALUE(SUBSTITUTE(SUBSTITUTE(TRIM(O16),"$",""),",",""))<=580000,"CP", IF(VALUE(SUBSTITUTE(SUBSTITUTE(TRIM(O16),"$",""),",",""))<=1740000,"IRP","LPNP"))), "")) -> LPNP | K16: 2,302,790,324.14 | L16: Concluido | M16: =IFERROR(IF(OR(VLOOKUP(A16,Adjudicacion!A:N,14,0)=0, VLOOKUP(A16,Adjudicacion!A:N,14,0)=""), L16, VLOOKUP(A16,Adjudicacion!A:N,14,0)), L16) -> Adjudicado | N16: Bien- Adquisición de materiales y suministros | O16: 2.3276237e+09 | P16: PAQUETE DE DESAYUNOS ESCOLARES FRÍOS PAQUETE DE ALIMENTOS DE DESAYUNOS ESCOLARES CALIENTES CANASTA DE PRODUCTOS ALIMENTICIOS | Q16: NO
A17: S007-D | B17: 46035 | C17: =IF(L17="Rechazado", "Rechazado", IF(L17="Concluido", "Concluido", IF(AND(L17="En Proceso", TODAY()<=WORKDAY(B17,15)), "En Tiempo", IF(L17="En Proceso", "Atrasado", "")))) -> Concluido | D17: Estatal | E17: Organismos OPDS | F17: Sistema para el Desarrollo Integral de la Familia del Estado de México 200C01000000000 | G17: 4000 Transferencias asignaciones subsidios y otras ayudas | H17: 4400 – Ayudas Sociales | I17: 4412 Despensas | J17: =IF(O17="","", IFERROR( IF(VALUE(SUBSTITUTE(SUBSTITUTE(TRIM(O17),"$",""),",",""))<=0,"", IF(VALUE(SUBSTITUTE(SUBSTITUTE(TRIM(O17),"$",""),",",""))<=580000,"CP", IF(VALUE(SUBSTITUTE(SUBSTITUTE(TRIM(O17),"$",""),",",""))<=1740000,"IRP","LPNP"))), "")) -> LPNP | K17: 2,302,790,324.14 | L17: Concluido | M17: =IFERROR(IF(OR(VLOOKUP(A17,Adjudicacion!A:N,14,0)=0, VLOOKUP(A17,Adjudicacion!A:N,14,0)=""), L17, VLOOKUP(A17,Adjudicacion!A:N,14,0)), L17) -> Desierta | N17: Bien- Adquisición de materiales y suministros | O17: 2.3276237e+09 | P17: PAQUETE DE DESAYUNOS ESCOLARES FRÍOS PAQUETE DE ALIMENTOS DE DESAYUNOS ESCOLARES CALIENTES CANASTA DE PRODUCTOS ALIMENTICIOS | Q17: NO
A18: S008 | B18: 46036 | C18: =IF(L18="Rechazado", "Rechazado", IF(L18="Concluido", "Concluido", IF(AND(L18="En Proceso", TODAY()<=WORKDAY(B18,15)), "En Tiempo", IF(L18="En Proceso", "Atrasado", "")))) -> Concluido | D18: Estatal | E18: Secretaría de Seguridad | F18: Coordinación Administrativa | G18: 3000 Servicios generales | H18: 3100 – Servicios Básicos | I18: 3191 Servicios de telecomunicación especializados | J18: =IF(O18="","", IFERROR( IF(VALUE(SUBSTITUTE(SUBSTITUTE(TRIM(O18),"$",""),",",""))<=0,"", IF(VALUE(SUBSTITUTE(SUBSTITUTE(TRIM(O18),"$",""),",",""))<=580000,"CP", IF(VALUE(SUBSTITUTE(SUBSTITUTE(TRIM(O18),"$",""),",",""))<=1740000,"IRP","LPNP"))), "")) -> LPNP | K18: 331,113,054.70 | L18: Concluido | M18: =IFERROR(IF(OR(VLOOKUP(A18,Adjudicacion!A:N,14,0)=0, VLOOKUP(A18,Adjudicacion!A:N,14,0)=""), L18, VLOOKUP(A18,Adjudicacion!A:N,14,0)), L18) -> Adjudicado | N18: Servicio- Contratacion de servicios generales | O18: 3.4135366e+08 | P18: SISTEMA INTEGRAL DE DISPOSITIVOS DE MONITOREO ELECTRONICO (BRAZALETES) | Q18: NO
A19: S009 | B19: 46037 | C19: =IF(L19="Rechazado", "Rechazado", IF(L19="Concluido", "Concluido", IF(AND(L19="En Proceso", TODAY()<=WORKDAY(B19,15)), "En Tiempo", IF(L19="En Proceso", "Atrasado", "")))) -> Concluido | D19: Estatal | E19: Secretaría de Seguridad | F19: Coordinación Administrativa | G19: 3000 Servicios generales | H19: 3500 – Servicios de Instalación, Reparación, Mantenimiento y Conservación | I19: 3581 Servicios de lavandería, limpieza e higiene | J19: =IF(O19="","", IFERROR( IF(VALUE(SUBSTITUTE(SUBSTITUTE(TRIM(O19),"$",""),",",""))<=0,"", IF(VALUE(SUBSTITUTE(SUBSTITUTE(TRIM(O19),"$",""),",",""))<=580000,"CP", IF(VALUE(SUBSTITUTE(SUBSTITUTE(TRIM(O19),"$",""),",",""))<=1740000,"IRP","LPNP"))), "")) -> LPNP | K19: 613,312,275.00 | L19: Concluido | M19: =IFERROR(IF(OR(VLOOKUP(A19,Adjudicacion!A:N,14,0)=0, VLOOKUP(A19,Adjudicacion!A:N,14,0)=""), L19, VLOOKUP(A19,Adjudicacion!A:N,14,0)), L19) -> Adjudicado | N19: Servicio- Contratacion de servicios generales | O19: 613312275 | P19: SERVICIO INTEGRAL DE LAVANDERIA, LIMPIEZA, DESINFECCION E HIGIENE | Q19: NO
A20: S010 | B20: 46038 | C20: =IF(L20="Rechazado", "Rechazado", IF(L20="Concluido", "Concluido", IF(AND(L20="En Proceso", TODAY()<=WORKDAY(B20,15)), "En Tiempo", IF(L20="En Proceso", "Atrasado", "")))) -> Concluido | D20: Estatal | E20: Secretaría de Seguridad | F20: Coordinación Administrativa | G20: 2000 Materiales y Suministros | H20: 2200 – Alimentos y Utensilios | I20: 2211 Productos alimenticios para personas | J20: =IF(O20="","", IFERROR( IF(VALUE(SUBSTITUTE(SUBSTITUTE(TRIM(O20),"$",""),",",""))<=0,"", IF(VALUE(SUBSTITUTE(SUBSTITUTE(TRIM(O20),"$",""),",",""))<=580000,"CP", IF(VALUE(SUBSTITUTE(SUBSTITUTE(TRIM(O20),"$",""),",",""))<=1740000,"IRP","LPNP"))), "")) -> LPNP | K20: 1,347,366,262.84 | L20: Concluido | M20: =IFERROR(IF(OR(VLOOKUP(A20,Adjudicacion!A:N,14,0)=0, VLOOKUP(A20,Adjudicacion!A:N,14,0)=""), L20, VLOOKUP(A20,Adjudicacion!A:N,14,0)), L20) -> Adjudicado | N20: Bien- Adquisición de materiales y suministros | O20: 1.3473663e+09 | P20: SUMINISTRO DE VIVERES Y ALIMENTOS PARA CONSUMO HUMANO | Q20: NO
A21: S011 | B21: 46039 | C21: =IF(L21="Rechazado", "Rechazado", IF(L21="Concluido", "Concluido", IF(AND(L21="En Proceso", TODAY()<=WORKDAY(B21,15)), "En Tiempo", IF(L21="En Proceso", "Atrasado", "")))) -> Concluido | D21: Estatal | E21: Secretaría de Cultura y Turismo | F21: Coordinación Administrativa | G21: 3000 Servicios generales | H21: 3800 – Servicios Oficiales | I21: 3841 Exposiciones y ferias | J21: =IF(O21="","", IFERROR( IF(VALUE(SUBSTITUTE(SUBSTITUTE(TRIM(O21),"$",""),",",""))<=0,"", IF(VALUE(SUBSTITUTE(SUBSTITUTE(TRIM(O21),"$",""),",",""))<=580000,"CP", IF(VALUE(SUBSTITUTE(SUBSTITUTE(TRIM(O21),"$",""),",",""))<=1740000,"IRP","LPNP"))), "")) -> IRP | K21: 1,220,900.00 | L21: Concluido | M21: =IFERROR(IF(OR(VLOOKUP(A21,Adjudicacion!A:N,14,0)=0, VLOOKUP(A21,Adjudicacion!A:N,14,0)=""), L21, VLOOKUP(A21,Adjudicacion!A:N,14,0)), L21) -> Adjudicado | N21: Servicio- Contratacion de servicios generales | O21: 1288900 | P21: SERVICIO INTEGRAL PARA LA PARTICIPACION DEL ESTADO DE MÉXICO EN LA FERIA INTERNACIONAL DEL TURISMO FITUR 2026 | Q21: NO
A22: S012 | B22: 46040 | C22: =IF(L22="Rechazado", "Rechazado", IF(L22="Concluido", "Concluido", IF(AND(L22="En Proceso", TODAY()<=WORKDAY(B22,15)), "En Tiempo", IF(L22="En Proceso", "Atrasado", "")))) -> Concluido | D22: Estatal | E22: Secretaría de Finanzas | F22: Coordinación Administrativa(20700002000000S) | G22: 3000 Servicios generales | H22: 3800 – Servicios Oficiales | I22: 3821 Gastos de ceremonias oficiales y de orden social | J22: =IF(O22="","", IFERROR( IF(VALUE(SUBSTITUTE(SUBSTITUTE(TRIM(O22),"$",""),",",""))<=0,"", IF(VALUE(SUBSTITUTE(SUBSTITUTE(TRIM(O22),"$",""),",",""))<=580000,"CP", IF(VALUE(SUBSTITUTE(SUBSTITUTE(TRIM(O22),"$",""),",",""))<=1740000,"IRP","LPNP"))), "")) -> CP | K22: 157,690.40 | L22: Concluido | M22: =IFERROR(IF(OR(VLOOKUP(A22,Adjudicacion!A:N,14,0)=0, VLOOKUP(A22,Adjudicacion!A:N,14,0)=""), L22, VLOOKUP(A22,Adjudicacion!A:N,14,0)), L22) -> Concluido | N22: Servicio- Contratacion de servicios generales | O22: 157690.4 | P22: SERVICIO DE ALIMENTOS | Q22: NO
A23: S013 | B23: 46036 | C23: =IF(L23="Rechazado", "Rechazado", IF(L23="Concluido", "Concluido", IF(AND(L23="En Proceso", TODAY()<=WORKDAY(B23,15)), "En Tiempo", IF(L23="En Proceso", "Atrasado", "")))) -> Rechazado | D23: Estatal | E23: Secretaría de las Mujeres | F23: Coordinación Administrativa | G23: 3000 Servicios generales | H23: 3990-Otros Servicios Generales | I23: 3992 Gastos y servicios menores | J23: =IF(O23="","", IFERROR( IF(VALUE(SUBSTITUTE(SUBSTITUTE(TRIM(O23),"$",""),",",""))<=0,"", IF(VALUE(SUBSTITUTE(SUBSTITUTE(TRIM(O23),"$",""),",",""))<=580000,"CP", IF(VALUE(SUBSTITUTE(SUBSTITUTE(TRIM(O23),"$",""),",",""))<=1740000,"IRP","LPNP"))), "")) | K23: 0 | L23: Rechazado | M23: =IFERROR(IF(OR(VLOOKUP(A23,Adjudicacion!A:N,14,0)=0, VLOOKUP(A23,Adjudicacion!A:N,14,0)=""), L23, VLOOKUP(A23,Adjudicacion!A:N,14,0)), L23) -> Rechazado | N23: Servicio- Contratacion de servicios generales | O23: 0 | P23: SERVICIO DE SUMINISTRO DE GARRAFÓN DE AGUA | Q23: NO
A24: S014 | B24: 46041 | C24: =IF(L24="Rechazado", "Rechazado", IF(L24="Concluido", "Concluido", IF(AND(L24="En Proceso", TODAY()<=WORKDAY(B24,15)), "En Tiempo", IF(L24="En Proceso", "Atrasado", "")))) -> Rechazado | D24: Estatal | E24: Secretaría de las Mujeres | F24: Coordinación Administrativa | G24: 3000 Servicios generales | H24: 3300 – Servicios Profesionales, Científicos, Técnicos y Otros Servicios | I24: 3311 Asesorías asociadas a convenios o acuerdos | J24: =IF(O24="","", IFERROR( IF(VALUE(SUBSTITUTE(SUBSTITUTE(TRIM(O24),"$",""),",",""))<=0,"", IF(VALUE(SUBSTITUTE(SUBSTITUTE(TRIM(O24),"$",""),",",""))<=580000,"CP", IF(VALUE(SUBSTITUTE(SUBSTITUTE(TRIM(O24),"$",""),",",""))<=1740000,"IRP","LPNP"))), "")) | K24: 0 | L24: Rechazado | M24: =IFERROR(IF(OR(VLOOKUP(A24,Adjudicacion!A:N,14,0)=0, VLOOKUP(A24,Adjudicacion!A:N,14,0)=""), L24, VLOOKUP(A24,Adjudicacion!A:N,14,0)), L24) -> Rechazado | N24: Servicio- Contratacion de servicios generales | O24: 0 | P24: ASESORÍA Y REVISIÓN DE LOS PROCESOS DE NÓMINA RELATIVOS AL PERSONAL POR CONTRATO INDIVIDUAL DE TRABAJO POR TIEMPO DETERMINADO | Q24: NO
A25: S015 | B25: 46042 | C25: =IF(L25="Rechazado", "Rechazado", IF(L25="Concluido", "Concluido", IF(AND(L25="En Proceso", TODAY()<=WORKDAY(B25,15)), "En Tiempo", IF(L25="En Proceso", "Atrasado", "")))) -> Rechazado | D25: Estatal | E25: Secretaría de las Mujeres | F25: Coordinación Administrativa | G25: 3000 Servicios generales | H25: 3700 – Servicios de Traslado y Viáticos | I25: 3791 Otros servicios de traslado y hospedaje | J25: =IF(O25="","", IFERROR( IF(VALUE(SUBSTITUTE(SUBSTITUTE(TRIM(O25),"$",""),",",""))<=0,"", IF(VALUE(SUBSTITUTE(SUBSTITUTE(TRIM(O25),"$",""),",",""))<=580000,"CP", IF(VALUE(SUBSTITUTE(SUBSTITUTE(TRIM(O25),"$",""),",",""))<=1740000,"IRP","LPNP"))), "")) | K25: 0 | L25: Rechazado | M25: =IFERROR(IF(OR(VLOOKUP(A25,Adjudicacion!A:N,14,0)=0, VLOOKUP(A25,Adjudicacion!A:N,14,0)=""), L25, VLOOKUP(A25,Adjudicacion!A:N,14,0)), L25) -> Rechazado | N25: Servicio- Contratacion de servicios generales | O25: 0 | P25: SERVICIO DE ESTACIONAMIENTO | Q25: NO
A26: S016 | B26: 46043 | C26: =IF(L26="Rechazado", "Rechazado", IF(L26="Concluido", "Concluido", IF(AND(L26="En Proceso", TODAY()<=WORKDAY(B26,15)), "En Tiempo", IF(L26="En Proceso", "Atrasado", "")))) -> Rechazado | D26: Estatal | E26: Secretaría de las Mujeres | F26: Coordinación Administrativa | G26: 5000 Bienes muebles inmuebles e intangibles | H26: 5300 – Equipo e Instrumental Médico y de Laboratorio | I26: 5311 Equipo médico y de laboratorio | J26: =IF(O26="","", IFERROR( IF(VALUE(SUBSTITUTE(SUBSTITUTE(TRIM(O26),"$",""),",",""))<=0,"", IF(VALUE(SUBSTITUTE(SUBSTITUTE(TRIM(O26),"$",""),",",""))<=580000,"CP", IF(VALUE(SUBSTITUTE(SUBSTITUTE(TRIM(O26),"$",""),",",""))<=1740000,"IRP","LPNP"))), "")) | K26: 0 | L26: Rechazado | M26: =IFERROR(IF(OR(VLOOKUP(A26,Adjudicacion!A:N,14,0)=0, VLOOKUP(A26,Adjudicacion!A:N,14,0)=""), L26, VLOOKUP(A26,Adjudicacion!A:N,14,0)), L26) -> Rechazado | N26: Bien- Adquisición de materiales y suministros | O26: 0 | P26: MESA DE EXPLORACIÓN ESTÁNDAR SILLA DE RUEDAS ANDADERA INDUSTRIAL PLEGABLE MULETAS AUXILIARES DE ALUMINIO BÁSCULA ELECTRÓNICA PARA BEBÉ | Q26: NO
A27: S017 | B27: 46036 | C27: =IF(L27="Rechazado", "Rechazado", IF(L27="Concluido", "Concluido", IF(AND(L27="En Proceso", TODAY()<=WORKDAY(B27,15)), "En Tiempo", IF(L27="En Proceso", "Atrasado", "")))) -> Rechazado | D27: Estatal | E27: Secretaría de las Mujeres | F27: Coordinación Administrativa | G27: 3000 Servicios generales | H27: 3500 – Servicios de Instalación, Reparación, Mantenimiento y Conservación | I27: 3571 Reparación, instalación y mantenimiento de maquinaria, equipo industrial y diverso | J27: =IF(O27="","", IFERROR( IF(VALUE(SUBSTITUTE(SUBSTITUTE(TRIM(O27),"$",""),",",""))<=0,"", IF(VALUE(SUBSTITUTE(SUBSTITUTE(TRIM(O27),"$",""),",",""))<=580000,"CP", IF(VALUE(SUBSTITUTE(SUBSTITUTE(TRIM(O27),"$",""),",",""))<=1740000,"IRP","LPNP"))), "")) | K27: 0 | L27: Rechazado | M27: =IFERROR(IF(OR(VLOOKUP(A27,Adjudicacion!A:N,14,0)=0, VLOOKUP(A27,Adjudicacion!A:N,14,0)=""), L27, VLOOKUP(A27,Adjudicacion!A:N,14,0)), L27) -> Rechazado | N27: Servicio- Contratacion de servicios generales | O27: 0 | P27: MANTENIMIENTO PREVENTIVO Y CORRECTIVO PARA ELEVADOR DE LA SECRETARÍA DE LAS MUJERES | Q27: No
A28: S018 | B28: 46044 | C28: =IF(L28="Rechazado", "Rechazado", IF(L28="Concluido", "Concluido", IF(AND(L28="En Proceso", TODAY()<=WORKDAY(B28,15)), "En Tiempo", IF(L28="En Proceso", "Atrasado", "")))) -> Rechazado | D28: Estatal | E28: Secretaría de las Mujeres | F28: Coordinación Administrativa | G28: 3000 Servicios generales | H28: 3100 – Servicios Básicos | I28: 3121 Gas | J28: =IF(O28="","", IFERROR( IF(VALUE(SUBSTITUTE(SUBSTITUTE(TRIM(O28),"$",""),",",""))<=0,"", IF(VALUE(SUBSTITUTE(SUBSTITUTE(TRIM(O28),"$",""),",",""))<=580000,"CP", IF(VALUE(SUBSTITUTE(SUBSTITUTE(TRIM(O28),"$",""),",",""))<=1740000,"IRP","LPNP"))), "")) | K28: 0 | L28: Rechazado | M28: =IFERROR(IF(OR(VLOOKUP(A28,Adjudicacion!A:N,14,0)=0, VLOOKUP(A28,Adjudicacion!A:N,14,0)=""), L28, VLOOKUP(A28,Adjudicacion!A:N,14,0)), L28) -> Rechazado | N28: Servicio- Contratacion de servicios generales | O28: 0 | P28: SUMINISTRO DE GAS L.P. PARA LOS CENTROS LIBRE DE LA SECRETARIA DE LAS MUJERES | Q28: NO
A29: S019 | B29: 46045 | C29: =IF(L29="Rechazado", "Rechazado", IF(L29="Concluido", "Concluido", IF(AND(L29="En Proceso", TODAY()<=WORKDAY(B29,15)), "En Tiempo", IF(L29="En Proceso", "Atrasado", "")))) -> Rechazado | D29: Estatal | E29: Secretaría de las Mujeres | F29: Coordinación Administrativa | G29: 2000 Materiales y Suministros | H29: 2500 – Productos Químicos, Farmacéuticos y de Laboratorio | I29: 2541 Materiales, accesorios y suministros médicos | J29: =IF(O29="","", IFERROR( IF(VALUE(SUBSTITUTE(SUBSTITUTE(TRIM(O29),"$",""),",",""))<=0,"", IF(VALUE(SUBSTITUTE(SUBSTITUTE(TRIM(O29),"$",""),",",""))<=580000,"CP", IF(VALUE(SUBSTITUTE(SUBSTITUTE(TRIM(O29),"$",""),",",""))<=1740000,"IRP","LPNP"))), "")) | K29: 0 | L29: Rechazado | M29: =IFERROR(IF(OR(VLOOKUP(A29,Adjudicacion!A:N,14,0)=0, VLOOKUP(A29,Adjudicacion!A:N,14,0)=""), L29, VLOOKUP(A29,Adjudicacion!A:N,14,0)), L29) -> Rechazado | N29: Bien- Adquisición de materiales y suministros | O29: 0 | P29: NEBULIZADOR ULTRASÓNICO HOSPITALARIO KIT DE NEBULIZADOR PEDIÁTRICA KIT DE NEBULIZADOR ADULTO MONITOR DE SIGNOS VITALES PORTÁTIL | Q29: NO
A30: S020 | B30: 46046 | C30: =IF(L30="Rechazado", "Rechazado", IF(L30="Concluido", "Concluido", IF(AND(L30="En Proceso", TODAY()<=WORKDAY(B30,15)), "En Tiempo", IF(L30="En Proceso", "Atrasado", "")))) -> Rechazado | D30: Estatal | E30: Secretaría de las Mujeres | F30: Coordinación Administrativa | G30: 2000 Materiales y Suministros | H30: 2500 – Productos Químicos, Farmacéuticos y de Laboratorio | I30: 2531 Medicinas y productos farmacéuticos | J30: =IF(O30="","", IFERROR( IF(VALUE(SUBSTITUTE(SUBSTITUTE(TRIM(O30),"$",""),",",""))<=0,"", IF(VALUE(SUBSTITUTE(SUBSTITUTE(TRIM(O30),"$",""),",",""))<=580000,"CP", IF(VALUE(SUBSTITUTE(SUBSTITUTE(TRIM(O30),"$",""),",",""))<=1740000,"IRP","LPNP"))), "")) | K30: 0 | L30: Rechazado | M30: =IFERROR(IF(OR(VLOOKUP(A30,Adjudicacion!A:N,14,0)=0, VLOOKUP(A30,Adjudicacion!A:N,14,0)=""), L30, VLOOKUP(A30,Adjudicacion!A:N,14,0)), L30) -> Rechazado | N30: Bien- Adquisición de materiales y suministros | O30: 0 | P30: VITAMINAS Y MINERALES GOMITAS LORATADINA 5 MILIGRAMOS JARABE LORATADINA 10 MILIGRAMOS TRAMADOL 37.5 MILIGRAMOS AMANTADINA, CLORFENAMINA Y PARACETAMOL SUSPENSIÓN INFANTIL DE 60 MILILITROS BUTILHIOSINA, PARACETAMOL, SOLUCIÓN EN GOTAS DE 20 MILILITROS LORATADINA, PARACETAMOL Y FENILEFRINA TABLETAS NAPROXENO CON PARACETAMOL SUPOSITORIOS NAPROXENO SÓDICO CON PARACETAMOL 100 MILILITROS PARACETAMOL SOLUCIÓN EN GOTAS 30 MILILITROS PARACETAMOL SOLUCIÓN INFANTIL 3.2 GRAMOS FRASCO 120 MILILITROS NAPROXENO CON PARACETAMOL TABLETAS SALBUTAMOL PARA NEBULIZAR SULFATO DE PLATA CREMA 1 G/100 G TARRO CON 30 G. DICLOFENACO GEL, TUBO DE 60 GRAMOS DICLOFENACO TABLETAS 100 MILIGRAMOS COMPLEJO B CON DICLOFENACO TABLETAS COMPLEJO B CON DICLOFENACO INYECTABLE 100,100,20,5,75 MG/3 ML. CAJA CON 3 ÁMPULAS DEXAMETASONA TABLETAS 4 MILIGRAMOS MICONAZOL EN CREMA AMBROXOL, SALBUTAMOL JARABE 120 MILILITROS NITROFURAZONA 0.2 G POMADA 85 G TUBO 85 G SALBUMATOL PARA INHALACIÓN ÁCIDO ACETILSALICÍLICO DE 500 MILIGRAMOS ANTIGRIPAL PARACETAMOL, CAFEINA, CLORHIDRATO DE FENILEFRINA MALEATO DE CLORFENAMINA 500/25/5/4 MG. CAJA CON 10 TAB. CLORFENAMINA COMPUESTA 500 MG PARACETAMOL TAB. CAJA CON 10 TAB. AMANTADINA/CLORFENAMINA/PARACETAMOL GOTAS PEDIÁTRICAS FRASCO CON 60 ML. HIOSCINA, PARACETAMOL 10/500 MG. CAJA CON 24 TAB TRAMADOL/PARACETAMOL CAJA CON 20 TABLETAS PARACETAMOL SOLUCIÓN PEDIÁTRICA FRASCO/GOTERO 15 ML 100 MG/1 ML. SOBRES DE SUERO ORAL POLVO SABOR MANZANA CAJA CON 100 SOBRES 28.3 G. CALCIO EFERVESCENTE SALBUTAMOL AEROSOL AMBROXOL /SALBUTAMOL JARABE (0,040/0,150 GRAMOS/ 100 MILILITROS) PARACETAMOL DE 500 MILIGRAMOS IODOPOVIDONA ANTISÉPTICO PARA PIEL Y MUCOSA 120 MILILITROS CLOTRIMAZOL, TUBO CON 20 GRAMOS OXIDO DE ZINC CREMA AMOXICILINA, ACIDO CLAVULÁNICO, SUSPENSIÓN DE 60 MILILITROS AMOXICILINA 500 MILIGRAMOS AMOXICILINA 7.5 GRAMOS (500 MILIGRAMOS/5 MILILITROS) COMPLEJO B TABLETAS DEXAMETASONA INYECTABLE DE 8 MILILITROS | Q30: NO
A31: S021 | B31: 46047 | C31: =IF(L31="Rechazado", "Rechazado", IF(L31="Concluido", "Concluido", IF(AND(L31="En Proceso", TODAY()<=WORKDAY(B31,15)), "En Tiempo", IF(L31="En Proceso", "Atrasado", "")))) -> Rechazado | D31: Estatal | E31: Secretaría de las Mujeres | F31: Coordinación Administrativa | G31: 2000 Materiales y Suministros | H31: 2700 – Vestuario, Blancos, Prendas de Protección y Artículos Deportivos | I31: 2721 Prendas de seguridad y protección personal | J31: =IF(O31="","", IFERROR( IF(VALUE(SUBSTITUTE(SUBSTITUTE(TRIM(O31),"$",""),",",""))<=0,"", IF(VALUE(SUBSTITUTE(SUBSTITUTE(TRIM(O31),"$",""),",",""))<=580000,"CP", IF(VALUE(SUBSTITUTE(SUBSTITUTE(TRIM(O31),"$",""),",",""))<=1740000,"IRP","LPNP"))), "")) | K31: 0 | L31: Rechazado | M31: =IFERROR(IF(OR(VLOOKUP(A31,Adjudicacion!A:N,14,0)=0, VLOOKUP(A31,Adjudicacion!A:N,14,0)=""), L31, VLOOKUP(A31,Adjudicacion!A:N,14,0)), L31) -> Rechazado | N31: Bien- Adquisición de materiales y suministros | O31: 0 | P31: SILBATO PARA BRIGADISTA OVERIK DESECHABLE CUBREZAPATO LAMPARA MANOS LIBRES PARA COMBATIR INCENDIOS MOCHILA PARA HERRAMIENTAS CINTURON DE HERRAMIENTAS, CON BOLSA PARA HERRAMIENTAS TRAJE DE BOMBERO PORTAEXTINTOR PARA EXTINTOR DE 9 KILOS CINTA DELIMIRADORA AMARILLA CON NEGRO CINTA DELIMITADORA PROHIBIDO EL PASO CINTA DELIMITADORA PRECAUCIÓN DETECTOR DE HUMO CON ALARMA DETECTOR DE GAS NATURAL Y GAS L.P. BATA DE TRABAJO | Q31: NO
A32: S022 | B32: 46048 | C32: =IF(L32="Rechazado", "Rechazado", IF(L32="Concluido", "Concluido", IF(AND(L32="En Proceso", TODAY()<=WORKDAY(B32,15)), "En Tiempo", IF(L32="En Proceso", "Atrasado", "")))) -> Rechazado | D32: Estatal | E32: Secretaría de las Mujeres | F32: Coordinación Administrativa | G32: 2000 Materiales y Suministros | H32: 2500 – Productos Químicos, Farmacéuticos y de Laboratorio | I32: 2541 Materiales, accesorios y suministros médicos | J32: =IF(O32="","", IFERROR( IF(VALUE(SUBSTITUTE(SUBSTITUTE(TRIM(O32),"$",""),",",""))<=0,"", IF(VALUE(SUBSTITUTE(SUBSTITUTE(TRIM(O32),"$",""),",",""))<=580000,"CP", IF(VALUE(SUBSTITUTE(SUBSTITUTE(TRIM(O32),"$",""),",",""))<=1740000,"IRP","LPNP"))), "")) | K32: 0 | L32: Rechazado | M32: =IFERROR(IF(OR(VLOOKUP(A32,Adjudicacion!A:N,14,0)=0, VLOOKUP(A32,Adjudicacion!A:N,14,0)=""), L32, VLOOKUP(A32,Adjudicacion!A:N,14,0)), L32) -> Rechazado | N32: Bien- Adquisición de materiales y suministros | O32: 0 | P32: CUBREBOCAS TIPO MASCARILLA 5 CAPAS KN95 CUBREBOCAS TRICAPA, CAJA BAUMANÓMETRO DIGITAL GLUCÓMETRO OXÍMETRO TORUNDA DE ALGODÓN VENDA ELÁSTICA DE 5 CENTÍMETROS AGUA OXIGENADA DE 480 MILILITROS ESTETOSCOPIO DOBLE SUMINISTROS PARA BOTIQUÍN ALCOHOL ETÍLICO DE 250 MILILITROS GUANTES DE LÁTEX SABANAS DESECHABLES AZUL PARA CAMILLA TERMÓMETRO DIGITAL TIPO PISTOLA VENDA ELÁSTICA DE 7.5 CENTÍMETROS BOTIQUÍN PORTÁTIL GASA ESTÉRIL DE 10 POR 10 CENTÍMETROS CINTA MICROPOROSA COLOR PIEL CINTA 5CM X 9.1 MT. VENDITAS TRANSPIEL SURTIDAS VENDA ELÁSTICA DE 10 CENTÍMETROS ABATELENGUAS COLLARÍN DE INMOVILIZACIÓN AJUSTABLE TIRAS REACTIVAS Y LANCETAS | Q32: NO
A33: S023 | B33: 46049 | C33: =IF(L33="Rechazado", "Rechazado", IF(L33="Concluido", "Concluido", IF(AND(L33="En Proceso", TODAY()<=WORKDAY(B33,15)), "En Tiempo", IF(L33="En Proceso", "Atrasado", "")))) -> Rechazado | D33: Estatal | E33: Secretaría de las Mujeres | F33: Coordinación Administrativa | G33: 2000 Materiales y Suministros | H33: 2700 – Vestuario, Blancos, Prendas de Protección y Artículos Deportivos | I33: 2721 Prendas de seguridad y protección personal | J33: =IF(O33="","", IFERROR( IF(VALUE(SUBSTITUTE(SUBSTITUTE(TRIM(O33),"$",""),",",""))<=0,"", IF(VALUE(SUBSTITUTE(SUBSTITUTE(TRIM(O33),"$",""),",",""))<=580000,"CP", IF(VALUE(SUBSTITUTE(SUBSTITUTE(TRIM(O33),"$",""),",",""))<=1740000,"IRP","LPNP"))), "")) | K33: 0 | L33: Rechazado | M33: =IFERROR(IF(OR(VLOOKUP(A33,Adjudicacion!A:N,14,0)=0, VLOOKUP(A33,Adjudicacion!A:N,14,0)=""), L33, VLOOKUP(A33,Adjudicacion!A:N,14,0)), L33) -> Rechazado | N33: Bien- Adquisición de materiales y suministros | O33: 0 | P33: CHALECO DE SEGURIDAD CASCO PROTECTOR LENTES DE PROTECCIÓN GUANTE DE CARNAZA ZAPATO INDUSTRIAL CON CASQUILLO DIELÉCTRICO GUANTES PARA COMBATIENTE DE INCENDIO CINTURON FAJA ARNÉS DE SEGURIDAD ANTICAIDAS CON CINCO ANILLOS LÍNEA DE VIDA GUANTES DIELÉCTRICOS PROTECCIÓN HASTA 1000 V. | Q33: NO
A34: S024 | B34: 46050 | C34: =IF(L34="Rechazado", "Rechazado", IF(L34="Concluido", "Concluido", IF(AND(L34="En Proceso", TODAY()<=WORKDAY(B34,15)), "En Tiempo", IF(L34="En Proceso", "Atrasado", "")))) -> Concluido | D34: Estatal | E34: Oficialía Mayor | F34: Coordinación Administrativa (23400000030000S) | G34: 3000 Servicios generales | H34: 3200 – Servicios de Arrendamiento | I34: 3251 Arrendamiento de vehículos | J34: =IF(O34="","", IFERROR( IF(VALUE(SUBSTITUTE(SUBSTITUTE(TRIM(O34),"$",""),",",""))<=0,"", IF(VALUE(SUBSTITUTE(SUBSTITUTE(TRIM(O34),"$",""),",",""))<=580000,"CP", IF(VALUE(SUBSTITUTE(SUBSTITUTE(TRIM(O34),"$",""),",",""))<=1740000,"IRP","LPNP"))), "")) -> LPNP | K34: 59,918,597.64 | L34: Concluido | M34: =IFERROR(IF(OR(VLOOKUP(A34,Adjudicacion!A:N,14,0)=0, VLOOKUP(A34,Adjudicacion!A:N,14,0)=""), L34, VLOOKUP(A34,Adjudicacion!A:N,14,0)), L34) -> Adjudicado | N34: Servicio- Contratacion de servicios generales | O34: 67808036 | P34: RENTA DE AUTOBUSES | Q34: NO
A35: S025 | B35: 46051 | C35: =IF(L35="Rechazado", "Rechazado", IF(L35="Concluido", "Concluido", IF(AND(L35="En Proceso", TODAY()<=WORKDAY(B35,15)), "En Tiempo", IF(L35="En Proceso", "Atrasado", "")))) -> Concluido | D35: Estatal | E35: Secretaría de Bienestar | F35: Coordinación Administrativa | G35: 4000 Transferencias asignaciones subsidios y otras ayudas | H35: 4400 – Ayudas Sociales | I35: 4413 Gastos relacionados con actividades culturales, deportivas y de ayuda extraordinaria | J35: =IF(O35="","", IFERROR( IF(VALUE(SUBSTITUTE(SUBSTITUTE(TRIM(O35),"$",""),",",""))<=0,"", IF(VALUE(SUBSTITUTE(SUBSTITUTE(TRIM(O35),"$",""),",",""))<=580000,"CP", IF(VALUE(SUBSTITUTE(SUBSTITUTE(TRIM(O35),"$",""),",",""))<=1740000,"IRP","LPNP"))), "")) -> LPNP | K35: 388,157,000.00 | L35: Concluido | M35: =IFERROR(IF(OR(VLOOKUP(A35,Adjudicacion!A:N,14,0)=0, VLOOKUP(A35,Adjudicacion!A:N,14,0)=""), L35, VLOOKUP(A35,Adjudicacion!A:N,14,0)), L35) -> Adjudicado | N35: Servicio- Contratacion de servicios generales | O35: 352850190 | P35: SERVICIO DE EMISIÓN DE TARJETAS PERSONALIZADAS QUE SIRVA COMO MEDIO DE ACCESO AL APOYO MONETARIO Y DE SERVICIOS QUE OTORGA EL PROGRAMA DE DESARROLLO SOCIAL "MUJERES CON BIENESTAR" | Q35: NO
A36: S026 | B36: 46052 | C36: =IF(L36="Rechazado", "Rechazado", IF(L36="Concluido", "Concluido", IF(AND(L36="En Proceso", TODAY()<=WORKDAY(B36,15)), "En Tiempo", IF(L36="En Proceso", "Atrasado", "")))) -> Concluido | D36: Estatal | E36: Secretaría de Educación, Ciencia, Tecnología e Innovación | F36: Coordinación Administrativa | G36: 3000 Servicios generales | H36: 3800 – Servicios Oficiales | I36: 3821 Gastos de ceremonias oficiales y de orden social | J36: =IF(O36="","", IFERROR( IF(VALUE(SUBSTITUTE(SUBSTITUTE(TRIM(O36),"$",""),",",""))<=0,"", IF(VALUE(SUBSTITUTE(SUBSTITUTE(TRIM(O36),"$",""),",",""))<=580000,"CP", IF(VALUE(SUBSTITUTE(SUBSTITUTE(TRIM(O36),"$",""),",",""))<=1740000,"IRP","LPNP"))), "")) -> LPNP | K36: 3,993,939.17 | L36: Concluido | M36: =IFERROR(IF(OR(VLOOKUP(A36,Adjudicacion!A:N,14,0)=0, VLOOKUP(A36,Adjudicacion!A:N,14,0)=""), L36, VLOOKUP(A36,Adjudicacion!A:N,14,0)), L36) -> Adjudicado | N36: Servicio- Contratacion de servicios generales | O36: 4000000 | P36: SERVICIO INTEGRAL PARA LA ORGANIZACIÓN Y EJECUCIÓN DE LA "PRESEA ESTADO DE MÉXICO" 2025 | Q36: NO
A37: S027 | B37: 46053 | C37: =IF(L37="Rechazado", "Rechazado", IF(L37="Concluido", "Concluido", IF(AND(L37="En Proceso", TODAY()<=WORKDAY(B37,15)), "En Tiempo", IF(L37="En Proceso", "Atrasado", "")))) -> Concluido | D37: Estatal | E37: Secretaría de Cultura y Turismo | F37: Coordinación Administrativa | G37: 3000 Servicios generales | H37: 3800 – Servicios Oficiales | I37: 3841 Exposiciones y ferias | J37: =IF(O37="","", IFERROR( IF(VALUE(SUBSTITUTE(SUBSTITUTE(TRIM(O37),"$",""),",",""))<=0,"", IF(VALUE(SUBSTITUTE(SUBSTITUTE(TRIM(O37),"$",""),",",""))<=580000,"CP", IF(VALUE(SUBSTITUTE(SUBSTITUTE(TRIM(O37),"$",""),",",""))<=1740000,"IRP","LPNP"))), "")) -> CP | K37: 576,666.76 | L37: Concluido | M37: =IFERROR(IF(OR(VLOOKUP(A37,Adjudicacion!A:N,14,0)=0, VLOOKUP(A37,Adjudicacion!A:N,14,0)=""), L37, VLOOKUP(A37,Adjudicacion!A:N,14,0)), L37) -> Concluido | N37: Servicio- Contratacion de servicios generales | O37: 580000 | P37: SERVICIO INTEGRAL PARA LA "EXPO FERIA TEQUIXQUIAC 206" | Q37: NO
A38: S028 | B38: 46054 | C38: =IF(L38="Rechazado", "Rechazado", IF(L38="Concluido", "Concluido", IF(AND(L38="En Proceso", TODAY()<=WORKDAY(B38,15)), "En Tiempo", IF(L38="En Proceso", "Atrasado", "")))) -> Concluido | D38: Estatal | E38: Oficialía Mayor | F38: Coordinación Administrativa (23400000030000S) | G38: 3000 Servicios generales | H38: 3300 – Servicios Profesionales, Científicos, Técnicos y Otros Servicios | I38: 3341 Capacitación | J38: =IF(O38="","", IFERROR( IF(VALUE(SUBSTITUTE(SUBSTITUTE(TRIM(O38),"$",""),",",""))<=0,"", IF(VALUE(SUBSTITUTE(SUBSTITUTE(TRIM(O38),"$",""),",",""))<=580000,"CP", IF(VALUE(SUBSTITUTE(SUBSTITUTE(TRIM(O38),"$",""),",",""))<=1740000,"IRP","LPNP"))), "")) -> CP | K38: 392,354.01 | L38: Concluido | M38: =IFERROR(IF(OR(VLOOKUP(A38,Adjudicacion!A:N,14,0)=0, VLOOKUP(A38,Adjudicacion!A:N,14,0)=""), L38, VLOOKUP(A38,Adjudicacion!A:N,14,0)), L38) -> Concluido | N38: Servicio- Contratacion de servicios generales | O38: 500000 | P38: ENTRENAMIENTO DE EXTINCIÓN CONTRA INCENDIOS (HELICOPTER AERIAL FIREFIGHTING TRAINING) | Q38: NO
A39: S029 | B39: 46055 | C39: =IF(L39="Rechazado", "Rechazado", IF(L39="Concluido", "Concluido", IF(AND(L39="En Proceso", TODAY()<=WORKDAY(B39,15)), "En Tiempo", IF(L39="En Proceso", "Atrasado", "")))) -> Concluido | D39: Estatal | E39: Secretaría de Salud | F39: Coordinación Administrativa ( 20800001000000S ) | G39: 3000 Servicios generales | H39: 3700 – Servicios de Traslado y Viáticos | I39: 3791 Otros servicios de traslado y hospedaje | J39: =IF(O39="","", IFERROR( IF(VALUE(SUBSTITUTE(SUBSTITUTE(TRIM(O39),"$",""),",",""))<=0,"", IF(VALUE(SUBSTITUTE(SUBSTITUTE(TRIM(O39),"$",""),",",""))<=580000,"CP", IF(VALUE(SUBSTITUTE(SUBSTITUTE(TRIM(O39),"$",""),",",""))<=1740000,"IRP","LPNP"))), "")) -> CP | K39: 965.51 | L39: Concluido | M39: =IFERROR(IF(OR(VLOOKUP(A39,Adjudicacion!A:N,14,0)=0, VLOOKUP(A39,Adjudicacion!A:N,14,0)=""), L39, VLOOKUP(A39,Adjudicacion!A:N,14,0)), L39) -> Concluido | N39: Servicio- Contratacion de servicios generales | O39: 117000 | P39: SERVICIO DE ESTACIONAMIENTO | Q39: NO
A40: S030 | B40: 46056 | C40: =IF(L40="Rechazado", "Rechazado", IF(L40="Concluido", "Concluido", IF(AND(L40="En Proceso", TODAY()<=WORKDAY(B40,15)), "En Tiempo", IF(L40="En Proceso", "Atrasado", "")))) -> Concluido | D40: Estatal | E40: Oficialía Mayor | F40: Coordinación Administrativa (23400000030000S) | G40: 3000 Servicios generales | H40: 3200 – Servicios de Arrendamiento | I40: 3251 Arrendamiento de vehículos | J40: =IF(O40="","", IFERROR( IF(VALUE(SUBSTITUTE(SUBSTITUTE(TRIM(O40),"$",""),",",""))<=0,"", IF(VALUE(SUBSTITUTE(SUBSTITUTE(TRIM(O40),"$",""),",",""))<=580000,"CP", IF(VALUE(SUBSTITUTE(SUBSTITUTE(TRIM(O40),"$",""),",",""))<=1740000,"IRP","LPNP"))), "")) -> CP | K40: 580,000.00 | L40: Concluido | M40: =IFERROR(IF(OR(VLOOKUP(A40,Adjudicacion!A:N,14,0)=0, VLOOKUP(A40,Adjudicacion!A:N,14,0)=""), L40, VLOOKUP(A40,Adjudicacion!A:N,14,0)), L40) -> Concluido | N40: Servicio- Contratacion de servicios generales | O40: 580000 | P40: SERVICIO DE RENTA DE AUTOBUSES PARA EL TRASLADO DEL PERSONAL. | Q40: NO
A41: S031 | B41: 46057 | C41: =IF(L41="Rechazado", "Rechazado", IF(L41="Concluido", "Concluido", IF(AND(L41="En Proceso", TODAY()<=WORKDAY(B41,15)), "En Tiempo", IF(L41="En Proceso", "Atrasado", "")))) -> Rechazado | D41: Estatal | E41: Consejería Jurídica | F41: Coordinación Administrativa (23300001000000S) | G41: 3000 Servicios generales | H41: 3800 – Servicios Oficiales | I41: 3821 Gastos de ceremonias oficiales y de orden social | J41: =IF(O41="","", IFERROR( IF(VALUE(SUBSTITUTE(SUBSTITUTE(TRIM(O41),"$",""),",",""))<=0,"", IF(VALUE(SUBSTITUTE(SUBSTITUTE(TRIM(O41),"$",""),",",""))<=580000,"CP", IF(VALUE(SUBSTITUTE(SUBSTITUTE(TRIM(O41),"$",""),",",""))<=1740000,"IRP","LPNP"))), "")) | K41: 0 | L41: Rechazado | M41: =IFERROR(IF(OR(VLOOKUP(A41,Adjudicacion!A:N,14,0)=0, VLOOKUP(A41,Adjudicacion!A:N,14,0)=""), L41, VLOOKUP(A41,Adjudicacion!A:N,14,0)), L41) -> Rechazado | N41: Servicio- Contratacion de servicios generales | O41: 0 | P41: ALCANCE A OFICIO DE CARAVANAS ITINERANTES | Q41: NO
A42: S032 | B42: 46050 | C42: =IF(L42="Rechazado", "Rechazado", IF(L42="Concluido", "Concluido", IF(AND(L42="En Proceso", TODAY()<=WORKDAY(B42,15)), "En Tiempo", IF(L42="En Proceso", "Atrasado", "")))) -> Concluido | D42: Estatal | E42: Secretaría de Finanzas | F42: Coordinación Administrativa(20700002000000S) | G42: 3000 Servicios generales | H42: 3300 – Servicios Profesionales, Científicos, Técnicos y Otros Servicios | I42: 3361 Servicios de apoyo administrativo y fotocopiado | J42: =IF(O42="","", IFERROR( IF(VALUE(SUBSTITUTE(SUBSTITUTE(TRIM(O42),"$",""),",",""))<=0,"", IF(VALUE(SUBSTITUTE(SUBSTITUTE(TRIM(O42),"$",""),",",""))<=580000,"CP", IF(VALUE(SUBSTITUTE(SUBSTITUTE(TRIM(O42),"$",""),",",""))<=1740000,"IRP","LPNP"))), "")) -> CP | K42: 561,541.50 | L42: Concluido | M42: =IFERROR(IF(OR(VLOOKUP(A42,Adjudicacion!A:N,14,0)=0, VLOOKUP(A42,Adjudicacion!A:N,14,0)=""), L42, VLOOKUP(A42,Adjudicacion!A:N,14,0)), L42) -> Concluido | N42: Servicio- Contratacion de servicios generales | O42: 580000 | P42: ENCUADERNACIÓN DE LA CUENTA PÚBLICA DEL GOBIERNO DEL ESTADO DE MÉXICO 2025 IMPRESIÓN Y ENCUADERNACIÓN DEL MANUAL ÚNICO DE CONTABILIDAD GUBERNAMENTAL 2026 (VIGÉSIMA QUINTA EDICIÓN) | Q42: NO
A43: S033 | B43: 46050 | C43: =IF(L43="Rechazado", "Rechazado", IF(L43="Concluido", "Concluido", IF(AND(L43="En Proceso", TODAY()<=WORKDAY(B43,15)), "En Tiempo", IF(L43="En Proceso", "Atrasado", "")))) -> Concluido | D43: Estatal | E43: Secretaría de Finanzas | F43: DIRECCIÓN DE ADMINISTRACIÓN Y SERVICIOS GENERALES | G43: 2000 Materiales y Suministros | H43: 2100 – Materiales de Administración, Emisión de Documentos y Artículos Oficiales | I43: 2171 Material didáctico | J43: =IF(O43="","", IFERROR( IF(VALUE(SUBSTITUTE(SUBSTITUTE(TRIM(O43),"$",""),",",""))<=0,"", IF(VALUE(SUBSTITUTE(SUBSTITUTE(TRIM(O43),"$",""),",",""))<=580000,"CP", IF(VALUE(SUBSTITUTE(SUBSTITUTE(TRIM(O43),"$",""),",",""))<=1740000,"IRP","LPNP"))), "")) -> CP | K43: 495.00 | L43: Concluido | M43: =IFERROR(IF(OR(VLOOKUP(A43,Adjudicacion!A:N,14,0)=0, VLOOKUP(A43,Adjudicacion!A:N,14,0)=""), L43, VLOOKUP(A43,Adjudicacion!A:N,14,0)), L43) -> Concluido | N43: Bien- Adquisición de materiales y suministros | O43: 263658 | P43: FISCO AGENDA 2026 | Q43: NO
A44: S034 | B44: 46050 | C44: =IF(L44="Rechazado", "Rechazado", IF(L44="Concluido", "Concluido", IF(AND(L44="En Proceso", TODAY()<=WORKDAY(B44,15)), "En Tiempo", IF(L44="En Proceso", "Atrasado", "")))) -> Concluido | D44: Estatal | E44: Secretaría de Finanzas | F44: DIRECCIÓN DE ADMINISTRACIÓN Y SERVICIOS GENERALES | G44: 3000 Servicios generales | H44: 3900 – Otros Servicios Generales | I44: 3992 Gastos y servicios menores | J44: =IF(O44="","", IFERROR( IF(VALUE(SUBSTITUTE(SUBSTITUTE(TRIM(O44),"$",""),",",""))<=0,"", IF(VALUE(SUBSTITUTE(SUBSTITUTE(TRIM(O44),"$",""),",",""))<=580000,"CP", IF(VALUE(SUBSTITUTE(SUBSTITUTE(TRIM(O44),"$",""),",",""))<=1740000,"IRP","LPNP"))), "")) -> CP | K44: 71.50 | L44: Concluido | M44: =IFERROR(IF(OR(VLOOKUP(A44,Adjudicacion!A:N,14,0)=0, VLOOKUP(A44,Adjudicacion!A:N,14,0)=""), L44, VLOOKUP(A44,Adjudicacion!A:N,14,0)), L44) -> Concluido | N44: Servicio- Contratacion de servicios generales | O44: 324788 | P44: SERVICIO DE GARRAFONES DE AGUA PARA LA DIRECCIÓN GENERAL DE RECAUDACIÓN | Q44: NO
A45: S035 | B45: 46050 | C45: =IF(L45="Rechazado", "Rechazado", IF(L45="Concluido", "Concluido", IF(AND(L45="En Proceso", TODAY()<=WORKDAY(B45,15)), "En Tiempo", IF(L45="En Proceso", "Atrasado", "")))) -> Concluido | D45: Estatal | E45: Secretaría de Finanzas | F45: DIRECCIÓN DE ADMINISTRACIÓN Y SERVICIOS GENERALES | G45: 3000 Servicios generales | H45: 3500 – Servicios de Instalación, Reparación, Mantenimiento y Conservación | I45: 3591 Servicios de fumigación | J45: =IF(O45="","", IFERROR( IF(VALUE(SUBSTITUTE(SUBSTITUTE(TRIM(O45),"$",""),",",""))<=0,"", IF(VALUE(SUBSTITUTE(SUBSTITUTE(TRIM(O45),"$",""),",",""))<=580000,"CP", IF(VALUE(SUBSTITUTE(SUBSTITUTE(TRIM(O45),"$",""),",",""))<=1740000,"IRP","LPNP"))), "")) -> CP | K45: 31,764.23 | L45: Concluido | M45: =IFERROR(IF(OR(VLOOKUP(A45,Adjudicacion!A:N,14,0)=0, VLOOKUP(A45,Adjudicacion!A:N,14,0)=""), L45, VLOOKUP(A45,Adjudicacion!A:N,14,0)), L45) -> Concluido | N45: Servicio- Contratacion de servicios generales | O45: 398860 | P45: SERVICIO DE FUMIGACIÓN Y CONTROL DE PLAGAS PARA DIRECCIÓN GENERAL DE RECAUDACIÓN | Q45: NO
A46: S036 | B46: 46050 | C46: =IF(L46="Rechazado", "Rechazado", IF(L46="Concluido", "Concluido", IF(AND(L46="En Proceso", TODAY()<=WORKDAY(B46,15)), "En Tiempo", IF(L46="En Proceso", "Atrasado", "")))) -> Concluido | D46: Estatal | E46: Secretaría de Finanzas | F46: DIRECCIÓN DE ADMINISTRACIÓN Y SERVICIOS GENERALES | G46: 2000 Materiales y Suministros | H46: 2100 – Materiales de Administración, Emisión de Documentos y Artículos Oficiales | I46: 2171 Material didáctico | J46: =IF(O46="","", IFERROR( IF(VALUE(SUBSTITUTE(SUBSTITUTE(TRIM(O46),"$",""),",",""))<=0,"", IF(VALUE(SUBSTITUTE(SUBSTITUTE(TRIM(O46),"$",""),",",""))<=580000,"CP", IF(VALUE(SUBSTITUTE(SUBSTITUTE(TRIM(O46),"$",""),",",""))<=1740000,"IRP","LPNP"))), "")) -> CP | K46: 2,550.00 | L46: Concluido | M46: =IFERROR(IF(OR(VLOOKUP(A46,Adjudicacion!A:N,14,0)=0, VLOOKUP(A46,Adjudicacion!A:N,14,0)=""), L46, VLOOKUP(A46,Adjudicacion!A:N,14,0)), L46) -> Concluido | N46: Bien- Adquisición de materiales y suministros | O46: 263658 | P46: MULTI AGENDA FISCAL Y COMPLEMENTO 2026 | Q46: NO
A47: S037 | B47: 46051 | C47: =IF(L47="Rechazado", "Rechazado", IF(L47="Concluido", "Concluido", IF(AND(L47="En Proceso", TODAY()<=WORKDAY(B47,15)), "En Tiempo", IF(L47="En Proceso", "Atrasado", "")))) -> Concluido | D47: Estatal | E47: Oficialía Mayor | F47: COORDINACIÓN ADMINISTRATIVA | G47: 3000 Servicios generales | H47: 3300 – Servicios Profesionales, Científicos, Técnicos y Otros Servicios | I47: 3361 Servicios de apoyo administrativo y fotocopiado | J47: =IF(O47="","", IFERROR( IF(VALUE(SUBSTITUTE(SUBSTITUTE(TRIM(O47),"$",""),",",""))<=0,"", IF(VALUE(SUBSTITUTE(SUBSTITUTE(TRIM(O47),"$",""),",",""))<=580000,"CP", IF(VALUE(SUBSTITUTE(SUBSTITUTE(TRIM(O47),"$",""),",",""))<=1740000,"IRP","LPNP"))), "")) | K47: 65,244,589.32 | L47: Concluido | M47: =IFERROR(IF(OR(VLOOKUP(A47,Adjudicacion!A:N,14,0)=0, VLOOKUP(A47,Adjudicacion!A:N,14,0)=""), L47, VLOOKUP(A47,Adjudicacion!A:N,14,0)), L47) -> Adjudicado | N47: Servicio- Contratacion de servicios generales | O47: 0 | P47: CONTRATACIÓN DE SERVICIOS DE FOTOCOPIADO, IMPRESIÓN Y DIGITALIZACIÓN PARA LAS DEPENDENCIAS, ORGANISMOS AUXILIARES, ORGANISMOS AUTÓNOMOS Y TRIBUNALES ADMINISTRATIVOS DEL PODER EJECUTIVO DEL ESTADO DE MÉXICO. | Q47: NO
A48: S038 | B48: 46051 | C48: =IF(L48="Rechazado", "Rechazado", IF(L48="Concluido", "Concluido", IF(AND(L48="En Proceso", TODAY()<=WORKDAY(B48,15)), "En Tiempo", IF(L48="En Proceso", "Atrasado", "")))) -> Concluido | D48: Estatal | E48: Oficialía Mayor | F48: COORDINACIÓN ADMINISTRATIVA | G48: 3000 Servicios generales | H48: 3800 – Servicios Oficiales | I48: 3821 Gastos de ceremonias oficiales y de orden social | J48: =IF(O48="","", IFERROR( IF(VALUE(SUBSTITUTE(SUBSTITUTE(TRIM(O48),"$",""),",",""))<=0,"", IF(VALUE(SUBSTITUTE(SUBSTITUTE(TRIM(O48),"$",""),",",""))<=580000,"CP", IF(VALUE(SUBSTITUTE(SUBSTITUTE(TRIM(O48),"$",""),",",""))<=1740000,"IRP","LPNP"))), "")) | K48: 315,136.95 | L48: Concluido | M48: =IFERROR(IF(OR(VLOOKUP(A48,Adjudicacion!A:N,14,0)=0, VLOOKUP(A48,Adjudicacion!A:N,14,0)=""), L48, VLOOKUP(A48,Adjudicacion!A:N,14,0)), L48) -> Adjudicado | N48: Servicio- Contratacion de servicios generales | O48: 0 | P48: RENTA DE SANITARIO PORTÁTIL TIPO A. RENTA DE SANITARIO PORTÁTIL TIPO B. RENTA DE SANITARIO PORTÁTIL PARA PERSONAS CON DISCAPACIDAD. RENTA DE SANITARIO TIPO C. RENTA DE SANITARIO PORTÁTIL TIPO CAMPER MIXTO. RENTA DE SANITARIO PORTÁTIL TIPO CAMPER HOMBRES. RENTA DE SANITARIO PORTÁTIL TIPO CAMPER MUJERES. RENTA DE MÓDULO DE SANITARIO ARMABLE MUJERES. RENTA DE MÓDULO DE SANITARIO ARMABLE HOMBRES. RENTA DE LAVAMANOS DOBLE. RENTA DE REGADERA PORTÁTIL. RENTA DE MODULO DE MINGITORIO. RENTA DE SANITARIO PORTÁTIL TIPO CAMPER DE OFICINA. RENTA DE MÓDULO DISPENSADOR DE GEL ANTIBACTERIAL. RENTA DE MÓDULO DE SANITARIO DOBLE. | Q48: NO
A49: S038-D | B49: 46051 | C49: =IF(L49="Rechazado", "Rechazado", IF(L49="Concluido", "Concluido", IF(AND(L49="En Proceso", TODAY()<=WORKDAY(B49,15)), "En Tiempo", IF(L49="En Proceso", "Atrasado", "")))) -> Concluido | D49: Estatal | E49: Oficialía Mayor | F49: COORDINACIÓN ADMINISTRATIVA | G49: 3000 Servicios generales | H49: 3800 – Servicios Oficiales | I49: 3821 Gastos de ceremonias oficiales y de orden social | J49: =IF(O49="","", IFERROR( IF(VALUE(SUBSTITUTE(SUBSTITUTE(TRIM(O49),"$",""),",",""))<=0,"", IF(VALUE(SUBSTITUTE(SUBSTITUTE(TRIM(O49),"$",""),",",""))<=580000,"CP", IF(VALUE(SUBSTITUTE(SUBSTITUTE(TRIM(O49),"$",""),",",""))<=1740000,"IRP","LPNP"))), "")) | K49: 315,136.95 | L49: Concluido | M49: =IFERROR(IF(OR(VLOOKUP(A49,Adjudicacion!A:N,14,0)=0, VLOOKUP(A49,Adjudicacion!A:N,14,0)=""), L49, VLOOKUP(A49,Adjudicacion!A:N,14,0)), L49) -> Desierta | N49: Servicio- Contratacion de servicios generales | O49: 0 | P49: RENTA DE SANITARIO PORTÁTIL TIPO A. RENTA DE SANITARIO PORTÁTIL TIPO B. RENTA DE SANITARIO PORTÁTIL PARA PERSONAS CON DISCAPACIDAD. RENTA DE SANITARIO TIPO C. RENTA DE SANITARIO PORTÁTIL TIPO CAMPER MIXTO. RENTA DE SANITARIO PORTÁTIL TIPO CAMPER HOMBRES. RENTA DE SANITARIO PORTÁTIL TIPO CAMPER MUJERES. RENTA DE MÓDULO DE SANITARIO ARMABLE MUJERES. RENTA DE MÓDULO DE SANITARIO ARMABLE HOMBRES. RENTA DE LAVAMANOS DOBLE. RENTA DE REGADERA PORTÁTIL. RENTA DE MODULO DE MINGITORIO. RENTA DE SANITARIO PORTÁTIL TIPO CAMPER DE OFICINA. RENTA DE MÓDULO DISPENSADOR DE GEL ANTIBACTERIAL. RENTA DE MÓDULO DE SANITARIO DOBLE. | Q49: NO
A50: S039 | B50: 46051 | C50: =IF(L50="Rechazado", "Rechazado", IF(L50="Concluido", "Concluido", IF(AND(L50="En Proceso", TODAY()<=WORKDAY(B50,15)), "En Tiempo", IF(L50="En Proceso", "Atrasado", "")))) -> Concluido | D50: Estatal | E50: Oficialía Mayor | F50: COORDINACIÓN ADMINISTRATIVA | G50: 3000 Servicios generales | H50: 3800 – Servicios Oficiales | I50: 3821 Gastos de ceremonias oficiales y de orden social | J50: =IF(O50="","", IFERROR( IF(VALUE(SUBSTITUTE(SUBSTITUTE(TRIM(O50),"$",""),",",""))<=0,"", IF(VALUE(SUBSTITUTE(SUBSTITUTE(TRIM(O50),"$",""),",",""))<=580000,"CP", IF(VALUE(SUBSTITUTE(SUBSTITUTE(TRIM(O50),"$",""),",",""))<=1740000,"IRP","LPNP"))), "")) | K50: 1,376.48 | L50: Concluido | M50: =IFERROR(IF(OR(VLOOKUP(A50,Adjudicacion!A:N,14,0)=0, VLOOKUP(A50,Adjudicacion!A:N,14,0)=""), L50, VLOOKUP(A50,Adjudicacion!A:N,14,0)), L50) -> Adjudicado | N50: Servicio- Contratacion de servicios generales | O50: 0 | P50: RENTA DE FUNDA PARA VALLA METÁLICA RENTA DE CARPA DE 3, 3.5 Y 4 METROS DE ALTURA. RENTA DE CARPA DE 20, 30, 40 O 50 METROS DE ANCHO RENTA DE CARPA DE 6 METROS DE ALTURA RENTA DE MESA REDONDA RENTA DE MESA TABLÓN RENTA DE ENLONADO RENTA DE VALLA DE METÁLICA RENTA DE MANTEL PARA MESA RENTA DE CARPA PANORÁMICA DE 20 METROS DE LARGO RENTA DE GRADAS RENTA DE SILLA PLEGADIZA RENTA DE SILLA TIPO TIFFANY RENTA DE SILLA DE TELA PLIANA RENTA DE CARPA DE 5 METROS DE ALTURA | Q50: NO
A51: S040 | B51: 46051 | C51: =IF(L51="Rechazado", "Rechazado", IF(L51="Concluido", "Concluido", IF(AND(L51="En Proceso", TODAY()<=WORKDAY(B51,15)), "En Tiempo", IF(L51="En Proceso", "Atrasado", "")))) -> Concluido | D51: Estatal | E51: Oficialía Mayor | F51: COORDINACIÓN ADMINISTRATIVA | G51: 2000 Materiales y Suministros | H51: 2600-COMBUSTIBLES, LUBRICANTES Y ADITIVOS. | I51: 2611-COMBUSTIBLES, LUBRICANTES Y ADITIVOS. | J51: =IF(O51="","", IFERROR( IF(VALUE(SUBSTITUTE(SUBSTITUTE(TRIM(O51),"$",""),",",""))<=0,"", IF(VALUE(SUBSTITUTE(SUBSTITUTE(TRIM(O51),"$",""),",",""))<=580000,"CP", IF(VALUE(SUBSTITUTE(SUBSTITUTE(TRIM(O51),"$",""),",",""))<=1740000,"IRP","LPNP"))), "")) | K51: 622,209,010.66 | L51: Concluido | M51: =IFERROR(IF(OR(VLOOKUP(A51,Adjudicacion!A:N,14,0)=0, VLOOKUP(A51,Adjudicacion!A:N,14,0)=""), L51, VLOOKUP(A51,Adjudicacion!A:N,14,0)), L51) -> Adjudicado | N51: Bien- Adquisición de materiales y suministros | O51: 0 | P51: SUMINISTRO DE MONEDEROS ELECTRÓNICOS DE COMBUSTIBLES, LUBRICANTES Y ADITIVOS | Q51: NO
A52: S041 | B52: 46051 | C52: =IF(L52="Rechazado", "Rechazado", IF(L52="Concluido", "Concluido", IF(AND(L52="En Proceso", TODAY()<=WORKDAY(B52,15)), "En Tiempo", IF(L52="En Proceso", "Atrasado", "")))) -> Concluido | D52: Estatal | E52: Oficialía Mayor | F52: COORDINACIÓN ADMINISTRATIVA | G52: 3000 Servicios generales | H52: 3500 – Servicios de Instalación, Reparación, Mantenimiento y Conservación | I52: 3581 Servicios de lavandería, limpieza e higiene | J52: =IF(O52="","", IFERROR( IF(VALUE(SUBSTITUTE(SUBSTITUTE(TRIM(O52),"$",""),",",""))<=0,"", IF(VALUE(SUBSTITUTE(SUBSTITUTE(TRIM(O52),"$",""),",",""))<=580000,"CP", IF(VALUE(SUBSTITUTE(SUBSTITUTE(TRIM(O52),"$",""),",",""))<=1740000,"IRP","LPNP"))), "")) | K52: 377,730,332.44 | L52: Concluido | M52: =IFERROR(IF(OR(VLOOKUP(A52,Adjudicacion!A:N,14,0)=0, VLOOKUP(A52,Adjudicacion!A:N,14,0)=""), L52, VLOOKUP(A52,Adjudicacion!A:N,14,0)), L52) -> Adjudicado | N52: Servicio- Contratacion de servicios generales | O52: 0 | P52: SERVICIO DE ASEO Y LIMPIEZA DE INMUEBLES. | Q52: NO
A53: S042 | B53: 46052 | C53: =IF(L53="Rechazado", "Rechazado", IF(L53="Concluido", "Concluido", IF(AND(L53="En Proceso", TODAY()<=WORKDAY(B53,15)), "En Tiempo", IF(L53="En Proceso", "Atrasado", "")))) -> Concluido | D53: Estatal | E53: Secretaría de Cultura y Turismo | F53: COORDINACIÓN ADMINISTRATIVA | G53: 3000 Servicios generales | H53: 3800 – Servicios Oficiales | I53: 3841 Exposiciones y ferias | J53: =IF(O53="","", IFERROR( IF(VALUE(SUBSTITUTE(SUBSTITUTE(TRIM(O53),"$",""),",",""))<=0,"", IF(VALUE(SUBSTITUTE(SUBSTITUTE(TRIM(O53),"$",""),",",""))<=580000,"CP", IF(VALUE(SUBSTITUTE(SUBSTITUTE(TRIM(O53),"$",""),",",""))<=1740000,"IRP","LPNP"))), "")) -> CP | K53: 344,725.00 | L53: Concluido | M53: =IFERROR(IF(OR(VLOOKUP(A53,Adjudicacion!A:N,14,0)=0, VLOOKUP(A53,Adjudicacion!A:N,14,0)=""), L53, VLOOKUP(A53,Adjudicacion!A:N,14,0)), L53) -> Concluido | N53: Servicio- Contratacion de servicios generales | O53: 350000 | P53: SERVICIO INTEGRAL PARA EL STAND CON EL QUE PARTICIPARÁ LA SECRETARÍA DE CULTURA Y TURISMO A TRAVÉS DEL CONSEJO EDITORIAL DE LA ADMINISTRACIÓN PÚBLICA ESTATAL EN LA “47 EDICIÓN DE LA FERIA INTERNACIONAL DEL LIBRO DEL PALACIO DE MINERÍA”. | Q53: NO
A54: S043 | B54: 46052 | C54: =IF(L54="Rechazado", "Rechazado", IF(L54="Concluido", "Concluido", IF(AND(L54="En Proceso", TODAY()<=WORKDAY(B54,15)), "En Tiempo", IF(L54="En Proceso", "Atrasado", "")))) -> Concluido | D54: Estatal | E54: Secretaría de Seguridad | F54: DIRECCIÓN DE SERVICIOS GENERALES Y APOYO LOGÍSTICO | G54: 3000 Servicios generales | H54: 3100 – Servicios Básicos | I54: 3121 Gas | J54: =IF(O54="","", IFERROR( IF(VALUE(SUBSTITUTE(SUBSTITUTE(TRIM(O54),"$",""),",",""))<=0,"", IF(VALUE(SUBSTITUTE(SUBSTITUTE(TRIM(O54),"$",""),",",""))<=580000,"CP", IF(VALUE(SUBSTITUTE(SUBSTITUTE(TRIM(O54),"$",""),",",""))<=1740000,"IRP","LPNP"))), "")) -> LPNP | K54: 33,900,068.87 | L54: Concluido | M54: =IFERROR(IF(OR(VLOOKUP(A54,Adjudicacion!A:N,14,0)=0, VLOOKUP(A54,Adjudicacion!A:N,14,0)=""), L54, VLOOKUP(A54,Adjudicacion!A:N,14,0)), L54) -> Adjudicado | N54: Servicio- Contratacion de servicios generales | O54: 33900069 | P54: SUMINISTRO DE GAS L.P. EN CENTROS PENITENCIARIOS Y DE REINSERCIÓN SOCIAL | Q54: NO
A55: S044 | B55: 46056 | C55: =IF(L55="Rechazado", "Rechazado", IF(L55="Concluido", "Concluido", IF(AND(L55="En Proceso", TODAY()<=WORKDAY(B55,15)), "En Tiempo", IF(L55="En Proceso", "Atrasado", "")))) -> Rechazado | D55: Estatal | E55: Secretaría de Finanzas | F55: DIRECCIÓN DE ADMINISTRACIÓN Y SERVICIOS GENERALES | G55: 3000 Servicios generales | H55: 3400 – Servicios Financieros, Bancarios y Comerciales | I55: 3421 Servicios de cobranza, investigación crediticia y similar | J55: =IF(O55="","", IFERROR( IF(VALUE(SUBSTITUTE(SUBSTITUTE(TRIM(O55),"$",""),",",""))<=0,"", IF(VALUE(SUBSTITUTE(SUBSTITUTE(TRIM(O55),"$",""),",",""))<=580000,"CP", IF(VALUE(SUBSTITUTE(SUBSTITUTE(TRIM(O55),"$",""),",",""))<=1740000,"IRP","LPNP"))), "")) -> LPNP | K55: 0 | L55: Rechazado | M55: =IFERROR(IF(OR(VLOOKUP(A55,Adjudicacion!A:N,14,0)=0, VLOOKUP(A55,Adjudicacion!A:N,14,0)=""), L55, VLOOKUP(A55,Adjudicacion!A:N,14,0)), L55) -> Rechazado | N55: Servicio- Contratacion de servicios generales | O55: 1.2844992e+08 | P55: ENTREGA A DOMICILIO DE MEDIOS DE IDENTIFICACIÓN VEHICULAR | Q55: NO
A56: S045 | B56: 46050 | C56: =IF(L56="Rechazado", "Rechazado", IF(L56="Concluido", "Concluido", IF(AND(L56="En Proceso", TODAY()<=WORKDAY(B56,15)), "En Tiempo", IF(L56="En Proceso", "Atrasado", "")))) -> Concluido | D56: Estatal | E56: Oficialía Mayor | F56: COORDINACIÓN ADMINISTRATIVA | G56: 3000 Servicios generales | H56: 3300 – Servicios Profesionales, Científicos, Técnicos y Otros Servicios | I56: 3381 Servicios de vigilancia | J56: =IF(O56="","", IFERROR( IF(VALUE(SUBSTITUTE(SUBSTITUTE(TRIM(O56),"$",""),",",""))<=0,"", IF(VALUE(SUBSTITUTE(SUBSTITUTE(TRIM(O56),"$",""),",",""))<=580000,"CP", IF(VALUE(SUBSTITUTE(SUBSTITUTE(TRIM(O56),"$",""),",",""))<=1740000,"IRP","LPNP"))), "")) -> LPNP | K56: 633,856,081.24 | L56: Concluido | M56: =IFERROR(IF(OR(VLOOKUP(A56,Adjudicacion!A:N,14,0)=0, VLOOKUP(A56,Adjudicacion!A:N,14,0)=""), L56, VLOOKUP(A56,Adjudicacion!A:N,14,0)), L56) -> Adjudicado | N56: Servicio- Contratacion de servicios generales | O56: 6.3385608e+08 | P56: SERVICIO DE SEGURIDAD Y VIGILANCIA | Q56: NO
A57: S046 | B57: 46057 | C57: =IF(L57="Rechazado", "Rechazado", IF(L57="Concluido", "Concluido", IF(AND(L57="En Proceso", TODAY()<=WORKDAY(B57,15)), "En Tiempo", IF(L57="En Proceso", "Atrasado", "")))) -> Concluido | D57: Estatal | E57: Secretaría de Finanzas | F57: SUBCOORDINACIÓN DE ADQUISICIONES Y CONTROL PATRIMONIAL | G57: 3000 Servicios generales | H57: 3500 – Servicios de Instalación, Reparación, Mantenimiento y Conservación | I57: 3571 Reparación, instalación y mantenimiento de maquinaria, equipo industrial y diverso | J57: =IF(O57="","", IFERROR( IF(VALUE(SUBSTITUTE(SUBSTITUTE(TRIM(O57),"$",""),",",""))<=0,"", IF(VALUE(SUBSTITUTE(SUBSTITUTE(TRIM(O57),"$",""),",",""))<=580000,"CP", IF(VALUE(SUBSTITUTE(SUBSTITUTE(TRIM(O57),"$",""),",",""))<=1740000,"IRP","LPNP"))), "")) -> CP | K57: 4466 | L57: Concluido | M57: =IFERROR(IF(OR(VLOOKUP(A57,Adjudicacion!A:N,14,0)=0, VLOOKUP(A57,Adjudicacion!A:N,14,0)=""), L57, VLOOKUP(A57,Adjudicacion!A:N,14,0)), L57) -> Concluido | N57: Servicio- Contratacion de servicios generales | O57: 35700 | P57: REPARACIÓN Y MANTENIMIENTO PARA ELEVADOR INSTALADO EN LA OFICINA DE LA GUBERNATURA | Q57: NO
A58: S047 | B58: 46057 | C58: =IF(L58="Rechazado", "Rechazado", IF(L58="Concluido", "Concluido", IF(AND(L58="En Proceso", TODAY()<=WORKDAY(B58,15)), "En Tiempo", IF(L58="En Proceso", "Atrasado", "")))) -> Concluido | D58: Estatal | E58: Secretaría de Finanzas | F58: SUBCOORDINACIÓN DE ADQUISICIONES Y CONTROL PATRIMONIAL | G58: 3000 Servicios generales | H58: 3500 – Servicios de Instalación, Reparación, Mantenimiento y Conservación | I58: 3591 Servicios de fumigación | J58: =IF(O58="","", IFERROR( IF(VALUE(SUBSTITUTE(SUBSTITUTE(TRIM(O58),"$",""),",",""))<=0,"", IF(VALUE(SUBSTITUTE(SUBSTITUTE(TRIM(O58),"$",""),",",""))<=580000,"CP", IF(VALUE(SUBSTITUTE(SUBSTITUTE(TRIM(O58),"$",""),",",""))<=1740000,"IRP","LPNP"))), "")) -> CP | K58: 34,761.69 | L58: Concluido | M58: =IFERROR(IF(OR(VLOOKUP(A58,Adjudicacion!A:N,14,0)=0, VLOOKUP(A58,Adjudicacion!A:N,14,0)=""), L58, VLOOKUP(A58,Adjudicacion!A:N,14,0)), L58) -> Concluido | N58: Servicio- Contratacion de servicios generales | O58: 41895 | P58: SERVICIO DE FUMIGACIÓN Y CONRTOL DE PLAGAS PARA LAS OFICINAS DE LA GUBERNATURA | Q58: NO
A59: S048 | B59: 46057 | C59: =IF(L59="Rechazado", "Rechazado", IF(L59="Concluido", "Concluido", IF(AND(L59="En Proceso", TODAY()<=WORKDAY(B59,15)), "En Tiempo", IF(L59="En Proceso", "Atrasado", "")))) -> Concluido | D59: Estatal | E59: Secretaría de Finanzas | F59: SUBCOORDINACIÓN DE ADQUISICIONES Y CONTROL PATRIMONIAL | G59: 3000 Servicios generales | H59: 3500 – Servicios de Instalación, Reparación, Mantenimiento y Conservación | I59: 3591 Servicios de fumigación | J59: =IF(O59="","", IFERROR( IF(VALUE(SUBSTITUTE(SUBSTITUTE(TRIM(O59),"$",""),",",""))<=0,"", IF(VALUE(SUBSTITUTE(SUBSTITUTE(TRIM(O59),"$",""),",",""))<=580000,"CP", IF(VALUE(SUBSTITUTE(SUBSTITUTE(TRIM(O59),"$",""),",",""))<=1740000,"IRP","LPNP"))), "")) -> CP | K59: 26,649.42 | L59: Concluido | M59: =IFERROR(IF(OR(VLOOKUP(A59,Adjudicacion!A:N,14,0)=0, VLOOKUP(A59,Adjudicacion!A:N,14,0)=""), L59, VLOOKUP(A59,Adjudicacion!A:N,14,0)), L59) -> Concluido | N59: Servicio- Contratacion de servicios generales | O59: 14301 | P59: SERVICIO DE FUMIGACIÓN Y CONTROL DE PLAGAS PARA LA OFICINA DE LA VOCERÍA DE LA GUBERNATURA | Q59: NO
A60: S049 | B60: 46057 | C60: =IF(L60="Rechazado", "Rechazado", IF(L60="Concluido", "Concluido", IF(AND(L60="En Proceso", TODAY()<=WORKDAY(B60,15)), "En Tiempo", IF(L60="En Proceso", "Atrasado", "")))) -> Concluido | D60: Estatal | E60: Secretaría de Finanzas | F60: SUBCOORDINACIÓN DE ADQUISICIONES Y CONTROL PATRIMONIAL | G60: 3000 Servicios generales | H60: 3500 – Servicios de Instalación, Reparación, Mantenimiento y Conservación | I60: 3591 Servicios de fumigación | J60: =IF(O60="","", IFERROR( IF(VALUE(SUBSTITUTE(SUBSTITUTE(TRIM(O60),"$",""),",",""))<=0,"", IF(VALUE(SUBSTITUTE(SUBSTITUTE(TRIM(O60),"$",""),",",""))<=580000,"CP", IF(VALUE(SUBSTITUTE(SUBSTITUTE(TRIM(O60),"$",""),",",""))<=1740000,"IRP","LPNP"))), "")) -> CP | K60: 125,092.38 | L60: Concluido | M60: =IFERROR(IF(OR(VLOOKUP(A60,Adjudicacion!A:N,14,0)=0, VLOOKUP(A60,Adjudicacion!A:N,14,0)=""), L60, VLOOKUP(A60,Adjudicacion!A:N,14,0)), L60) -> Concluido | N60: Servicio- Contratacion de servicios generales | O60: 43835 | P60: SERVICIO DE FUMIGACIÓN Y CONTROL DE PLAGAS PARA LA OFICINAS DE LA UNIDAD DE APOYO A LA ADMINISTRACIÓN GENERAL | Q60: NO
A61: S050 | B61: 46057 | C61: =IF(L61="Rechazado", "Rechazado", IF(L61="Concluido", "Concluido", IF(AND(L61="En Proceso", TODAY()<=WORKDAY(B61,15)), "En Tiempo", IF(L61="En Proceso", "Atrasado", "")))) -> Concluido | D61: Estatal | E61: Secretaría de Seguridad | F61: DIRECCIÓN DE SERVICIOS GENERALES Y APOYO LOGÍSTICO | G61: 2000 Materiales y Suministros | H61: 2200 – Alimentos y Utensilios | I61: 2222 Productos alimenticios para animales | J61: =IF(O61="","", IFERROR( IF(VALUE(SUBSTITUTE(SUBSTITUTE(TRIM(O61),"$",""),",",""))<=0,"", IF(VALUE(SUBSTITUTE(SUBSTITUTE(TRIM(O61),"$",""),",",""))<=580000,"CP", IF(VALUE(SUBSTITUTE(SUBSTITUTE(TRIM(O61),"$",""),",",""))<=1740000,"IRP","LPNP"))), "")) -> LPNP | K61: 3,367.50 | L61: Concluido | M61: =IFERROR(IF(OR(VLOOKUP(A61,Adjudicacion!A:N,14,0)=0, VLOOKUP(A61,Adjudicacion!A:N,14,0)=""), L61, VLOOKUP(A61,Adjudicacion!A:N,14,0)), L61) -> Adjudicado | N61: Bien- Adquisición de materiales y suministros | O61: 11908085 | P61: ALFALFA ACHICALADA. ALIMENTO PARA CANINOS ADULTOS. ALIMENTO EXTRUIDO AL 100% PARA EQUINOS. | Q61: NO
A62: S051 | B62: 46057 | C62: =IF(L62="Rechazado", "Rechazado", IF(L62="Concluido", "Concluido", IF(AND(L62="En Proceso", TODAY()<=WORKDAY(B62,15)), "En Tiempo", IF(L62="En Proceso", "Atrasado", "")))) -> Concluido | D62: Estatal | E62: Secretaría de Seguridad | F62: DIRECCIÓN DE SERVICIOS GENERALES Y APOYO LOGÍSTICO | G62: 2000 Materiales y Suministros | H62: 2200 – Alimentos y Utensilios | I62: 2211 Productos alimenticios para personas | J62: =IF(O62="","", IFERROR( IF(VALUE(SUBSTITUTE(SUBSTITUTE(TRIM(O62),"$",""),",",""))<=0,"", IF(VALUE(SUBSTITUTE(SUBSTITUTE(TRIM(O62),"$",""),",",""))<=580000,"CP", IF(VALUE(SUBSTITUTE(SUBSTITUTE(TRIM(O62),"$",""),",",""))<=1740000,"IRP","LPNP"))), "")) -> LPNP | K62: 1,601,349.58 | L62: Concluido | M62: =IFERROR(IF(OR(VLOOKUP(A62,Adjudicacion!A:N,14,0)=0, VLOOKUP(A62,Adjudicacion!A:N,14,0)=""), L62, VLOOKUP(A62,Adjudicacion!A:N,14,0)), L62) -> Adjudicado | N62: Bien- Adquisición de materiales y suministros | O62: 94508237 | P62: HARINA DE TRIGO PARA LA ELABORACIÓN DE PAN HARINA DE MAÍZ PARA LA ELABORACIÓN DE TORTILLA MATERIAS PRIMAS PARA LA ELABORACIÓN DE PAN Y TORTILLA | Q62: NO
A63: S052 | B63: 46057 | C63: =IF(L63="Rechazado", "Rechazado", IF(L63="Concluido", "Concluido", IF(AND(L63="En Proceso", TODAY()<=WORKDAY(B63,15)), "En Tiempo", IF(L63="En Proceso", "Atrasado", "")))) -> Concluido | D63: Estatal | E63: Secretaría de Seguridad | F63: DIRECCIÓN DE SERVICIOS GENERALES Y APOYO LOGÍSTICO | G63: 2000 Materiales y Suministros | H63: 2200 – Alimentos y Utensilios | I63: 2211 Productos alimenticios para personas | J63: =IF(O63="","", IFERROR( IF(VALUE(SUBSTITUTE(SUBSTITUTE(TRIM(O63),"$",""),",",""))<=0,"", IF(VALUE(SUBSTITUTE(SUBSTITUTE(TRIM(O63),"$",""),",",""))<=580000,"CP", IF(VALUE(SUBSTITUTE(SUBSTITUTE(TRIM(O63),"$",""),",",""))<=1740000,"IRP","LPNP"))), "")) -> LPNP | K63: 292,798,548.00 | L63: Concluido | M63: =IFERROR(IF(OR(VLOOKUP(A63,Adjudicacion!A:N,14,0)=0, VLOOKUP(A63,Adjudicacion!A:N,14,0)=""), L63, VLOOKUP(A63,Adjudicacion!A:N,14,0)), L63) -> Adjudicado | N63: Bien- Adquisición de materiales y suministros | O63: 293382230 | P63: SUMINISTRO DE VIVERES Y ALIMENTOS PARA CONSUMO HUMANO | Q63: NO
A64: S053 | B64: 46058 | C64: =IF(L64="Rechazado", "Rechazado", IF(L64="Concluido", "Concluido", IF(AND(L64="En Proceso", TODAY()<=WORKDAY(B64,15)), "En Tiempo", IF(L64="En Proceso", "Atrasado", "")))) -> Concluido | D64: Estatal | E64: Secretaría de Finanzas | F64: COORDINACIÓN ADMINISTRATIVA | G64: 3000 Servicios generales | H64: 3900 – Otros Servicios Generales | I64: 3992 GASTOS DE SERVICIOS MENORES | J64: =IF(O64="","", IFERROR( IF(VALUE(SUBSTITUTE(SUBSTITUTE(TRIM(O64),"$",""),",",""))<=0,"", IF(VALUE(SUBSTITUTE(SUBSTITUTE(TRIM(O64),"$",""),",",""))<=580000,"CP", IF(VALUE(SUBSTITUTE(SUBSTITUTE(TRIM(O64),"$",""),",",""))<=1740000,"IRP","LPNP"))), "")) -> CP | K64: 71.50 | L64: Concluido | M64: =IFERROR(IF(OR(VLOOKUP(A64,Adjudicacion!A:N,14,0)=0, VLOOKUP(A64,Adjudicacion!A:N,14,0)=""), L64, VLOOKUP(A64,Adjudicacion!A:N,14,0)), L64) -> Concluido | N64: Servicio- Contratacion de servicios generales | O64: 247052.25 | P64: GARRAFÓN DE AGUA | Q64: NO
A65: S054 | B65: 46058 | C65: =IF(L65="Rechazado", "Rechazado", IF(L65="Concluido", "Concluido", IF(AND(L65="En Proceso", TODAY()<=WORKDAY(B65,15)), "En Tiempo", IF(L65="En Proceso", "Atrasado", "")))) -> Concluido | D65: Estatal | E65: Secretaría de Cultura y Turismo | F65: COORDINACIÓN ADMINISTRATIVA | G65: 3000 Servicios generales | H65: 3800 – Servicios Oficiales | I65: 3831 Congresos y convenciones | J65: =IF(O65="","", IFERROR( IF(VALUE(SUBSTITUTE(SUBSTITUTE(TRIM(O65),"$",""),",",""))<=0,"", IF(VALUE(SUBSTITUTE(SUBSTITUTE(TRIM(O65),"$",""),",",""))<=580000,"CP", IF(VALUE(SUBSTITUTE(SUBSTITUTE(TRIM(O65),"$",""),",",""))<=1740000,"IRP","LPNP"))), "")) -> CP | K65: 578,250.00 | L65: Concluido | M65: =IFERROR(IF(OR(VLOOKUP(A65,Adjudicacion!A:N,14,0)=0, VLOOKUP(A65,Adjudicacion!A:N,14,0)=""), L65, VLOOKUP(A65,Adjudicacion!A:N,14,0)), L65) -> Concluido | N65: Servicio- Contratacion de servicios generales | O65: 580000 | P65: CONTRATACIÓN DEL SERVICIO DE CAPACITACIÓN A TRAVES DEL “DIPLOMADO PARA LA FORMACIÓN DE GUÍAS DE TURISTAS ESPECIALIZADOS EN EXCURSIONISMO DE LOS PUEBLOS CON ENCANTO” | Q65: NO
A66: S055 | B66: 46059 | C66: =IF(L66="Rechazado", "Rechazado", IF(L66="Concluido", "Concluido", IF(AND(L66="En Proceso", TODAY()<=WORKDAY(B66,15)), "En Tiempo", IF(L66="En Proceso", "Atrasado", "")))) -> Concluido | D66: Estatal | E66: Consejería Jurídica | F66: COORDINACIÓN ADMINISTRATIVA | G66: 3000 Servicios generales | H66: 3800 – Servicios Oficiales | I66: 3821 Gastos de ceremonias oficiales y de orden social | J66: =IF(O66="","", IFERROR( IF(VALUE(SUBSTITUTE(SUBSTITUTE(TRIM(O66),"$",""),",",""))<=0,"", IF(VALUE(SUBSTITUTE(SUBSTITUTE(TRIM(O66),"$",""),",",""))<=580000,"CP", IF(VALUE(SUBSTITUTE(SUBSTITUTE(TRIM(O66),"$",""),",",""))<=1740000,"IRP","LPNP"))), "")) | K66: 130,469.10 | L66: Concluido | M66: =IFERROR(IF(OR(VLOOKUP(A66,Adjudicacion!A:N,14,0)=0, VLOOKUP(A66,Adjudicacion!A:N,14,0)=""), L66, VLOOKUP(A66,Adjudicacion!A:N,14,0)), L66) -> Concluido | N66: Servicio- Contratacion de servicios generales | O66: 0 | P66: CONTRATACIÓN DE TESTIGO SOCIAL PARA LA CONTRATACIÓN DEL SERVICIO INTEGRAL “CARAVANAS ITINERANTES POR LA JUSTICIA SOCIAL” | Q66: NO
A67: S056 | B67: 46062 | C67: =IF(L67="Rechazado", "Rechazado", IF(L67="Concluido", "Concluido", IF(AND(L67="En Proceso", TODAY()<=WORKDAY(B67,15)), "En Tiempo", IF(L67="En Proceso", "Atrasado", "")))) -> Concluido | D67: Estatal | E67: Oficialía Mayor | F67: Coordinación Administrativa (23400000030000S) | G67: 3000 Servicios generales | H67: 3300 – Servicios Profesionales, Científicos, Técnicos y Otros Servicios | I67: 3381 Servicios de vigilancia | J67: =IF(O67="","", IFERROR( IF(VALUE(SUBSTITUTE(SUBSTITUTE(TRIM(O67),"$",""),",",""))<=0,"", IF(VALUE(SUBSTITUTE(SUBSTITUTE(TRIM(O67),"$",""),",",""))<=580000,"CP", IF(VALUE(SUBSTITUTE(SUBSTITUTE(TRIM(O67),"$",""),",",""))<=1740000,"IRP","LPNP"))), "")) | K67: 130469.1 | L67: Concluido | M67: =IFERROR(IF(OR(VLOOKUP(A67,Adjudicacion!A:N,14,0)=0, VLOOKUP(A67,Adjudicacion!A:N,14,0)=""), L67, VLOOKUP(A67,Adjudicacion!A:N,14,0)), L67) -> Concluido | N67: Servicio- Contratacion de servicios generales | O67: 0 | P67: TESTIGO SOCIAL PARA LA CONTRATACIÓN DEL SERVICIO DE SEGURIDAD Y VIGILANCIA | Q67: NO
A68: S057 | B68: 46062 | C68: =IF(L68="Rechazado", "Rechazado", IF(L68="Concluido", "Concluido", IF(AND(L68="En Proceso", TODAY()<=WORKDAY(B68,15)), "En Tiempo", IF(L68="En Proceso", "Atrasado", "")))) -> Concluido | D68: Estatal | E68: Oficialía Mayor | F68: Coordinación Administrativa (23400000030000S) | G68: 2000 Materiales y Suministros | H68: 2400 – Materiales y Artículos de Construcción y de Reparación | I68: 2461 Material eléctrico y electrónico | J68: =IF(O68="","", IFERROR( IF(VALUE(SUBSTITUTE(SUBSTITUTE(TRIM(O68),"$",""),",",""))<=0,"", IF(VALUE(SUBSTITUTE(SUBSTITUTE(TRIM(O68),"$",""),",",""))<=580000,"CP", IF(VALUE(SUBSTITUTE(SUBSTITUTE(TRIM(O68),"$",""),",",""))<=1740000,"IRP","LPNP"))), "")) -> IRP | K68: 62,762.45 | L68: Concluido | M68: =IFERROR(IF(OR(VLOOKUP(A68,Adjudicacion!A:N,14,0)=0, VLOOKUP(A68,Adjudicacion!A:N,14,0)=""), L68, VLOOKUP(A68,Adjudicacion!A:N,14,0)), L68) -> Concluido | N68: Bien- Adquisición de materiales y suministros | O68: 1050278 | P68: CALBE TIPO POT CAL. 10 ROLLO CON 100 MT. (BLANCO O GRIS) ROLLO DE 100 MT. CADA UNA DE CABLE PORTA ELECTRODO DE 1/0 ANTIFLAMA ROLLO DE 100 MT. CADA UNA DE CABLE PORTA ELECTRODO DE 2/0 ANTIFLAMA ROLLO DE 100 MT. CADA UNA DE CABLE PORTA ELECTRODO DE 3/0 ANTIFLAMA ROLLO DE 100 MT. CADA UNA DE CABLE PORTA ELECTRODO ANTIFLAMA CALIBRE 2 CONTACTO USO RUDO MONOFÁSICO TAPAS PARA CONTACTO DE USO RUDO DE ALUMINIO CHALUPAS DE ALUMINIO PARA CONTACTO USO RUDO LÁMPARAS SORDAS TORRE DE MINIBRUTO CON 4 UNIDADES C/U DE 120 VOLTS FOCOS DE MINIBRUTOS 120 VOLTS 650 WATTS INTERRUPTORES DOBLE TIRO DE ZAPATAS DE COBRE PARA CONECTORES CAM LOOK CONECTORES DE CHASIS CONECTORES DE CHASIS YELOW JACKET CABLE CABLE DUPLEX PROBADOR DE CORRIENTE TIPO LAPIZ SOQUET LÁMPARA DE EMERGENCIA LÁMPARA EXTENSIÓN ELECTRICA DE 20 METROS USO RUDO EXTENSIÓN ELÉCTRICA USO RUDO DE 6 METROS CABLE THW CALIBRE 14 TERMO-PASTILLA 10 AMPERES TERMO-PASTILLA 15 AMPERES TERMO-PASTILLA 40 AMPERES REFLECTOR LED DE 100 WATTS LÁMPARA DE MANO TÁCTICA DE 3000 LUMENES FOCO LED 45 WATTS PANEL LED DE 60 POR 60 CENTIMETROS, LUZ CALIDA LÁMPARA DE EMERGENCIA DE 60 LEDS CABLE POT FOCO AHORRADOR LUZ CALIDA DE 45 WATTS MCA, MAG FOCO AHORRADOR LUZ CALIDA DE 65 WATTS MCA, MAG FOCO LED TIPO MR-16 MARCA TECNOLITE DE 5.5 W. COLOR DE LUZ CALIDA 3000 °K FOCO PILOTO DE 10 WATTS 110-140 VOLTS LAMPARA FLUORESCENTE TIPO SLIM DE 30 WATTS LUZ DE DIA LÁMPARA FLUORESCENTE TIPO SLIM DE 60 WATTS LUZ DE DIA LAMPARA LED LAMPARA LED LAMPARA LED LÁMPARA TUBULAR LÁMPARA TUBULAR PASTILLA BREAKER FEDERAL PASTILLA BREAKER FEDERAL CENTRO DE CARGA EXTENSIÓN ELÉCTRICA REFLECTOR LED BASE PARA LAMPARA T8 CABLE USO RUDO CINTA COMPROBADOR DE VOLTAJE CONDUCTOR DE COBRE DE NUDO CONECTOR CILÍNDRICO CONECTOR DERIVADOR CONECTOR DERIVADOR ELEMENTO QUÍMICO, PARA PUESTA A TIERRA FOCO DE 33W FOTOCELDA MULTIRANGO DE 110-240 V KIT DE CRIMPADORA HIDRÁULICA LÁMPARA DE 10 WATTS DE LED TERMINAL PARA PUESTA A TIERRA ZAPATA CILÍNDRICA BIMETÁLICA SOQUET TIPO MOGUL LAMPARA TIPO SUBURBANA DE LED CABLE ELÉCTRICO DUPLEX CALIBRE 10 LINTERNA RECARGABLE FOCO DE 100 WATTS EXTENSIÓN ELÉCTRICA USO RUDO DE 20 METROS APAGADOR SENCILLO CON TAPA EXTENSIÓN ELÉCTRICA USO RUDO DE 15 METROS PROBADOR DE CORRIENTE TIPO LAPIZ SOQUET CINCHO DE 10 CENTÍMETROS CANALETA DE 2 VÍAS DE PVC CINTA PARA DUCTOS LÁMPARA DE EMERGENCIA DE 90 LEDS FOCO AHORRADOR DE 23 WATTS FOCO AHORRADOR DE 65 WATTS CANALETA DE 1/2 PULGADA FOCO AHORRADOR DE 10 WATTS CONTACTO DUPLEX CON PLACA CINTA DE AISLAR DE 19 MILÍMETROS EXTENSIÓN ELÉCTRICA DE 4 METROS EXTENSIÓN ELÉCTRICA USO RUDO DE 10 METROS LÁMPARA LINTERNA DE MANO RECARGABLE CLAVIJA METÁLICA USO RUDO FOCO AHORRADOR DE 15 WATTS CANALETA PLÁSTICA DE 12 POR 32 MILÍMETROS POR 2 METROS DE LARGO GRAPA PARA CABLE FUSIBLE DE 30 AMPERES FUSIBLE DE 60 AMPERES TIPO CARTUCHO CONTACTO SENCILLO CON TAPA CLAVIJA MULTICONTACTO DE 6 ENTRADAS EXTENSIÓN ELÉCTRICA USO RUDO DE 5 METROS CABLE DUPLEX CALIBRE 12 EXTENSIÓN ELÉCTRICA DE 5 METROS SOQUET DE BAQUELITA FOCO AHORRADOR DE 24 WATTS CANALETA BLANCA DE 17 MILÍMETROS POR 35 MILÍMETROS POR 2 METROS EXTENSIÓN ELÉCTRICA DE 3 METROS CENTRO DE CARGA 6 ESPACIOS PROBADOR DE POLARIDAD PARA CONTACTOS CANALETA AUTOADHERIBLE 20 POR 20 MILÍMETROS POR 2 METROS DE LARGO CINCHOS DE 15 CENTÍMETROS CINCHOS DE 30 CENTÍMETROS GUÍA PARA CABLE 30 METROS CAJA CHALUPA DE 2 POR 4 PULGADAS APAGADOR CON PLACA CENTRO DE CARGA QOD2S CENTRO DE CARGA QOD4S FOCO ESPIRAL DE 26 WATTS T2 TAPA DE 2 PERFORACIONES PARA JACK RJ45 REFLECTOR LED DE 200 WATTS LINTERNA TIPO MINERO LISTÓN FUSIBLE DE 30 AMPERES EXTENSIÓN PARA LÍNEA TELEFÓNICA DE 10 METROS EXTENSIÓN PARA LÍNEA TELEFÓNICA DE 15 METROS CABLE THW AWG CALIBRE 12 LÁMPARA TUBO DE LED 18 WATTS LÁMPARA FLUORESCENTE DE 14 WATTS T8 PILA ALCALINA AA PILA ALCALINA AAA POLIDUCTO DE 1/2 PULGADA CARGADOR CON (4) BATERIAS RECARGABLES CINCHOS DE 20 CENTÍMETROS GABINETE BLANCO CON REJA Y FOCOS LED 36 W EXTENSIÓN ELECTRICA DE 20 METROS USO RUDO EXTENSIÓN ELÉCTRICA USO RUDO DE 6 METROS EXTENSIÓN ELÉCTRICA USO RUDO DE 30 METROS CANALETA PLÁSTICA 2 X 1.2 X 200 CENTÍMETROS AUTOADHERIBLE CANALETA PLÁSTICA 2.5 X 2.5 X 200 CENTÍMETROS AUTOADHERIBLE CANALETA PLÁSTICA 2.4 POR 4.0 POR 200 CENTÍMETROS AUTOADHERIBLE CABLE THW CALIBRE 8 CABLE THW CALIBRE 14 CABLE THW CALIBRE 16 CABLE THW DEL NÚMERO 10 CABLE UTP CATEGORIA 6 CINTA ADHESIVA DOBLE CARA TRANSPARENTE 1 PULGADA DE ANCHO POR 1.50 METROS DE LARGO APAGADOR ESCALERA CON PLACA INTERRUPTOR TERMOMAGNÉTICO DE 3 POLOS DE 100 AMPERES CABLE DUPLEX CALIBRE 14 APAGADOR SENCILLO VISIBLE CUADRADO CAJA UNIVERSAL PARA CANALETA CANALETA DE ALUMNIO MEDIA CAÑA DE 2 ½ PULGADA PLACA PARA CONTACTO DUPLEX CONTACTO DUPLEX POLARIZADO SIN TAPA LÁMPARA DE MANO TÁCTICA DE 3000 LUMENES CABLE THW DEL NÚMERO 12 SOCKET PARA TUBO T8 CON BASE G13 CONECTOR PARA TUBO LED T8 CONTACTO CON PLACA BALASTRO 3 POR 14 WATTS APAGADOR DOBLE CON TAPA LAMPARA FLUORESCENTE ESPIRAL DE 23 WATTS. FOCO DULUX 2 PINES DE S13W CINTA CANELA GRIS INDUSTRIAL PAQUETE DE BATERÍAS AAA EXTENSIÓN DE 10 METROS PILA O BATERÍA RECARGABLE NÍQUEL-METAL, TAMAÑO C 4 PILAS O BATERÍAS RECARGABLES TIPO “AAA” CAJA DE CONTACTOS PARA CANALETA 4 PILAS O BATERÍAS RECARGABLES "AA" LÁMPARA DE EMERGENCIA TIPO LED PROBADOR UNIVERSAL DE PILAS CARGADOR DE PILAS BATERÍA RECARGABLE AA CABLE TELEFÓNICO CONECTOR RJ CATEGORÍA 5 CABLE ESPIRAL TELEFÓNICO CABLE DE USO RUDO CALIBRE 12 (3 POR 12) CINTA DE AISLAR DE VINIL BATERÍA ALCALINA AA DESECHABLE CAJA EXTERIOR SENCILLA CABLE DE USO RUDO CALIBRE 14 LÁMPARA COLGANTE TECNOLOGIA LED CLAVIJA CONVERTIDORA TERMO-PASTILLA 15 AMPERES TERMO-PASTILLA 20 AMPERES TERMO-PASTILLA 30 AMPERES TUBO CONDUIT PARED DELGADA ½ PULGADA CODO CONDUIT PARED DELGADA ½ PULGADA EXTENSIÓN ELÉCTRICA DE USO RUDO 2 METROS ROSETA CON JACK PLUG RJ11 BATERÍA RECARGABLE AA | Q68: NO
A69: S058 | B69: 46062 | C69: =IF(L69="Rechazado", "Rechazado", IF(L69="Concluido", "Concluido", IF(AND(L69="En Proceso", TODAY()<=WORKDAY(B69,15)), "En Tiempo", IF(L69="En Proceso", "Atrasado", "")))) -> Rechazado | D69: Estatal | E69: Oficialía Mayor | F69: Coordinación Administrativa (23400000030000S) | G69: 3000 Servicios generales | H69: 3500 – Servicios de Instalación, Reparación, Mantenimiento y Conservación | I69: 3511 Reparación y mantenimiento de inmuebles | J69: =IF(O69="","", IFERROR( IF(VALUE(SUBSTITUTE(SUBSTITUTE(TRIM(O69),"$",""),",",""))<=0,"", IF(VALUE(SUBSTITUTE(SUBSTITUTE(TRIM(O69),"$",""),",",""))<=580000,"CP", IF(VALUE(SUBSTITUTE(SUBSTITUTE(TRIM(O69),"$",""),",",""))<=1740000,"IRP","LPNP"))), "")) -> LPNP | K69: 0 | L69: Rechazado | M69: =IFERROR(IF(OR(VLOOKUP(A69,Adjudicacion!A:N,14,0)=0, VLOOKUP(A69,Adjudicacion!A:N,14,0)=""), L69, VLOOKUP(A69,Adjudicacion!A:N,14,0)), L69) -> Rechazado | N69: Servicio- Contratacion de servicios generales | O69: 12000000 | P69: SERVICIO DE IMPERMEABILIZACIÓN DE AZOTEA EN EL INMUEBLE DENOMINADO PALACIO DE GOBIERNO. IMPERMEABILIZACIÓN DE EDIFICIOS ARCHIVO GENERAL DEL ESTADO DE MÉXICO. SERVICIO DE PINTURA DE DOS EDIFICIOS ARCHIVO GENERAL DEL ESTADO DE MÉXICO. | Q69: NO
A70: S059 | B70: 46062 | C70: =IF(L70="Rechazado", "Rechazado", IF(L70="Concluido", "Concluido", IF(AND(L70="En Proceso", TODAY()<=WORKDAY(B70,15)), "En Tiempo", IF(L70="En Proceso", "Atrasado", "")))) -> Concluido | D70: Estatal | E70: Secretaría de Seguridad | F70: Oficialía Mayor (20603000000000L) | G70: 3000 Servicios generales | H70: 3100 – Servicios Básicos | I70: 3131 Servicio de agua | J70: =IF(O70="","", IFERROR( IF(VALUE(SUBSTITUTE(SUBSTITUTE(TRIM(O70),"$",""),",",""))<=0,"", IF(VALUE(SUBSTITUTE(SUBSTITUTE(TRIM(O70),"$",""),",",""))<=580000,"CP", IF(VALUE(SUBSTITUTE(SUBSTITUTE(TRIM(O70),"$",""),",",""))<=1740000,"IRP","LPNP"))), "")) -> LPNP | K70: 133,632,803.97 | L70: Concluido | M70: =IFERROR(IF(OR(VLOOKUP(A70,Adjudicacion!A:N,14,0)=0, VLOOKUP(A70,Adjudicacion!A:N,14,0)=""), L70, VLOOKUP(A70,Adjudicacion!A:N,14,0)), L70) -> Adjudicado | N70: Servicio- Contratacion de servicios generales | O70: 1.3205711e+08 | P70: SERVICIO DE SUMINISTRO, ABASTECIMIENTO Y DISTRIBUCIÓN DIARIO DE AGUA POTABLE EN PIPA | Q70: NO
A71: S060 | B71: 46063 | C71: =IF(L71="Rechazado", "Rechazado", IF(L71="Concluido", "Concluido", IF(AND(L71="En Proceso", TODAY()<=WORKDAY(B71,15)), "En Tiempo", IF(L71="En Proceso", "Atrasado", "")))) -> Rechazado | D71: Estatal | E71: Oficialía Mayor | F71: Coordinación Administrativa (23400000030000S) | G71: 3000 Servicios generales | H71: 3500 – Servicios de Instalación, Reparación, Mantenimiento y Conservación | I71: 3531 Reparación, instalación y mantenimiento de bienes informáticos, microfilmación y tecnologías de la información | J71: =IF(O71="","", IFERROR( IF(VALUE(SUBSTITUTE(SUBSTITUTE(TRIM(O71),"$",""),",",""))<=0,"", IF(VALUE(SUBSTITUTE(SUBSTITUTE(TRIM(O71),"$",""),",",""))<=580000,"CP", IF(VALUE(SUBSTITUTE(SUBSTITUTE(TRIM(O71),"$",""),",",""))<=1740000,"IRP","LPNP"))), "")) -> LPNP | K71: 0 | L71: Rechazado | M71: =IFERROR(IF(OR(VLOOKUP(A71,Adjudicacion!A:N,14,0)=0, VLOOKUP(A71,Adjudicacion!A:N,14,0)=""), L71, VLOOKUP(A71,Adjudicacion!A:N,14,0)), L71) -> Rechazado | N71: Servicio- Contratacion de servicios generales | O71: =200000+4295753 -> 4495753 | P71: MANTENIMIENTO PREVENTIVO Y CORRECTIVO DEL SISTEMA DE DETECCIÓN DE HUMO (MARCA BOSCH) INSTALACIÓN Y CAMBIO DE BATERÍAS AL SISTEMA DE ENERGÍA ININTERRUMPIDA (UPS) MARCA EATON MODELO FE7KVA SERVICIO DE MANTENIMIENTO A LA INFRAESTRUCTURA DE TELEFONÍA DEL CENTRO DE ATENCIÓN TELEFÓNICA DEL GOBIERNO DEL ESTADO DE MÉXICO | Q71: NO
A72: S061 | B72: 46063 | C72: =IF(L72="Rechazado", "Rechazado", IF(L72="Concluido", "Concluido", IF(AND(L72="En Proceso", TODAY()<=WORKDAY(B72,15)), "En Tiempo", IF(L72="En Proceso", "Atrasado", "")))) -> Concluido | D72: Estatal | E72: Oficialía Mayor | F72: Coordinación Administrativa (23400000030000S) | G72: 2000 Materiales y Suministros | H72: 2700 – Vestuario, Blancos, Prendas de Protección y Artículos Deportivos | I72: 2721 Prendas de seguridad y protección personal | J72: =IF(O72="","", IFERROR( IF(VALUE(SUBSTITUTE(SUBSTITUTE(TRIM(O72),"$",""),",",""))<=0,"", IF(VALUE(SUBSTITUTE(SUBSTITUTE(TRIM(O72),"$",""),",",""))<=580000,"CP", IF(VALUE(SUBSTITUTE(SUBSTITUTE(TRIM(O72),"$",""),",",""))<=1740000,"IRP","LPNP"))), "")) -> IRP | K72: 45404.24 | L72: Concluido | M72: =IFERROR(IF(OR(VLOOKUP(A72,Adjudicacion!A:N,14,0)=0, VLOOKUP(A72,Adjudicacion!A:N,14,0)=""), L72, VLOOKUP(A72,Adjudicacion!A:N,14,0)), L72) -> Concluido | N72: Bien- Adquisición de materiales y suministros | O72: =328267.78+900000+52415 -> 1280682.8 | P72: BOTAS DE HULE DE SEGURIDAD, INDUSTRIAL DIELÉCTRICA. GUANTES DE PIEL PARA TRABAJO. IMPERMEABLE TIPO GABARDINA. IMPERMEABLE DE DOS PIEZAS DIELÉCTRICO. MOCHILA TÁCTICA MILITAR SENDERISMO. CHALECO PARA TOPOGRÁFIA. CHALECO DE ALTA VISIVILIDAD CON TIRAS REFLEJANTES. CARETA PROTECTORA FACIAL CON LENTES. ARNÉS PARA DESCENSO EN BARRANCOS. GUANTES DIELÉCTRICOS PROTECCIÓN HASTA 1000 V. GUANTES DE TRABAJO PARA DEMOLICIÓN. RESPIRADOR REUTILIZABLE CON ANTEOJOS DE SEGURIDAD Y FILTROS. GUANTES DE CARNAZA PARA SOLDAR PUÑO LARGO. CINTURON PORTA HERRAMIENTA. | Q72: NO
A73: S062 | B73: 46063 | C73: =IF(L73="Rechazado", "Rechazado", IF(L73="Concluido", "Concluido", IF(AND(L73="En Proceso", TODAY()<=WORKDAY(B73,15)), "En Tiempo", IF(L73="En Proceso", "Atrasado", "")))) -> Concluido | D73: Estatal | E73: Consejería Jurídica | F73: Coordinación Administrativa (23300001000000S) | G73: 3000 Servicios generales | H73: 3300 – Servicios Profesionales, Científicos, Técnicos y Otros Servicios | I73: 3362 Impresiones de documentos oficiales | J73: =IF(O73="","", IFERROR( IF(VALUE(SUBSTITUTE(SUBSTITUTE(TRIM(O73),"$",""),",",""))<=0,"", IF(VALUE(SUBSTITUTE(SUBSTITUTE(TRIM(O73),"$",""),",",""))<=580000,"CP", IF(VALUE(SUBSTITUTE(SUBSTITUTE(TRIM(O73),"$",""),",",""))<=1740000,"IRP","LPNP"))), "")) -> CP | K73: 126.00 | L73: concluido | M73: =IFERROR(IF(OR(VLOOKUP(A73,Adjudicacion!A:N,14,0)=0, VLOOKUP(A73,Adjudicacion!A:N,14,0)=""), L73, VLOOKUP(A73,Adjudicacion!A:N,14,0)), L73) -> concluido | N73: Servicio- Contratacion de servicios generales | O73: 148862 | P73: IMPRESIÓN DE GAFETE INVEA DEL ESTADO DE MÉXICO 2026 | Q73: NO
A74: S063 | B74: 46063 | C74: =IF(L74="Rechazado", "Rechazado", IF(L74="Concluido", "Concluido", IF(AND(L74="En Proceso", TODAY()<=WORKDAY(B74,15)), "En Tiempo", IF(L74="En Proceso", "Atrasado", "")))) -> Rechazado | D74: Estatal | E74: Secretaría de Seguridad | F74: Oficialía Mayor (20603000000000L) | G74: 3000 Servicios generales | H74: 3200 – Servicios de Arrendamiento | I74: 3271 Arrendamiento de activos intangibles | J74: =IF(O74="","", IFERROR( IF(VALUE(SUBSTITUTE(SUBSTITUTE(TRIM(O74),"$",""),",",""))<=0,"", IF(VALUE(SUBSTITUTE(SUBSTITUTE(TRIM(O74),"$",""),",",""))<=580000,"CP", IF(VALUE(SUBSTITUTE(SUBSTITUTE(TRIM(O74),"$",""),",",""))<=1740000,"IRP","LPNP"))), "")) -> IRP | K74: 0 | L74: Rechazado | M74: =IFERROR(IF(OR(VLOOKUP(A74,Adjudicacion!A:N,14,0)=0, VLOOKUP(A74,Adjudicacion!A:N,14,0)=""), L74, VLOOKUP(A74,Adjudicacion!A:N,14,0)), L74) -> Rechazado | N74: Servicio- Contratacion de servicios generales | O74: 1300000 | P74: RENOVACIÓN DEL SOFTWARE DE LA MARCA VMWARE DE LA SECRETARÍA DE SEGURIDAD | Q74: NO
A75: S064 | B75: 46064 | C75: =IF(L75="Rechazado", "Rechazado", IF(L75="Concluido", "Concluido", IF(AND(L75="En Proceso", TODAY()<=WORKDAY(B75,15)), "En Tiempo", IF(L75="En Proceso", "Atrasado", "")))) -> Concluido | D75: Estatal | E75: Oficialía Mayor | F75: Coordinación Administrativa (23400000030000S) | G75: 2000 Materiales y Suministros | H75: 2600-COMBUSTIBLES, LUBRICANTES Y ADITIVOS. | I75: 2611 COMBUSTIBLES, LUBRICANTES Y ADITIVOS. | J75: =IF(O75="","", IFERROR( IF(VALUE(SUBSTITUTE(SUBSTITUTE(TRIM(O75),"$",""),",",""))<=0,"", IF(VALUE(SUBSTITUTE(SUBSTITUTE(TRIM(O75),"$",""),",",""))<=580000,"CP", IF(VALUE(SUBSTITUTE(SUBSTITUTE(TRIM(O75),"$",""),",",""))<=1740000,"IRP","LPNP"))), "")) | K75: 130,469.10 | L75: Concluido | M75: =IFERROR(IF(OR(VLOOKUP(A75,Adjudicacion!A:N,14,0)=0, VLOOKUP(A75,Adjudicacion!A:N,14,0)=""), L75, VLOOKUP(A75,Adjudicacion!A:N,14,0)), L75) -> Concluido | N75: Servicio- Contratacion de servicios generales | O75: 0 | P75: TESTIGO SOCIAL PARA LA CONTRATACIÓN DEL SERVICIO DE COMBUSTIBLES, LUBRICANTES Y ADITIVOS | Q75: NO
A76: S065 | B76: 46064 | C76: =IF(L76="Rechazado", "Rechazado", IF(L76="Concluido", "Concluido", IF(AND(L76="En Proceso", TODAY()<=WORKDAY(B76,15)), "En Tiempo", IF(L76="En Proceso", "Atrasado", "")))) -> Concluido | D76: Estatal | E76: Oficialía Mayor | F76: Coordinación Administrativa (23400000030000S) | G76: 3000 Servicios generales | H76: 3500 – Servicios de Instalación, Reparación, Mantenimiento y Conservación | I76: 3581 Servicios de lavandería, limpieza e higiene | J76: =IF(O76="","", IFERROR( IF(VALUE(SUBSTITUTE(SUBSTITUTE(TRIM(O76),"$",""),",",""))<=0,"", IF(VALUE(SUBSTITUTE(SUBSTITUTE(TRIM(O76),"$",""),",",""))<=580000,"CP", IF(VALUE(SUBSTITUTE(SUBSTITUTE(TRIM(O76),"$",""),",",""))<=1740000,"IRP","LPNP"))), "")) | K76: 130,469.10 | L76: Concluido | M76: =IFERROR(IF(OR(VLOOKUP(A76,Adjudicacion!A:N,14,0)=0, VLOOKUP(A76,Adjudicacion!A:N,14,0)=""), L76, VLOOKUP(A76,Adjudicacion!A:N,14,0)), L76) -> Concluido | N76: Servicio- Contratacion de servicios generales | O76: 0 | P76: TESTIGO SOCIAL PARA LA CONTRATACIÓN DEL SERVICIO DE LAVANDERÍA, LIMPIEZA E HIGIENE | Q76: NO
A77: S066 | B77: 46065 | C77: =IF(L77="Rechazado", "Rechazado", IF(L77="Concluido", "Concluido", IF(AND(L77="En Proceso", TODAY()<=WORKDAY(B77,15)), "En Tiempo", IF(L77="En Proceso", "Atrasado", "")))) -> Concluido | D77: Estatal | E77: Secretaría del Campo | F77: Coordinación Administrativa | G77: 4000 Transferencias asignaciones subsidios y otras ayudas | H77: 4400 – Ayudas Sociales | I77: 4415 Apoyo a la infraestructura agropecuaria y forestal | J77: =IF(O77="","", IFERROR( IF(VALUE(SUBSTITUTE(SUBSTITUTE(TRIM(O77),"$",""),",",""))<=0,"", IF(VALUE(SUBSTITUTE(SUBSTITUTE(TRIM(O77),"$",""),",",""))<=580000,"CP", IF(VALUE(SUBSTITUTE(SUBSTITUTE(TRIM(O77),"$",""),",",""))<=1740000,"IRP","LPNP"))), "")) -> IRP | K77: 100.00 | L77: Concluido | M77: =IFERROR(IF(OR(VLOOKUP(A77,Adjudicacion!A:N,14,0)=0, VLOOKUP(A77,Adjudicacion!A:N,14,0)=""), L77, VLOOKUP(A77,Adjudicacion!A:N,14,0)), L77) -> Concluido | N77: Bien- Adquisición de materiales y suministros | O77: 883000 | P77: KAIROMONA (ATRAYENTE) PARA EL MONITOREO DE LA MOSCA DEL GUSANO BARRENADOR DEL GANADO. TRAMPA ADHESIVA AZUL DE 10 POR 24 PUNTO 5 CENTIMETROS PARA EL MONITOREO DE LA MOSCA DEL GUSANO BARRENADOR DEL GANADO. | Q77: NO
A78: S067 | B78: 46065 | C78: =IF(L78="Rechazado", "Rechazado", IF(L78="Concluido", "Concluido", IF(AND(L78="En Proceso", TODAY()<=WORKDAY(B78,15)), "En Tiempo", IF(L78="En Proceso", "Atrasado", "")))) -> Concluido | D78: Estatal | E78: Secretaría del Campo | F78: Coordinación Administrativa | G78: 3000 Servicios generales | H78: 3300 – Servicios Profesionales, Científicos, Técnicos y Otros Servicios | I78: 3311 Servicios Profesionales, Científicos, Técnicos y Otros Servicios | J78: =IF(O78="","", IFERROR( IF(VALUE(SUBSTITUTE(SUBSTITUTE(TRIM(O78),"$",""),",",""))<=0,"", IF(VALUE(SUBSTITUTE(SUBSTITUTE(TRIM(O78),"$",""),",",""))<=580000,"CP", IF(VALUE(SUBSTITUTE(SUBSTITUTE(TRIM(O78),"$",""),",",""))<=1740000,"IRP","LPNP"))), "")) -> CP | K78: 72200 | L78: Concluido | M78: =IFERROR(IF(OR(VLOOKUP(A78,Adjudicacion!A:N,14,0)=0, VLOOKUP(A78,Adjudicacion!A:N,14,0)=""), L78, VLOOKUP(A78,Adjudicacion!A:N,14,0)), L78) -> Concluido | N78: Servicio- Contratacion de servicios generales | O78: 75000 | P78: SERVICIO PROFESIONAL DE AUDITORÍA EXTERNA PARA REALIZAR TRABAJOS DE REVISIÓN, ANÁLISIS Y DICTAMINACIÓN DE ESTADOS FINANCIEROS DEL FIDEICOMISO FONDO ALIANZA PARA EL CAMPO DEL ESTADO DE MÉXICO (FACEM) | Q78: NO
A79: S068 | B79: 46069 | C79: =IF(L79="Rechazado", "Rechazado", IF(L79="Concluido", "Concluido", IF(AND(L79="En Proceso", TODAY()<=WORKDAY(B79,15)), "En Tiempo", IF(L79="En Proceso", "Atrasado", "")))) -> Concluido | D79: Estatal | E79: Secretaría de Cultura y Turismo | F79: Coordinación Administrativa | G79: 2000 Materiales y Suministros | H79: 2400 – Materiales y Artículos de Construcción y de Reparación | I79: 2441 Madera y productos de madera | J79: =IF(O79="","", IFERROR( IF(VALUE(SUBSTITUTE(SUBSTITUTE(TRIM(O79),"$",""),",",""))<=0,"", IF(VALUE(SUBSTITUTE(SUBSTITUTE(TRIM(O79),"$",""),",",""))<=580000,"CP", IF(VALUE(SUBSTITUTE(SUBSTITUTE(TRIM(O79),"$",""),",",""))<=1740000,"IRP","LPNP"))), "")) -> IRP | K79: 13,374.28 | L79: Concluido | M79: =IFERROR(IF(OR(VLOOKUP(A79,Adjudicacion!A:N,14,0)=0, VLOOKUP(A79,Adjudicacion!A:N,14,0)=""), L79, VLOOKUP(A79,Adjudicacion!A:N,14,0)), L79) -> Concluido | N79: Bien- Adquisición de materiales y suministros | O79: =368880+30000+117770+70000 -> 586650 | P79: VIGA DE MADERA DE PINO (10 POR 20 CENTÍMETROS) TABLA DE MADERA DE PINO (30 CENTÍMETROS POR 2.5 METROS) DECK DE MADERA DE TECA (9 CENTÍMETROS POR 1.20 METROS) DECK DE MADERA CUMARÚ (9 CENTÍMETROS POR 1.20 METROS) DUELA DE MADERA DE ENCINO AMERICANO (6 POR 90 CENTÍMETROS) DUELA DE MADERA DE ENCINO AMERICANO (7 POR 90 CENTÍMETROS) DUELA DE MADERA DE ENCINO NACIONAL (7 POR 90 CENTÍMETROS) | Q79: NO
A80: S069 | B80: 46069 | C80: =IF(L80="Rechazado", "Rechazado", IF(L80="Concluido", "Concluido", IF(AND(L80="En Proceso", TODAY()<=WORKDAY(B80,15)), "En Tiempo", IF(L80="En Proceso", "Atrasado", "")))) -> Concluido | D80: Estatal | E80: Secretaría de Cultura y Turismo | F80: Coordinación Administrativa | G80: 3000 Servicios generales | H80: 3800 – Servicios Oficiales | I80: 3821 Gastos de ceremonias oficiales y de orden social | J80: =IF(O80="","", IFERROR( IF(VALUE(SUBSTITUTE(SUBSTITUTE(TRIM(O80),"$",""),",",""))<=0,"", IF(VALUE(SUBSTITUTE(SUBSTITUTE(TRIM(O80),"$",""),",",""))<=580000,"CP", IF(VALUE(SUBSTITUTE(SUBSTITUTE(TRIM(O80),"$",""),",",""))<=1740000,"IRP","LPNP"))), "")) -> CP | K80: 174,333.33 | L80: Concluido | M80: =IFERROR(IF(OR(VLOOKUP(A80,Adjudicacion!A:N,14,0)=0, VLOOKUP(A80,Adjudicacion!A:N,14,0)=""), L80, VLOOKUP(A80,Adjudicacion!A:N,14,0)), L80) -> Concluido | N80: Servicio- Contratacion de servicios generales | O80: 175000 | P80: CONTRATACIÓN DE EQUIPO DE SONIDO PARA EL “FESTIVAL CULTURAL QUINTO SOL, EN SU EDICIÓN XXXIX”. | Q80: NO
A81: S070 | B81: 46069 | C81: =IF(L81="Rechazado", "Rechazado", IF(L81="Concluido", "Concluido", IF(AND(L81="En Proceso", TODAY()<=WORKDAY(B81,15)), "En Tiempo", IF(L81="En Proceso", "Atrasado", "")))) -> Concluido | D81: Estatal | E81: Secretaría de Cultura y Turismo | F81: Coordinación Administrativa | G81: 3000 Servicios generales | H81: 3300 – Servicios Profesionales, Científicos, Técnicos y Otros Servicios | I81: 3363 Servicios de impresión de documentos oficiales | J81: =IF(O81="","", IFERROR( IF(VALUE(SUBSTITUTE(SUBSTITUTE(TRIM(O81),"$",""),",",""))<=0,"", IF(VALUE(SUBSTITUTE(SUBSTITUTE(TRIM(O81),"$",""),",",""))<=580000,"CP", IF(VALUE(SUBSTITUTE(SUBSTITUTE(TRIM(O81),"$",""),",",""))<=1740000,"IRP","LPNP"))), "")) -> CP | K81: 5,339.30 | L81: Concluido | M81: =IFERROR(IF(OR(VLOOKUP(A81,Adjudicacion!A:N,14,0)=0, VLOOKUP(A81,Adjudicacion!A:N,14,0)=""), L81, VLOOKUP(A81,Adjudicacion!A:N,14,0)), L81) -> Concluido | N81: Servicio- Contratacion de servicios generales | O81: 76500 | P81: IMPRESIÓN DE CARTEL PARA EL FESTIVAL CULTURAL QUINTO SOL, EN SU EDICIÓN XXXIX. IMPRESIÓN DE LONA PARA EL FESTIVAL CULTURAL QUINTO SOL, EN SU EDICIÓN XXXIX. IMPRESIÓN DE BANNER PARA EL FESTIVAL CULTURAL QUINTO SOL, EN SU EDICIÓN XXXIX. IMPRESIÓN DE GAFETE “STAFF” PARA EL FESTIVAL CULTURAL QUINTO SOL, EN SU EDICIÓN XXXIX. IMPRESIÓN DE GAFETE “PARTICIPANTE” PARA EL FESTIVAL CULTURAL QUINTO SOL, EN SU EDICIÓN XXXIX. | Q81: NO
A82: S071 | B82: 46069 | C82: =IF(L82="Rechazado", "Rechazado", IF(L82="Concluido", "Concluido", IF(AND(L82="En Proceso", TODAY()<=WORKDAY(B82,15)), "En Tiempo", IF(L82="En Proceso", "Atrasado", "")))) -> Concluido | D82: Estatal | E82: Secretaría de Cultura y Turismo | F82: Coordinación Administrativa | G82: 3000 Servicios generales | H82: 3800 – Servicios Oficiales | I82: 3821 Gastos de ceremonias oficiales y de orden social | J82: =IF(O82="","", IFERROR( IF(VALUE(SUBSTITUTE(SUBSTITUTE(TRIM(O82),"$",""),",",""))<=0,"", IF(VALUE(SUBSTITUTE(SUBSTITUTE(TRIM(O82),"$",""),",",""))<=580000,"CP", IF(VALUE(SUBSTITUTE(SUBSTITUTE(TRIM(O82),"$",""),",",""))<=1740000,"IRP","LPNP"))), "")) -> CP | K82: 206.40 | L82: Concluido | M82: =IFERROR(IF(OR(VLOOKUP(A82,Adjudicacion!A:N,14,0)=0, VLOOKUP(A82,Adjudicacion!A:N,14,0)=""), L82, VLOOKUP(A82,Adjudicacion!A:N,14,0)), L82) -> Concluido | N82: Servicio- Contratacion de servicios generales | O82: =73562+73560+73560+73560+73560 -> 367802 | P82: SERVICIO DE BOX LUNCH DE LA TEMPORADA DE CONCIERTOS 154 DE LA ORQUESTA SINFÓNICA DEL ESTADO DE MÉXICO Y LA TEMPORADA 17 DE LA ORQUESTA FILARMÓNICA DEL ESTADO DE MÉXICO. | Q82: NO
A83: S072 | B83: 46069 | C83: =IF(L83="Rechazado", "Rechazado", IF(L83="Concluido", "Concluido", IF(AND(L83="En Proceso", TODAY()<=WORKDAY(B83,15)), "En Tiempo", IF(L83="En Proceso", "Atrasado", "")))) -> Concluido | D83: Estatal | E83: Consejería Jurídica | F83: Coordinación Administrativa (23300001000000S) | G83: 5000 Bienes muebles inmuebles e intangibles | H83: 5400 – Vehículos y Equipo de Transporte | I83: 5411 Vehículos y equipo de transporte terrestre | J83: =IF(O83="","", IFERROR( IF(VALUE(SUBSTITUTE(SUBSTITUTE(TRIM(O83),"$",""),",",""))<=0,"", IF(VALUE(SUBSTITUTE(SUBSTITUTE(TRIM(O83),"$",""),",",""))<=580000,"CP", IF(VALUE(SUBSTITUTE(SUBSTITUTE(TRIM(O83),"$",""),",",""))<=1740000,"IRP","LPNP"))), "")) -> LPNP | K83: 1,095,074.50 | L83: Concluido | M83: =IFERROR(IF(OR(VLOOKUP(A83,Adjudicacion!A:N,14,0)=0, VLOOKUP(A83,Adjudicacion!A:N,14,0)=""), L83, VLOOKUP(A83,Adjudicacion!A:N,14,0)), L83) -> Concluido | N83: Bien- Adquisición de materiales y suministros | O83: 7157349 | P83: VEHÍCULO TIPO SEDÁN 2026 CAMIONETA TIPO VAN 2026 | Q83: NO
A84: S073 | B84: 46069 | C84: =IF(L84="Rechazado", "Rechazado", IF(L84="Concluido", "Concluido", IF(AND(L84="En Proceso", TODAY()<=WORKDAY(B84,15)), "En Tiempo", IF(L84="En Proceso", "Atrasado", "")))) -> Rechazado | D84: Estatal | E84: Secretaría de las Mujeres | F84: Coordinación Administrativa | G84: 2000 Materiales y Suministros | H84: 2200 – Alimentos y Utensilios | I84: 2211 Productos alimenticios para personas | J84: =IF(O84="","", IFERROR( IF(VALUE(SUBSTITUTE(SUBSTITUTE(TRIM(O84),"$",""),",",""))<=0,"", IF(VALUE(SUBSTITUTE(SUBSTITUTE(TRIM(O84),"$",""),",",""))<=580000,"CP", IF(VALUE(SUBSTITUTE(SUBSTITUTE(TRIM(O84),"$",""),",",""))<=1740000,"IRP","LPNP"))), "")) -> LPNP | K84: 0 | L84: Rechazado | M84: =IFERROR(IF(OR(VLOOKUP(A84,Adjudicacion!A:N,14,0)=0, VLOOKUP(A84,Adjudicacion!A:N,14,0)=""), L84, VLOOKUP(A84,Adjudicacion!A:N,14,0)), L84) -> Rechazado | N84: Bien- Adquisición de materiales y suministros | O84: 4518775 | P84: SUMINISTRO DE ABARROTES Y ALIMENTOS PARA LOS REFUGIOS DE LAS MUJERES EN SITUACIÓN DE VIOLENCIA. | Q84: NO
A85: S074 | B85: 46069 | C85: =IF(L85="Rechazado", "Rechazado", IF(L85="Concluido", "Concluido", IF(AND(L85="En Proceso", TODAY()<=WORKDAY(B85,15)), "En Tiempo", IF(L85="En Proceso", "Atrasado", "")))) -> Concluido | D85: Estatal | E85: Secretaría de las Mujeres | F85: Coordinación Administrativa | G85: 3000 Servicios generales | H85: 3100 – Servicios Básicos | I85: 3121 Gas | J85: =IF(O85="","", IFERROR( IF(VALUE(SUBSTITUTE(SUBSTITUTE(TRIM(O85),"$",""),",",""))<=0,"", IF(VALUE(SUBSTITUTE(SUBSTITUTE(TRIM(O85),"$",""),",",""))<=580000,"CP", IF(VALUE(SUBSTITUTE(SUBSTITUTE(TRIM(O85),"$",""),",",""))<=1740000,"IRP","LPNP"))), "")) -> CP | K85: 10.34 | L85: Concluido | M85: =IFERROR(IF(OR(VLOOKUP(A85,Adjudicacion!A:N,14,0)=0, VLOOKUP(A85,Adjudicacion!A:N,14,0)=""), L85, VLOOKUP(A85,Adjudicacion!A:N,14,0)), L85) -> Concluido | N85: Servicio- Contratacion de servicios generales | O85: 322366.39 | P85: SUMINISTRO DE GAS L.P. PARA LOS CENTROS LIBRE DE LA SECRETARIA DE LAS MUJERES | Q85: NO
A86: S075 | B86: 46069 | C86: =IF(L86="Rechazado", "Rechazado", IF(L86="Concluido", "Concluido", IF(AND(L86="En Proceso", TODAY()<=WORKDAY(B86,15)), "En Tiempo", IF(L86="En Proceso", "Atrasado", "")))) -> Rechazado | D86: Estatal | E86: Secretaría de las Mujeres | F86: Coordinación Administrativa | G86: 3000 Servicios generales | H86: 3500 – Servicios de Instalación, Reparación, Mantenimiento y Conservación | I86: 3571 Reparación, instalación y mantenimiento de maquinaria, equipo industrial y diverso | J86: =IF(O86="","", IFERROR( IF(VALUE(SUBSTITUTE(SUBSTITUTE(TRIM(O86),"$",""),",",""))<=0,"", IF(VALUE(SUBSTITUTE(SUBSTITUTE(TRIM(O86),"$",""),",",""))<=580000,"CP", IF(VALUE(SUBSTITUTE(SUBSTITUTE(TRIM(O86),"$",""),",",""))<=1740000,"IRP","LPNP"))), "")) -> CP | K86: 0 | L86: Rechazado | M86: =IFERROR(IF(OR(VLOOKUP(A86,Adjudicacion!A:N,14,0)=0, VLOOKUP(A86,Adjudicacion!A:N,14,0)=""), L86, VLOOKUP(A86,Adjudicacion!A:N,14,0)), L86) -> Rechazado | N86: Servicio- Contratacion de servicios generales | O86: 381784.88 | P86: MANTENIMIENTO PREVENTIVO Y CORRECTIVO PARA ELEVADOR DE LA SECRETARÍA DE LAS MUJERES | Q86: NO
A87: S076 | B87: 46069 | C87: =IF(L87="Rechazado", "Rechazado", IF(L87="Concluido", "Concluido", IF(AND(L87="En Proceso", TODAY()<=WORKDAY(B87,15)), "En Tiempo", IF(L87="En Proceso", "Atrasado", "")))) -> Rechazado | D87: Estatal | E87: Secretaría de las Mujeres | F87: Coordinación Administrativa | G87: 3000 Servicios generales | H87: 3300 – Servicios Profesionales, Científicos, Técnicos y Otros Servicios | I87: 3311 Asesorías asociadas a convenios o acuerdos | J87: =IF(O87="","", IFERROR( IF(VALUE(SUBSTITUTE(SUBSTITUTE(TRIM(O87),"$",""),",",""))<=0,"", IF(VALUE(SUBSTITUTE(SUBSTITUTE(TRIM(O87),"$",""),",",""))<=580000,"CP", IF(VALUE(SUBSTITUTE(SUBSTITUTE(TRIM(O87),"$",""),",",""))<=1740000,"IRP","LPNP"))), "")) -> CP | K87: 0 | L87: Rechazado | M87: =IFERROR(IF(OR(VLOOKUP(A87,Adjudicacion!A:N,14,0)=0, VLOOKUP(A87,Adjudicacion!A:N,14,0)=""), L87, VLOOKUP(A87,Adjudicacion!A:N,14,0)), L87) -> Rechazado | N87: Servicio- Contratacion de servicios generales | O87: 163000 | P87: ASESORÍA Y REVISIÓN DE LOS PROCESOS DE NÓMINA RELATIVOS AL PERSONAL POR CONTRATO INDIVIDUAL DE TRABAJO POR TIEMPO DETERMINADO | Q87: NO
A88: S077 | B88: 46069 | C88: =IF(L88="Rechazado", "Rechazado", IF(L88="Concluido", "Concluido", IF(AND(L88="En Proceso", TODAY()<=WORKDAY(B88,15)), "En Tiempo", IF(L88="En Proceso", "Atrasado", "")))) -> Rechazado | D88: Estatal | E88: Secretaría de las Mujeres | F88: Coordinación Administrativa | G88: 3000 Servicios generales | H88: 3700 – Servicios de Traslado y Viáticos | I88: 3791 Otros servicios de traslado y hospedaje | J88: =IF(O88="","", IFERROR( IF(VALUE(SUBSTITUTE(SUBSTITUTE(TRIM(O88),"$",""),",",""))<=0,"", IF(VALUE(SUBSTITUTE(SUBSTITUTE(TRIM(O88),"$",""),",",""))<=580000,"CP", IF(VALUE(SUBSTITUTE(SUBSTITUTE(TRIM(O88),"$",""),",",""))<=1740000,"IRP","LPNP"))), "")) -> IRP | K88: 0 | L88: Rechazado | M88: =IFERROR(IF(OR(VLOOKUP(A88,Adjudicacion!A:N,14,0)=0, VLOOKUP(A88,Adjudicacion!A:N,14,0)=""), L88, VLOOKUP(A88,Adjudicacion!A:N,14,0)), L88) -> Rechazado | N88: Servicio- Contratacion de servicios generales | O88: =173340+577800 -> 751140 | P88: SERVICIO DE ESTACIONAMIENTO | Q88: NO
A89: S078 | B89: 46069 | C89: =IF(L89="Rechazado", "Rechazado", IF(L89="Concluido", "Concluido", IF(AND(L89="En Proceso", TODAY()<=WORKDAY(B89,15)), "En Tiempo", IF(L89="En Proceso", "Atrasado", "")))) -> Rechazado | D89: Estatal | E89: Secretaría de las Mujeres | F89: Coordinación Administrativa | G89: 3000 Servicios generales | H89: 3900 – Otros Servicios Generales | I89: 3992 Gastos y servicios menores | J89: =IF(O89="","", IFERROR( IF(VALUE(SUBSTITUTE(SUBSTITUTE(TRIM(O89),"$",""),",",""))<=0,"", IF(VALUE(SUBSTITUTE(SUBSTITUTE(TRIM(O89),"$",""),",",""))<=580000,"CP", IF(VALUE(SUBSTITUTE(SUBSTITUTE(TRIM(O89),"$",""),",",""))<=1740000,"IRP","LPNP"))), "")) -> CP | K89: 0 | L89: Rechazado | M89: =IFERROR(IF(OR(VLOOKUP(A89,Adjudicacion!A:N,14,0)=0, VLOOKUP(A89,Adjudicacion!A:N,14,0)=""), L89, VLOOKUP(A89,Adjudicacion!A:N,14,0)), L89) -> Rechazado | N89: Servicio- Contratacion de servicios generales | O89: 200000 | P89: SUMINISTRO DE GARRAFÓN DE AGUA | Q89: NO
